Workbook

Sheet turkey_rental_multiplier
A1: FB010 | B1: cpi_rent | C1: cpi_rent_growth | D1: cpi_2003_100 | E1: inflation | F1: house_price_index_2023100 | G1: house_price_growth | H1: sahibinden_rental_turkiye | I1: sahibinden_kondeger_turkiye | J1: hba_rental_val_original | K1: price_to_rent_sahibinden2 | L1: silc_mean_imputed_rent | M1: imprent_correction | N1: imprent_upgrade_factor
A2: 2003 | B2: 100 | C2: =(B3-B2)/B2 -> 0.4132 | D2: 100 | E2: =(D3-D2)/D2 -> 0.14485579
A3: 2005 | B3: =cpi_june!E2 -> 141.32 | C3: =(B4-B3)/B3 -> 0.20209454 | D3: 114.48558 | E3: =(D4-D3)/D3 -> 0.079349911 | G3: =(J4-J3)/J3 -> 0.38559669 | H3: =H4/(1+C3) -> 299.41989 | I3: =I4/(1+G3) -> 43985.333 | J3: 32667.76 | K3: =I3/H3 -> 146.90184 | N3: =AVERAGE(M5:M20) -> 2.6537759
A4: 2006 | B4: =cpi_june!E3 -> 169.88 | C4: =(B5-B4)/B4 -> 0.19443136 | D4: 123.57 | E4: =(D5-D4)/D4 -> 0.099295946 | G4: =(J5-J4)/J4 -> 0.1387547 | H4: =H5/(1+C4) -> 359.93102 | I4: =I5/(1+G4) -> 60945.931 | J4: 45264.34 | K4: =I4/H4 -> 169.3267 | N4: =N3 -> 2.6537759
A5: 2007 | B5: =cpi_june!E4 -> 202.91 | C5: =(B6-B5)/B5 -> 0.14070277 | D5: 135.84 | E5: =(D6-D5)/D5 -> 0.081713781 | G5: =(J6-J5)/J5 -> 0.19879298 | H5: =H6/(1+C5) -> 429.9129 | I5: =I6/(1+G5) -> 69402.466 | J5: 51544.98 | K5: =I5/H5 -> 161.43378 | L5: 1933.1638 | M5: =((H5*12)/L5) -> 2.6686589 | N5: =N3 -> 2.6537759
A6: 2008 | B6: =cpi_june!E5 -> 231.46 | C6: =(B7-B6)/B6 -> 0.087358507 | D6: 146.94 | E6: =(D7-D6)/D6 -> 0.095004764 | G6: =(J7-J6)/J6 -> -0.047355505 | H6: =H7/(1+C6) -> 490.40284 | I6: =I7/(1+G6) -> 83199.188 | J6: 61791.76 | K6: =I6/H6 -> 169.65479 | L6: 2189.0355 | M6: =((H6*12)/L6) -> 2.6883228 | N6: =N5 -> 2.6537759
A7: 2009 | B7: =cpi_june!E6 -> 251.68 | C7: =(B8-B7)/B7 -> 0.042116974 | D7: 160.9 | E7: =(D8-D7)/D7 -> 0.081852082 | G7: =(J8-J7)/J7 -> 0.067783924 | H7: =H8/(1+C7) -> 533.2437 | I7: =I8/(1+G7) -> 79259.249 | J7: 58865.58 | K7: =I7/H7 -> 148.63607 | L7: 2470.1196 | M7: =((H7*12)/L7) -> 2.5905322 | N7: =N6 -> 2.6537759
A8: 2010 | B8: =cpi_june!E7 -> 262.28 | C8: =(B9-B8)/B8 -> 0.04426567 | D8: 174.07 | E8: =(D9-D8)/D8 -> 0.049003275 | G8: =(J9-J8)/J8 -> 0.16124976 | H8: =H9/(1+C8) -> 555.70231 | I8: =I9/(1+G8) -> 84631.752 | J8: 62855.72 | K8: =I8/H8 -> 152.29692 | L8: 2687.2122 | M8: =((H8*12)/L8) -> 2.4815411 | N8: =N7 -> 2.6537759
A9: 2011 | B9: =cpi_june!E8 -> 273.89 | C9: =(B10-B9)/B9 -> 0.048048487 | D9: 182.6 | E9: =(D10-D9)/D9 -> 0.10613363 | G9: =(J10-J9)/J9 -> 0.15173872 | H9: =H10/(1+C9) -> 580.30084 | I9: =I10/(1+G9) -> 98278.602 | J9: 72991.19 | K9: =I9/H9 -> 169.35802 | L9: 2715.1743 | M9: =((H9*12)/L9) -> 2.564701 | N9: =N8 -> 2.6537759
A10: 2012 | B10: =cpi_june!E9 -> 287.05 | C10: =(B11-B10)/B10 -> 0.061661731 | D10: 201.98 | E10: =(D11-D10)/D10 -> 0.073076542 | F10: =house_price_index_evds!C9 -> 5.67 | G10: =(F11-F10)/F10 -> 0.11287478 | H10: =H11/(1+C10) -> 608.18342 | I10: =I11/(1+G10) -> 113191.27 | J10: 84066.78 | K10: =I10/H10 -> 186.11371 | L10: 2644.7564 | M10: =((H10*12)/L10) -> 2.7594984 | N10: =N9 -> 2.6537759
A11: 2013 | B11: =cpi_june!E10 -> 304.75 | C11: =(B12-B11)/B11 -> 0.06802297 | D11: 216.74 | E11: =(D12-D11)/D11 -> 0.077512227 | F11: =house_price_index_evds!C10 -> 6.31 | G11: =(F12-F11)/F11 -> 0.1251981 | H11: =H12/(1+C11) -> 645.68506 | I11: =I12/(1+G11) -> 125967.71 | J11: 87101.62 | K11: =I11/H11 -> 195.09157 | L11: 2733.4253 | M11: =((H11*12)/L11) -> 2.8346195 | N11: =N10 -> 2.6537759
A12: 2014 | B12: =cpi_june!E11 -> 325.48 | C12: =(B13-B12)/B12 -> 0.074658965 | D12: 233.54 | E12: =(D13-D12)/D12 -> 0.072407296 | F12: =house_price_index_evds!C11 -> 7.1 | G12: =(F13-F12)/F12 -> 0.15774648 | H12: =H13/(1+C12) -> 689.60648 | I12: =I13/(1+G12) -> 141738.63 | J12: 106254.9 | K12: =I12/H12 -> 205.53552 | L12: 3179.6084 | M12: =((H12*12)/L12) -> 2.6026091 | N12: =N11 -> 2.6537759
A13: 2015 | B13: =cpi_june!E12 -> 349.78 | C13: =(B14-B13)/B13 -> 0.088284064 | D13: 250.45 | E13: =(D14-D13)/D13 -> 0.095787582 | F13: =house_price_index_evds!C12 -> 8.22 | G13: =(F14-F13)/F13 -> 0.12773723 | H13: =H14/(1+C13) -> 741.09178 | I13: =I14/(1+G13) -> 164097.4 | J13: =J12*(1+G12) -> 123016.24 | K13: =I13/H13 -> 221.42655 | L13: 3467.6421 | M13: =((H13*12)/L13) -> 2.5645961 | N13: =N12 -> 2.6537759
A14: 2016 | B14: =cpi_june!E13 -> 380.66 | C14: =(B15-B14)/B14 -> 0.088110125 | D14: 274.44 | E14: =(D15-D14)/D14 -> 0.092187728 | F14: =house_price_index_evds!C13 -> 9.27 | G14: =(F15-F14)/F14 -> 0.10895361 | H14: =H15/(1+C14) -> 806.51838 | I14: =I15/(1+G14) -> 185058.75 | J14: =J13*(1+G13) -> 138729.99 | K14: =I14/H14 -> 229.45385 | L14: 3261.4627 | M14: =((H14*12)/L14) -> 2.9674478 | N14: =N13 -> 2.6537759
A15: 2017 | B15: =cpi_june!E14 -> 414.2 | C15: =(B16-B15)/B15 -> 0.096185418 | D15: 299.74 | E15: =(D16-D15)/D15 -> 0.10345633 | F15: =house_price_index_evds!C14 -> 10.28 | G15: =(F16-F15)/F15 -> 0.077821012 | H15: =H16/(1+C15) -> 877.58081 | I15: =I16/(1+G15) -> 205221.56 | J15: =J14*(1+G14) -> 153845.12 | K15: =I15/H15 -> 233.84919 | L15: 3643.9959 | M15: =((H15*12)/L15) -> 2.889951 | N15: =N14 -> 2.6537759
A16: 2018 | B16: =cpi_june!E15 -> 454.04 | C16: =(B17-B16)/B16 -> 0.10201744 | D16: 330.75 | E16: =(D17-D16)/D16 -> 0.20353741 | F16: =house_price_index_evds!C15 -> 11.08 | G16: =(F17-F16)/F16 -> 0.047833935 | H16: =H17/(1+C16) -> 961.99129 | I16: =I17/(1+G16) -> 221192.11 | J16: =J15*(1+G15) -> 165817.51 | K16: =I16/H16 -> 229.93151 | L16: 4555.434 | M16: =((H16*12)/L16) -> 2.5340935 | N16: =N15 -> 2.6537759
A17: 2019 | B17: =cpi_june!E16 -> 500.36 | C17: =(B18-B17)/B17 -> 0.092193621 | D17: 398.07 | E17: =(D18-D17)/D17 -> 0.12153641 | F17: =house_price_index_evds!C16 -> 11.61 | G17: =(F18-F17)/F17 -> 0.23858742 | H17: =H18/(1+C17) -> 1060.1312 | I17: =I18/(1+G17) -> 231772.6 | J17: =J16*(1+G16) -> 173749.21 | K17: =I17/H17 -> 218.62634 | L17: 5267.3189 | M17: =((H17*12)/L17) -> 2.4151897 | N17: =N16 -> 2.6537759
A18: 2020 | B18: =cpi_june!E17 -> 546.49 | C18: =(B19-B18)/B18 -> 0.09934308 | D18: 446.45 | E18: =(D19-D18)/D18 -> 0.14973681 | F18: =house_price_index_evds!C17 -> 14.38 | G18: =(F19-F18)/F18 -> 0.37482615 | H18: =H19/(1+C18) -> 1157.8685 | I18: =I19/(1+G18) -> 287070.63 | J18: =J17*(1+G17) -> 215203.59 | K18: =I18/H18 -> 247.93025 | L18: 6054.6882 | M18: =((H18*12)/L18) -> 2.2948204 | N18: =N17 -> 2.6537759
A19: 2021 | B19: =cpi_june!E18 -> 600.78 | C19: =(B20-B19)/B19 -> 0.22798695 | D19: 513.3 | E19: =(D20-D19)/D19 -> 0.48690824 | F19: =house_price_index_evds!C18 -> 19.77 | G19: =(F20-F19)/F19 -> 1.4997471 | H19: =AVERAGE(sahibinden_rent_and_price_june!D2:D77) -> 1272.8947 | I19: =AVERAGE(sahibinden_rent_and_price_june!E2:E77) -> 394672.21 | J19: =J18*(1+G18) -> 295867.52 | K19: =I19/H19 -> 310.0588 | L19: 5524.0546 | M19: =((H19*12)/L19) -> 2.7651314 | N19: =N18 -> 2.6537759
A20: 2022 | B20: =cpi_june!E19 -> 737.75 | C20: =(B21-B20)/B20 -> 0.75905117 | D20: 763.23 | E20: =(D21-D20)/D20 -> -1 | F20: =house_price_index_evds!C19 -> 49.42 | G20: =(F21-F20)/F20 -> 1.0234723 | H20: =AVERAGE(sahibinden_rent_and_price_june!D78:D154) -> 3048.5584 | I20: =AVERAGE(sahibinden_rent_and_price_june!E78:E154) -> 1037824.9 | J20: =J19*(1+G19) -> 739593.97 | K20: =I20/H20 -> 340.43136 | L20: 12887.129 | M20: =((H20*12)/L20) -> 2.8387007 | N20: =N19 -> 2.6537759
A21: 2023 | B21: =cpi_june!E20 -> 1297.74 | F21: =house_price_index_evds!C20 -> 100

Sheet regional_rent_multiplier_ibbs1
A1: year | B1: TR1 | C1: TR2 | D1: TR2 | E1: TR3 | F1: TR3 | G1: TR3 | H1: TR4 | I1: TR4 | J1: TR5 | K1: TR5 | L1: TR6 | M1: TR6 | N1: TR6 | O1: TR7 | P1: TR7 | Q1: TR8 | R1: TR8 | S1: TR8 | T1: TR9 | U1: TRA | V1: TRA | W1: TRB | X1: TRB | Y1: TRC | Z1: TRC | AA1: TRC
A2: 2005 | B2: =regional_houseprice!B2/regional_rent!B2 -> 72.344727 | C2: =regional_houseprice!C2/regional_rent!C2 -> 141.27845 | D2: =regional_houseprice!D2/regional_rent!D2 -> 171.28356 | E2: =regional_houseprice!E2/regional_rent!E2 -> 101.86069 | F2: =regional_houseprice!F2/regional_rent!F2 -> 154.85707 | G2: =regional_houseprice!G2/regional_rent!G2 -> 215.14175 | H2: =regional_houseprice!H2/regional_rent!H2 -> 188.45544 | I2: =regional_houseprice!I2/regional_rent!I2 -> 167.29362 | ... AA2: =regional_houseprice!AA2/regional_rent!AA2 -> 162.03782
A3: 2006 | B3: =regional_houseprice!B3/regional_rent!B3 -> 88.244069 | C3: =regional_houseprice!C3/regional_rent!C3 -> 163.47107 | D3: =regional_houseprice!D3/regional_rent!D3 -> 196.99268 | E3: =regional_houseprice!E3/regional_rent!E3 -> 122.06012 | F3: =regional_houseprice!F3/regional_rent!F3 -> 181.86667 | G3: =regional_houseprice!G3/regional_rent!G3 -> 244.56266 | H3: =regional_houseprice!H3/regional_rent!H3 -> 216.46983 | I3: =regional_houseprice!I3/regional_rent!I3 -> 192.67698 | ... AA3: =regional_houseprice!AA3/regional_rent!AA3 -> 182.37351
A4: 2007 | B4: =regional_houseprice!B4/regional_rent!B4 -> 88.318031 | C4: =regional_houseprice!C4/regional_rent!C4 -> 156.26104 | D4: =regional_houseprice!D4/regional_rent!D4 -> 187.67356 | E4: =regional_houseprice!E4/regional_rent!E4 -> 120.72368 | F4: =regional_houseprice!F4/regional_rent!F4 -> 177.13106 | G4: =regional_houseprice!G4/regional_rent!G4 -> 229.89319 | H4: =regional_houseprice!H4/regional_rent!H4 -> 205.34512 | I4: =regional_houseprice!I4/regional_rent!I4 -> 182.8321 | ... AA4: =regional_houseprice!AA4/regional_rent!AA4 -> 171.09763
A5: 2008 | B5: =regional_houseprice!B5/regional_rent!B5 -> 95.900906 | C5: =regional_houseprice!C5/regional_rent!C5 -> 164.12365 | D5: =regional_houseprice!D5/regional_rent!D5 -> 197.79627 | E5: =regional_houseprice!E5/regional_rent!E5 -> 130.44532 | F5: =regional_houseprice!F5/regional_rent!F5 -> 190.53072 | G5: =regional_houseprice!G5/regional_rent!G5 -> 238.39037 | H5: =regional_houseprice!H5/regional_rent!H5 -> 214.50067 | I5: =regional_houseprice!I5/regional_rent!I5 -> 190.69971 | ... AA5: =regional_houseprice!AA5/regional_rent!AA5 -> 178.93848
A6: 2009 | B6: =regional_houseprice!B6/regional_rent!B6 -> 87.513829 | C6: =regional_houseprice!C6/regional_rent!C6 -> 143.71179 | D6: =regional_houseprice!D6/regional_rent!D6 -> 172.81974 | E6: =regional_houseprice!E6/regional_rent!E6 -> 116.40593 | F6: =regional_houseprice!F6/regional_rent!F6 -> 170.71461 | G6: =regional_houseprice!G6/regional_rent!G6 -> 202.47021 | H6: =regional_houseprice!H6/regional_rent!H6 -> 184.91821 | I6: =regional_houseprice!I6/regional_rent!I6 -> 165.95823 | ... AA6: =regional_houseprice!AA6/regional_rent!AA6 -> 155.42345
A7: 2010 | B7: =regional_houseprice!B7/regional_rent!B7 -> 91.546786 | C7: =regional_houseprice!C7/regional_rent!C7 -> 148.77009 | D7: =regional_houseprice!D7/regional_rent!D7 -> 177.37728 | E7: =regional_houseprice!E7/regional_rent!E7 -> 120.87767 | F7: =regional_houseprice!F7/regional_rent!F7 -> 178.62847 | G7: =regional_houseprice!G7/regional_rent!G7 -> 203.90278 | H7: =regional_houseprice!H7/regional_rent!H7 -> 187.06311 | I7: =regional_houseprice!I7/regional_rent!I7 -> 170.46734 | ... AA7: =regional_houseprice!AA7/regional_rent!AA7 -> 156.81242
A8: 2011 | B8: =regional_houseprice!B8/regional_rent!B8 -> 97.751697 | C8: =regional_houseprice!C8/regional_rent!C8 -> 151.79334 | D8: =regional_houseprice!D8/regional_rent!D8 -> 177.28729 | E8: =regional_houseprice!E8/regional_rent!E8 -> 127.32218 | F8: =regional_houseprice!F8/regional_rent!F8 -> 182.11795 | G8: =regional_houseprice!G8/regional_rent!G8 -> 213.59326 | H8: =regional_houseprice!H8/regional_rent!H8 -> 191.41597 | I8: =regional_houseprice!I8/regional_rent!I8 -> 171.61183 | ... AA8: =regional_houseprice!AA8/regional_rent!AA8 -> 173.16477
A9: 2012 | B9: =regional_houseprice!B9/regional_rent!B9 -> 105.03282 | C9: =regional_houseprice!C9/regional_rent!C9 -> 153.73982 | D9: =regional_houseprice!D9/regional_rent!D9 -> 180.178 | E9: =regional_houseprice!E9/regional_rent!E9 -> 133.17581 | F9: =regional_houseprice!F9/regional_rent!F9 -> 185.65176 | G9: =regional_houseprice!G9/regional_rent!G9 -> 231.63042 | H9: =regional_houseprice!H9/regional_rent!H9 -> 193.72735 | I9: =regional_houseprice!I9/regional_rent!I9 -> 170.79787 | ... AA9: =regional_houseprice!AA9/regional_rent!AA9 -> 198.02751
A10: 2013 | B10: =regional_houseprice!B10/regional_rent!B10 -> 115.04356 | C10: =regional_houseprice!C10/regional_rent!C10 -> 155.22667 | D10: =regional_houseprice!D10/regional_rent!D10 -> 181.41098 | E10: =regional_houseprice!E10/regional_rent!E10 -> 140.79586 | F10: =regional_houseprice!F10/regional_rent!F10 -> 193.07127 | G10: =regional_houseprice!G10/regional_rent!G10 -> 243.32644 | H10: =regional_houseprice!H10/regional_rent!H10 -> 197.21648 | I10: =regional_houseprice!I10/regional_rent!I10 -> 172.91073 | ... AA10: =regional_houseprice!AA10/regional_rent!AA10 -> 208.14704
A11: 2014 | B11: =regional_houseprice!B11/regional_rent!B11 -> 130.21703 | C11: =regional_houseprice!C11/regional_rent!C11 -> 158.88075 | D11: =regional_houseprice!D11/regional_rent!D11 -> 182.68561 | E11: =regional_houseprice!E11/regional_rent!E11 -> 148.56313 | F11: =regional_houseprice!F11/regional_rent!F11 -> 204.38014 | G11: =regional_houseprice!G11/regional_rent!G11 -> 246.45122 | H11: =regional_houseprice!H11/regional_rent!H11 -> 201.33402 | I11: =regional_houseprice!I11/regional_rent!I11 -> 179.60135 | ... AA11: =regional_houseprice!AA11/regional_rent!AA11 -> 211.03351
A12: 2015 | B12: =regional_houseprice!B12/regional_rent!B12 -> 153.21165 | C12: =regional_houseprice!C12/regional_rent!C12 -> 171.01123 | D12: =regional_houseprice!D12/regional_rent!D12 -> 196.29112 | E12: =regional_houseprice!E12/regional_rent!E12 -> 160.59099 | F12: =regional_houseprice!F12/regional_rent!F12 -> 226.83997 | G12: =regional_houseprice!G12/regional_rent!G12 -> 251.42392 | H12: =regional_houseprice!H12/regional_rent!H12 -> 209.00447 | I12: =regional_houseprice!I12/regional_rent!I12 -> 194.01714 | ... AA12: =regional_houseprice!AA12/regional_rent!AA12 -> 210.1368
A13: 2016 | B13: =regional_houseprice!B13/regional_rent!B13 -> 165.18042 | C13: =regional_houseprice!C13/regional_rent!C13 -> 189.07199 | D13: =regional_houseprice!D13/regional_rent!D13 -> 209.87709 | E13: =regional_houseprice!E13/regional_rent!E13 -> 171.13176 | F13: =regional_houseprice!F13/regional_rent!F13 -> 241.92428 | G13: =regional_houseprice!G13/regional_rent!G13 -> 251.52185 | H13: =regional_houseprice!H13/regional_rent!H13 -> 217.36631 | I13: =regional_houseprice!I13/regional_rent!I13 -> 210.21245 | ... AA13: =regional_houseprice!AA13/regional_rent!AA13 -> 199.7259
... A19: 2022 | B19: =regional_houseprice!B19/regional_rent!B19 -> 250.59744 | C19: =regional_houseprice!C19/regional_rent!C19 -> 325.44864 | D19: =regional_houseprice!D19/regional_rent!D19 -> 384.28207 | E19: =regional_houseprice!E19/regional_rent!E19 -> 264.37597 | F19: =regional_houseprice!F19/regional_rent!F19 -> 460.35379 | G19: =regional_houseprice!G19/regional_rent!G19 -> 368.66102 | H19: =regional_houseprice!H19/regional_rent!H19 -> 311.92446 | I19: =regional_houseprice!I19/regional_rent!I19 -> 306.59301 | ... AA19: =regional_houseprice!AA19/regional_rent!AA19 -> 399.9418

Sheet regional_rent_multiplier_ibbs2
A1: year | B1: TR1 | C1: TR21 | D1: TR22 | E1: TR31 | F1: TR32 | G1: TR33 | H1: TR41 | I1: TR42 | J1: TR51 | K1: TR52 | L1: TR61 | M1: TR62 | N1: TR63 | O1: TR71 | P1: TR72 | Q1: TR81 | R1: TR82 | S1: TR83 | T1: TR90 | U1: TRA1 | V1: TRA2 | W1: TRB1 | X1: TRB2 | Y1: TRC1 | Z1: TRC2 | AA1: TRC3
A2: 2005 | B2: =regional_houseprice!B2/regional_rent!B2 -> 72.344727 | C2: =regional_houseprice!C2/regional_rent!C2 -> 141.27845 | D2: =regional_houseprice!D2/regional_rent!D2 -> 171.28356 | E2: =regional_houseprice!E2/regional_rent!E2 -> 101.86069 | F2: =regional_houseprice!F2/regional_rent!F2 -> 154.85707 | G2: =regional_houseprice!G2/regional_rent!G2 -> 215.14175 | H2: =regional_houseprice!H2/regional_rent!H2 -> 188.45544 | I2: =regional_houseprice!I2/regional_rent!I2 -> 167.29362 | ... AA2: =regional_houseprice!AA2/regional_rent!AA2 -> 162.03782
A3: 2006 | B3: =regional_houseprice!B3/regional_rent!B3 -> 88.244069 | C3: =regional_houseprice!C3/regional_rent!C3 -> 163.47107 | D3: =regional_houseprice!D3/regional_rent!D3 -> 196.99268 | E3: =regional_houseprice!E3/regional_rent!E3 -> 122.06012 | F3: =regional_houseprice!F3/regional_rent!F3 -> 181.86667 | G3: =regional_houseprice!G3/regional_rent!G3 -> 244.56266 | H3: =regional_houseprice!H3/regional_rent!H3 -> 216.46983 | I3: =regional_houseprice!I3/regional_rent!I3 -> 192.67698 | ... AA3: =regional_houseprice!AA3/regional_rent!AA3 -> 182.37351
A4: 2007 | B4: =regional_houseprice!B4/regional_rent!B4 -> 88.318031 | C4: =regional_houseprice!C4/regional_rent!C4 -> 156.26104 | D4: =regional_houseprice!D4/regional_rent!D4 -> 187.67356 | E4: =regional_houseprice!E4/regional_rent!E4 -> 120.72368 | F4: =regional_houseprice!F4/regional_rent!F4 -> 177.13106 | G4: =regional_houseprice!G4/regional_rent!G4 -> 229.89319 | H4: =regional_houseprice!H4/regional_rent!H4 -> 205.34512 | I4: =regional_houseprice!I4/regional_rent!I4 -> 182.8321 | ... AA4: =regional_houseprice!AA4/regional_rent!AA4 -> 171.09763
A5: 2008 | B5: =regional_houseprice!B5/regional_rent!B5 -> 95.900906 | C5: =regional_houseprice!C5/regional_rent!C5 -> 164.12365 | D5: =regional_houseprice!D5/regional_rent!D5 -> 197.79627 | E5: =regional_houseprice!E5/regional_rent!E5 -> 130.44532 | F5: =regional_houseprice!F5/regional_rent!F5 -> 190.53072 | G5: =regional_houseprice!G5/regional_rent!G5 -> 238.39037 | H5: =regional_houseprice!H5/regional_rent!H5 -> 214.50067 | I5: =regional_houseprice!I5/regional_rent!I5 -> 190.69971 | ... AA5: =regional_houseprice!AA5/regional_rent!AA5 -> 178.93848
A6: 2009 | B6: =regional_houseprice!B6/regional_rent!B6 -> 87.513829 | C6: =regional_houseprice!C6/regional_rent!C6 -> 143.71179 | D6: =regional_houseprice!D6/regional_rent!D6 -> 172.81974 | E6: =regional_houseprice!E6/regional_rent!E6 -> 116.40593 | F6: =regional_houseprice!F6/regional_rent!F6 -> 170.71461 | G6: =regional_houseprice!G6/regional_rent!G6 -> 202.47021 | H6: =regional_houseprice!H6/regional_rent!H6 -> 184.91821 | I6: =regional_houseprice!I6/regional_rent!I6 -> 165.95823 | ... AA6: =regional_houseprice!AA6/regional_rent!AA6 -> 155.42345
A7: 2010 | B7: =regional_houseprice!B7/regional_rent!B7 -> 91.546786 | C7: =regional_houseprice!C7/regional_rent!C7 -> 148.77009 | D7: =regional_houseprice!D7/regional_rent!D7 -> 177.37728 | E7: =regional_houseprice!E7/regional_rent!E7 -> 120.87767 | F7: =regional_houseprice!F7/regional_rent!F7 -> 178.62847 | G7: =regional_houseprice!G7/regional_rent!G7 -> 203.90278 | H7: =regional_houseprice!H7/regional_rent!H7 -> 187.06311 | I7: =regional_houseprice!I7/regional_rent!I7 -> 170.46734 | ... AA7: =regional_houseprice!AA7/regional_rent!AA7 -> 156.81242
A8: 2011 | B8: =regional_houseprice!B8/regional_rent!B8 -> 97.751697 | C8: =regional_houseprice!C8/regional_rent!C8 -> 151.79334 | D8: =regional_houseprice!D8/regional_rent!D8 -> 177.28729 | E8: =regional_houseprice!E8/regional_rent!E8 -> 127.32218 | F8: =regional_houseprice!F8/regional_rent!F8 -> 182.11795 | G8: =regional_houseprice!G8/regional_rent!G8 -> 213.59326 | H8: =regional_houseprice!H8/regional_rent!H8 -> 191.41597 | I8: =regional_houseprice!I8/regional_rent!I8 -> 171.61183 | ... AA8: =regional_houseprice!AA8/regional_rent!AA8 -> 173.16477
A9: 2012 | B9: =regional_houseprice!B9/regional_rent!B9 -> 105.03282 | C9: =regional_houseprice!C9/regional_rent!C9 -> 153.73982 | D9: =regional_houseprice!D9/regional_rent!D9 -> 180.178 | E9: =regional_houseprice!E9/regional_rent!E9 -> 133.17581 | F9: =regional_houseprice!F9/regional_rent!F9 -> 185.65176 | G9: =regional_houseprice!G9/regional_rent!G9 -> 231.63042 | H9: =regional_houseprice!H9/regional_rent!H9 -> 193.72735 | I9: =regional_houseprice!I9/regional_rent!I9 -> 170.79787 | ... AA9: =regional_houseprice!AA9/regional_rent!AA9 -> 198.02751
A10: 2013 | B10: =regional_houseprice!B10/regional_rent!B10 -> 115.04356 | C10: =regional_houseprice!C10/regional_rent!C10 -> 155.22667 | D10: =regional_houseprice!D10/regional_rent!D10 -> 181.41098 | E10: =regional_houseprice!E10/regional_rent!E10 -> 140.79586 | F10: =regional_houseprice!F10/regional_rent!F10 -> 193.07127 | G10: =regional_houseprice!G10/regional_rent!G10 -> 243.32644 | H10: =regional_houseprice!H10/regional_rent!H10 -> 197.21648 | I10: =regional_houseprice!I10/regional_rent!I10 -> 172.91073 | ... AA10: =regional_houseprice!AA10/regional_rent!AA10 -> 208.14704
A11: 2014 | B11: =regional_houseprice!B11/regional_rent!B11 -> 130.21703 | C11: =regional_houseprice!C11/regional_rent!C11 -> 158.88075 | D11: =regional_houseprice!D11/regional_rent!D11 -> 182.68561 | E11: =regional_houseprice!E11/regional_rent!E11 -> 148.56313 | F11: =regional_houseprice!F11/regional_rent!F11 -> 204.38014 | G11: =regional_houseprice!G11/regional_rent!G11 -> 246.45122 | H11: =regional_houseprice!H11/regional_rent!H11 -> 201.33402 | I11: =regional_houseprice!I11/regional_rent!I11 -> 179.60135 | ... AA11: =regional_houseprice!AA11/regional_rent!AA11 -> 211.03351
A12: 2015 | B12: =regional_houseprice!B12/regional_rent!B12 -> 153.21165 | C12: =regional_houseprice!C12/regional_rent!C12 -> 171.01123 | D12: =regional_houseprice!D12/regional_rent!D12 -> 196.29112 | E12: =regional_houseprice!E12/regional_rent!E12 -> 160.59099 | F12: =regional_houseprice!F12/regional_rent!F12 -> 226.83997 | G12: =regional_houseprice!G12/regional_rent!G12 -> 251.42392 | H12: =regional_houseprice!H12/regional_rent!H12 -> 209.00447 | I12: =regional_houseprice!I12/regional_rent!I12 -> 194.01714 | ... AA12: =regional_houseprice!AA12/regional_rent!AA12 -> 210.1368
A13: 2016 | B13: =regional_houseprice!B13/regional_rent!B13 -> 165.18042 | C13: =regional_houseprice!C13/regional_rent!C13 -> 189.07199 | D13: =regional_houseprice!D13/regional_rent!D13 -> 209.87709 | E13: =regional_houseprice!E13/regional_rent!E13 -> 171.13176 | F13: =regional_houseprice!F13/regional_rent!F13 -> 241.92428 | G13: =regional_houseprice!G13/regional_rent!G13 -> 251.52185 | H13: =regional_houseprice!H13/regional_rent!H13 -> 217.36631 | I13: =regional_houseprice!I13/regional_rent!I13 -> 210.21245 | ... AA13: =regional_houseprice!AA13/regional_rent!AA13 -> 199.7259
... A19: 2022 | B19: =regional_houseprice!B19/regional_rent!B19 -> 250.59744 | C19: =regional_houseprice!C19/regional_rent!C19 -> 325.44864 | D19: =regional_houseprice!D19/regional_rent!D19 -> 384.28207 | E19: =regional_houseprice!E19/regional_rent!E19 -> 264.37597 | F19: =regional_houseprice!F19/regional_rent!F19 -> 460.35379 | G19: =regional_houseprice!G19/regional_rent!G19 -> 368.66102 | H19: =regional_houseprice!H19/regional_rent!H19 -> 311.92446 | I19: =regional_houseprice!I19/regional_rent!I19 -> 306.59301 | ... AA19: =regional_houseprice!AA19/regional_rent!AA19 -> 399.9418

Sheet regional_houseprice
A1: year | B1: TR10 (İstanbul) | C1: TR21 (Tekirdağ, Edirne, Kırklareli) | D1: TR22 (Balıkesir, Çanakkale) | E1: TR31 (İzmir) | F1: TR32 (Aydın, Denizli, Muğla) | G1: TR33 (Manisa, Afyon, Kütahya, Uşak) | H1: TR41 (Bursa, Eskişehir, Bilecik) | I1: TR42 (Kocaeli, Sakarya, Düzce, Bolu, Yalova) | J1: TR51 (Ankara) | K1: TR52 (Konya, Karaman) | L1: TR61 (Antalya, Isparta, Burdur) | M1: TR62 (Adana, Mersin) | N1: TR63 (Hatay, K.Maraş, Osmaniye) | O1: TR71 (Kırıkkale, Aksaray, Niğde, Nevşehir, Kırşehir) | P1: TR72 (Kayseri, Sivas, Yozgat) | Q1: TR81 (Zonguldak, Karabük, Bartın) | R1: TR82 (Kastamonu, Çankırı, Sinop) | S1: TR83 (Samsun, Tokat, Çorum, Amasya) | T1: TR90 (Trabzon, Ordu, Giresun, Rize, Artvin, Gümüşhane) | U1: TRA1 (Erzurum, Erzincan, Bayburt) | V1: TRA2 (Ağrı, Kars, Iğdır, Ardahan) | W1: TRB1 (Malatya, Elazığ, Bingöl, Tunceli) | X1: TRB2 (Van, Muş, Bitlis, Hakkari) | Y1: TRC1 (Gaziantep, Adıyaman, Kilis) | Z1: TRC2 (Şanlıurfa, Diyarbakır) | AA1: TRC3 (Mardin, Batman, Şırnak, Siirt)
A2: 2005 | B2: =B3/(1+regional_houseprice_growth!D2) -> 66973.92 | C2: =C3/(1+regional_houseprice_growth!E2) -> 44449.266 | D2: =D3/(1+regional_houseprice_growth!F2) -> 57071.826 | E2: =E3/(1+regional_houseprice_growth!G2) -> 60630.038 | F2: =F3/(1+regional_houseprice_growth!H2) -> 58575.504 | G2: =G3/(1+regional_houseprice_growth!I2) -> 52155.404 | H2: =H3/(1+regional_houseprice_growth!J2) -> 53334.493 | I2: =I3/(1+regional_houseprice_growth!K2) -> 54878.676 | ... O2: =O3/(1+regional_houseprice_growth!Q2) -> 52122.893 | P2: =P3/(1+regional_houseprice_growth!Q2) -> 50188.156 | Q2: =Q3/(1+regional_houseprice_growth!R2) -> 53573.41 | R2: =R3/(1+regional_houseprice_growth!R2) -> 53556.663 | S2: =S3/(1+regional_houseprice_growth!R2) -> 54480.7 | T2: =T3/(1+regional_houseprice_growth!S2) -> 62058.767 | U2: =U3/(1+regional_houseprice_growth!T2) -> 57171.072 | V2: =V3/(1+regional_houseprice_growth!T2) -> 49914.634 | W2: =W3/(1+regional_houseprice_growth!U2) -> 56074.686 | X2: =X3/(1+regional_houseprice_growth!U2) -> 47608.45 | Y2: =Y3/(1+regional_houseprice_growth!V2) -> 53367.754 | Z2: =Z3/(1+regional_houseprice_growth!V2) -> 49262.565 | AA2: =AA3/(1+regional_houseprice_growth!V2) -> 45215.594
A3: 2006 | B3: =B4/(1+regional_houseprice_growth!D3) -> 93887.92 | C3: =C4/(1+regional_houseprice_growth!E3) -> 61752.544 | D3: =D4/(1+regional_houseprice_growth!F3) -> 79190.939 | E3: =E4/(1+regional_houseprice_growth!G3) -> 84980.815 | F3: =F4/(1+regional_houseprice_growth!H3) -> 82038.392 | G3: =G4/(1+regional_houseprice_growth!I3) -> 71708.917 | H3: =H4/(1+regional_houseprice_growth!J3) -> 73386.318 | I3: =I4/(1+regional_houseprice_growth!K3) -> 75627.251 | ... O3: =O4/(1+regional_houseprice_growth!Q3) -> 71644.026 | P3: =P4/(1+regional_houseprice_growth!Q3) -> 68984.689 | Q3: =Q4/(1+regional_houseprice_growth!R3) -> 73519.646 | R3: =R4/(1+regional_houseprice_growth!R3) -> 73496.664 | S3: =S4/(1+regional_houseprice_growth!R3) -> 74764.735 | T3: =T4/(1+regional_houseprice_growth!S3) -> 85086.658 | U3: =U4/(1+regional_houseprice_growth!T3) -> 78328.793 | V3: =V4/(1+regional_houseprice_growth!T3) -> 68386.913 | W3: =W4/(1+regional_houseprice_growth!U3) -> 77000.209 | X3: =X4/(1+regional_houseprice_growth!U3) -> 65374.607 | Y3: =Y4/(1+regional_houseprice_growth!V3) -> 73645.72 | Z3: =Z4/(1+regional_houseprice_growth!V3) -> 67980.696 | AA3: =AA4/(1+regional_houseprice_growth!V3) -> 62396.011
A4: 2007 | B4: =B5/(1+regional_houseprice_growth!D4) -> 108082.12 | C4: =C5/(1+regional_houseprice_growth!E4) -> 70438.801 | D4: =D5/(1+regional_houseprice_growth!F4) -> 90377.166 | E4: =E5/(1+regional_houseprice_growth!G4) -> 98151.249 | F4: =F5/(1+regional_houseprice_growth!H4) -> 94822.88 | G4: =G5/(1+regional_houseprice_growth!I4) -> 80911.245 | H4: =H5/(1+regional_houseprice_growth!J4) -> 82915.323 | I4: =I5/(1+regional_houseprice_growth!K4) -> 85395.07 | ... O4: =O5/(1+regional_houseprice_growth!Q4) -> 80831.078 | P4: =P5/(1+regional_houseprice_growth!Q4) -> 77830.729 | Q4: =Q5/(1+regional_houseprice_growth!R4) -> 82895.536 | R4: =R5/(1+regional_houseprice_growth!R4) -> 82869.623 | S4: =S5/(1+regional_houseprice_growth!R4) -> 84299.41 | T4: =T5/(1+regional_houseprice_growth!S4) -> 95581.153 | U4: =U5/(1+regional_houseprice_growth!T4) -> 87923.684 | V4: =V5/(1+regional_houseprice_growth!T4) -> 76763.971 | W4: =W5/(1+regional_houseprice_growth!U4) -> 86987.138 | X4: =X5/(1+regional_houseprice_growth!U4) -> 73853.695 | Y4: =Y5/(1+regional_houseprice_growth!V4) -> 83827.075 | Z4: =Z5/(1+regional_houseprice_growth!V4) -> 77378.875 | AA4: =AA5/(1+regional_houseprice_growth!V4) -> 71022.12
A5: 2008 | B5: =B6/(1+regional_houseprice_growth!D5) -> 130610.43 | C5: =C6/(1+regional_houseprice_growth!E5) -> 84341.658 | D5: =D6/(1+regional_houseprice_growth!F5) -> 108855.25 | E5: =E6/(1+regional_houseprice_growth!G5) -> 119225 | F5: =F6/(1+regional_houseprice_growth!H5) -> 115868.62 | G5: =G6/(1+regional_houseprice_growth!I5) -> 96005.309 | H5: =H6/(1+regional_houseprice_growth!J5) -> 98621.225 | I5: =I6/(1+regional_houseprice_growth!K5) -> 101359.87 | ... O5: =O6/(1+regional_houseprice_growth!Q5) -> 96058.987 | P5: =P6/(1+regional_houseprice_growth!Q5) -> 92493.397 | Q5: =Q6/(1+regional_houseprice_growth!R5) -> 98345.869 | R5: =R6/(1+regional_houseprice_growth!R5) -> 98315.127 | S5: =S6/(1+regional_houseprice_growth!R5) -> 100011.4 | T5: =T6/(1+regional_houseprice_growth!S5) -> 112903.91 | U5: =U6/(1+regional_houseprice_growth!T5) -> 103786.17 | V5: =V6/(1+regional_houseprice_growth!T5) -> 90613.11 | W5: =W6/(1+regional_houseprice_growth!U5) -> 103281.88 | X5: =X6/(1+regional_houseprice_growth!U5) -> 87688.23 | Y5: =Y6/(1+regional_houseprice_growth!V5) -> 100988.48 | Z5: =Z6/(1+regional_houseprice_growth!V5) -> 93220.176 | AA5: =AA6/(1+regional_houseprice_growth!V5) -> 85562.042
A6: 2009 | B6: =B7/(1+regional_houseprice_growth!D6) -> 127750.22 | C6: =C7/(1+regional_houseprice_growth!E6) -> 80276.047 | D6: =D7/(1+regional_houseprice_growth!F6) -> 103527.4 | E6: =E7/(1+regional_houseprice_growth!G6) -> 114716.64 | F6: =F7/(1+regional_houseprice_growth!H6) -> 112620.86 | G6: =G7/(1+regional_houseprice_growth!I6) -> 88819.867 | H6: =H7/(1+regional_houseprice_growth!J6) -> 92352.255 | I6: =I7/(1+regional_houseprice_growth!K6) -> 95784.318 | ... O6: =O7/(1+regional_houseprice_growth!Q6) -> 89035.402 | P6: =P7/(1+regional_houseprice_growth!Q6) -> 85730.518 | Q6: =Q7/(1+regional_houseprice_growth!R6) -> 91240.018 | R6: =R7/(1+regional_houseprice_growth!R6) -> 91211.496 | S6: =S7/(1+regional_houseprice_growth!R6) -> 92785.209 | T6: =T7/(1+regional_houseprice_growth!S6) -> 103960.17 | U6: =U7/(1+regional_houseprice_growth!T6) -> 94512.886 | V6: =V7/(1+regional_houseprice_growth!T6) -> 82516.839 | W6: =W7/(1+regional_houseprice_growth!U6) -> 94669.665 | X6: =X7/(1+regional_houseprice_growth!U6) -> 80376.303 | Y6: =Y7/(1+regional_houseprice_growth!V6) -> 95911.026 | Z6: =Z7/(1+regional_houseprice_growth!V6) -> 88533.296 | AA6: =AA7/(1+regional_houseprice_growth!V6) -> 81260.193
A7: 2010 | B7: =B8/(1+regional_houseprice_growth!D7) -> 138332.98 | C7: =C8/(1+regional_houseprice_growth!E7) -> 86587.704 | D7: =D8/(1+regional_houseprice_growth!F7) -> 110786.82 | E7: =E8/(1+regional_houseprice_growth!G7) -> 123654.51 | F7: =F8/(1+regional_houseprice_growth!H7) -> 122670.48 | G7: =G8/(1+regional_houseprice_growth!I7) -> 93291.958 | H7: =H8/(1+regional_houseprice_growth!J7) -> 97311.829 | I7: =I8/(1+regional_houseprice_growth!K7) -> 102465.72 | ... O7: =O8/(1+regional_houseprice_growth!Q7) -> 92771.091 | P7: =P8/(1+regional_houseprice_growth!Q7) -> 89327.543 | Q7: =Q8/(1+regional_houseprice_growth!R7) -> 96448.165 | R7: =R8/(1+regional_houseprice_growth!R7) -> 96418.015 | S7: =S8/(1+regional_houseprice_growth!R7) -> 98081.559 | T7: =T8/(1+regional_houseprice_growth!S7) -> 109740.22 | U7: =U8/(1+regional_houseprice_growth!T7) -> 97958.616 | V7: =V8/(1+regional_houseprice_growth!T7) -> 85525.22 | W7: =W8/(1+regional_houseprice_growth!U7) -> 98121.732 | X7: =X8/(1+regional_houseprice_growth!U7) -> 83307.172 | Y7: =Y8/(1+regional_houseprice_growth!V7) -> 101102.03 | Z7: =Z8/(1+regional_houseprice_growth!V7) -> 93324.995 | AA7: =AA8/(1+regional_houseprice_growth!V7) -> 85658.249
A8: 2011 | B8: =B9/(1+regional_houseprice_growth!D8) -> 153200.54 | C8: =C9/(1+regional_houseprice_growth!E8) -> 92243.207 | D8: =D9/(1+regional_houseprice_growth!F8) -> 115688.9 | E8: =E9/(1+regional_houseprice_growth!G8) -> 135474.43 | F8: =F9/(1+regional_houseprice_growth!H8) -> 130459.08 | G8: =G9/(1+regional_houseprice_growth!I8) -> 102135.62 | H8: =H9/(1+regional_houseprice_growth!J8) -> 103934.18 | I8: =I9/(1+regional_houseprice_growth!K8) -> 107651.23 | ... O8: =O9/(1+regional_houseprice_growth!Q8) -> 101024.75 | P8: =P9/(1+regional_houseprice_growth!Q8) -> 97274.834 | Q8: =Q9/(1+regional_houseprice_growth!R8) -> 101806.4 | R8: =R9/(1+regional_houseprice_growth!R8) -> 101774.57 | S8: =S9/(1+regional_houseprice_growth!R8) -> 103530.53 | T8: =T9/(1+regional_houseprice_growth!S8) -> 115043.65 | U8: =U9/(1+regional_houseprice_growth!T8) -> 109444.55 | V8: =V9/(1+regional_houseprice_growth!T8) -> 95553.303 | W8: =W9/(1+regional_houseprice_growth!U8) -> 103196.99 | X8: =X9/(1+regional_houseprice_growth!U8) -> 87616.163 | Y8: =Y9/(1+regional_houseprice_growth!V8) -> 116886.73 | Z8: =Z9/(1+regional_houseprice_growth!V8) -> 107895.5 | AA8: =AA9/(1+regional_houseprice_growth!V8) -> 99031.771
A9: 2012 | B9: =B10/(1+regional_houseprice_growth!D9) -> 171300.19 | C9: =C10/(1+regional_houseprice_growth!E9) -> 97898.711 | D9: =D10/(1+regional_houseprice_growth!F9) -> 123287.11 | E9: =E10/(1+regional_houseprice_growth!G9) -> 147900.5 | F9: =F10/(1+regional_houseprice_growth!H9) -> 139221.26 | G9: =G10/(1+regional_houseprice_growth!I9) -> 116181.43 | H9: =H10/(1+regional_houseprice_growth!J9) -> 110188.63 | I9: =I10/(1+regional_houseprice_growth!K9) -> 112214.48 | ... O9: =O10/(1+regional_houseprice_growth!Q9) -> 111919.57 | P9: =P10/(1+regional_houseprice_growth!Q9) -> 107765.26 | Q9: =Q10/(1+regional_houseprice_growth!R9) -> 110490.43 | R9: =R10/(1+regional_houseprice_growth!R9) -> 110455.89 | S9: =S10/(1+regional_houseprice_growth!R9) -> 112361.63 | T9: =T10/(1+regional_houseprice_growth!S9) -> 121774.93 | U9: =U10/(1+regional_houseprice_growth!T9) -> 128314.3 | V9: =V10/(1+regional_houseprice_growth!T9) -> 112028.01 | W9: =W10/(1+regional_houseprice_growth!U9) -> 111824.94 | X9: =X10/(1+regional_houseprice_growth!U9) -> 94941.449 | Y9: =Y10/(1+regional_houseprice_growth!V9) -> 140463.89 | Z9: =Z10/(1+regional_houseprice_growth!V9) -> 129659.03 | AA9: =AA10/(1+regional_houseprice_growth!V9) -> 119007.41
A10: 2013 | B10: =B11/(1+regional_houseprice_growth!D10) -> 197480.03 | C10: =C11/(1+regional_houseprice_growth!E10) -> 104919.34 | D10: =D11/(1+regional_houseprice_growth!F10) -> 131865.73 | E10: =E11/(1+regional_houseprice_growth!G10) -> 165175.76 | F10: =F11/(1+regional_houseprice_growth!H10) -> 153500.36 | G10: =G11/(1+regional_houseprice_growth!I10) -> 129707.03 | H10: =H11/(1+regional_houseprice_growth!J10) -> 119018.44 | I10: =I11/(1+regional_houseprice_growth!K10) -> 120511.3 | ... O10: =O11/(1+regional_houseprice_growth!Q10) -> 122979.47 | P10: =P11/(1+regional_houseprice_growth!Q10) -> 118414.63 | Q10: =Q11/(1+regional_houseprice_growth!R10) -> 119728.76 | R10: =R11/(1+regional_houseprice_growth!R10) -> 119691.33 | S10: =S11/(1+regional_houseprice_growth!R10) -> 121756.42 | T10: =T11/(1+regional_houseprice_growth!S10) -> 130953.94 | U10: =U11/(1+regional_houseprice_growth!T10) -> 138815.73 | V10: =V11/(1+regional_houseprice_growth!T10) -> 121196.54 | W10: =W11/(1+regional_houseprice_growth!U10) -> 121467.94 | X10: =X11/(1+regional_houseprice_growth!U10) -> 103128.53 | Y10: =Y11/(1+regional_houseprice_growth!V10) -> 157247.62 | Z10: =Z11/(1+regional_houseprice_growth!V10) -> 145151.72 | AA10: =AA11/(1+regional_houseprice_growth!V10) -> 133227.36
A11: 2014 | B11: =B12/(1+regional_houseprice_growth!D11) -> 236588.18 | C11: =C12/(1+regional_houseprice_growth!E11) -> 114670.2 | D11: =D12/(1+regional_houseprice_growth!F11) -> 141914.98 | E11: =E12/(1+regional_houseprice_growth!G11) -> 185178.7 | F11: =F12/(1+regional_houseprice_growth!H11) -> 173296.39 | G11: =G12/(1+regional_houseprice_growth!I11) -> 140458.15 | H11: =H12/(1+regional_houseprice_growth!J11) -> 129687.79 | I11: =I12/(1+regional_houseprice_growth!K11) -> 133578.79 | ... O11: =O12/(1+regional_houseprice_growth!Q11) -> 136515.47 | P11: =P12/(1+regional_houseprice_growth!Q11) -> 131448.18 | Q11: =Q12/(1+regional_houseprice_growth!R11) -> 128412.79 | R11: =R12/(1+regional_houseprice_growth!R11) -> 128372.64 | S11: =S12/(1+regional_houseprice_growth!R11) -> 130587.52 | T11: =T12/(1+regional_houseprice_growth!S11) -> 142376.71 | U11: =U12/(1+regional_houseprice_growth!T11) -> 151942.51 | V11: =V12/(1+regional_houseprice_growth!T11) -> 132657.21 | W11: =W12/(1+regional_houseprice_growth!U11) -> 128911.65 | X11: =X12/(1+regional_houseprice_growth!U11) -> 109448.39 | Y11: =Y12/(1+regional_houseprice_growth!V11) -> 170834.46 | Z11: =Z12/(1+regional_houseprice_growth!V11) -> 157693.42 | AA11: =AA12/(1+regional_houseprice_growth!V11) -> 144738.74
A12: 2015 | B12: =B13/(1+regional_houseprice_growth!D12) -> 296381.64 | C12: =C13/(1+regional_houseprice_growth!E12) -> 132611.8 | D12: =D13/(1+regional_houseprice_growth!F12) -> 163974.3 | E12: =E13/(1+regional_houseprice_growth!G12) -> 213970.8 | F12: =F13/(1+regional_houseprice_growth!H12) -> 206397.95 | G12: =G13/(1+regional_houseprice_growth!I12) -> 154157.16 | H12: =H13/(1+regional_houseprice_growth!J12) -> 144588.09 | I12: =I13/(1+regional_houseprice_growth!K12) -> 154943.1 | ... O12: =O13/(1+regional_houseprice_growth!Q12) -> 150876.83 | P12: =P13/(1+regional_houseprice_growth!Q12) -> 145276.47 | Q12: =Q13/(1+regional_houseprice_growth!R12) -> 141531.21 | R12: =R13/(1+regional_houseprice_growth!R12) -> 141486.97 | S12: =S13/(1+regional_houseprice_growth!R12) -> 143928.11 | T12: =T13/(1+regional_houseprice_growth!S12) -> 159306.9 | U12: =U13/(1+regional_houseprice_growth!T12) -> 161787.6 | V12: =V13/(1+regional_houseprice_growth!T12) -> 141252.71 | W12: =W13/(1+regional_houseprice_growth!U12) -> 141938.16 | X12: =X13/(1+regional_houseprice_growth!U12) -> 120508.13 | Y12: =Y13/(1+regional_houseprice_growth!V12) -> 183422.26 | Z12: =Z13/(1+regional_houseprice_growth!V12) -> 169312.93 | AA12: =AA13/(1+regional_houseprice_growth!V12) -> 155403.7
A13: 2016 | B13: =B14/(1+regional_houseprice_growth!D13) -> 344216.41 | C13: =C14/(1+regional_houseprice_growth!E13) -> 159524.19 | D13: =D14/(1+regional_houseprice_growth!F13) -> 190935.7 | E13: =E14/(1+regional_houseprice_growth!G13) -> 246702.88 | F13: =F14/(1+regional_houseprice_growth!H13) -> 239174.98 | G13: =G14/(1+regional_houseprice_growth!I13) -> 168029.57 | H13: =H14/(1+regional_houseprice_growth!J13) -> 163535.38 | I13: =I14/(1+regional_houseprice_growth!K13) -> 182530.02 | ... O13: =O14/(1+regional_houseprice_growth!Q13) -> 162927.16 | P13: =P14/(1+regional_houseprice_growth!Q13) -> 156879.51 | Q13: =Q14/(1+regional_houseprice_growth!R13) -> 155943.01 | R13: =R14/(1+regional_houseprice_growth!R13) -> 155894.26 | S13: =S14/(1+regional_houseprice_growth!R13) -> 158583.98 | T13: =T14/(1+regional_houseprice_growth!S13) -> 179296.75 | U13: =U14/(1+regional_houseprice_growth!T13) -> 174914.38 | V13: =V14/(1+regional_houseprice_growth!T13) -> 152713.38 | W13: =W14/(1+regional_houseprice_growth!U13) -> 152934.56 | X13: =X14/(1+regional_houseprice_growth!U13) -> 129844.28 | Y13: =Y14/(1+regional_houseprice_growth!V13) -> 190415.48 | Z13: =Z14/(1+regional_houseprice_growth!V13) -> 175768.22 | AA13: =AA14/(1+regional_houseprice_growth!V13) -> 161328.68
... A17: 2020 | B17: =B18/(1+regional_houseprice_growth!D17) -> 461217.67 | C17: =C18/(1+regional_houseprice_growth!E17) -> 267563.81 | D17: =D18/(1+regional_houseprice_growth!F17) -> 345350.96 | E17: =E18/(1+regional_houseprice_growth!G17) -> 441276.89 | F17: =F18/(1+regional_houseprice_growth!H17) -> 429346.68 | G17: =G18/(1+regional_houseprice_growth!I17) -> 266523.68 | H17: =H18/(1+regional_houseprice_growth!J17) -> 277403.1 | I17: =I18/(1+regional_houseprice_growth!K17) -> 283958.64 | ... O17: =O18/(1+regional_houseprice_growth!Q17) -> 266097.86 | P17: =P18/(1+regional_houseprice_growth!Q17) -> 256220.64 | Q17: =Q18/(1+regional_houseprice_growth!R17) -> 269944 | R17: =R18/(1+regional_houseprice_growth!R17) -> 269859.62 | S17: =S18/(1+regional_houseprice_growth!R17) -> 274515.63 | T17: =T18/(1+regional_houseprice_growth!S17) -> 296584.16 | U17: =U18/(1+regional_houseprice_growth!T17) -> 269427.22 | V17: =V18/(1+regional_houseprice_growth!T17) -> 235230.17 | W17: =W18/(1+regional_houseprice_growth!U17) -> 288444.06 | X17: =X18/(1+regional_houseprice_growth!U17) -> 244894.36 | Y17: =Y18/(1+regional_houseprice_growth!V17) -> 306303.19 | Z17: =Z18/(1+regional_houseprice_growth!V17) -> 282741.54 | AA17: =AA18/(1+regional_houseprice_growth!V17) -> 259514.02
A18: 2021 | B18: =sahibinden_rent_price_ibbs!E2 -> 621852 | C18: =AVERAGE(sahibinden_rent_price_ibbs!E4:E6) -> 355906.67 | D18: =AVERAGE(sahibinden_rent_price_ibbs!E10:E11) -> 490942.5 | E18: =sahibinden_rent_price_ibbs!E14 -> 611908 | F18: =AVERAGE(sahibinden_rent_price_ibbs!E16:E17) -> 634122 | G18: =AVERAGE(sahibinden_rent_price_ibbs!E20:E23) -> 356867.75 | H18: =AVERAGE(sahibinden_rent_price_ibbs!E28:E30) -> 377106.33 | I18: =AVERAGE(sahibinden_rent_price_ibbs!E34:E38) -> 378749.8 | J18: =sahibinden_rent_price_ibbs!E44 -> 371250 | K18: =AVERAGE(sahibinden_rent_price_ibbs!E46:E47) -> 392565 | L18: =AVERAGE(sahibinden_rent_price_ibbs!E50:E52) -> 476742 | M18: =AVERAGE(sahibinden_rent_price_ibbs!E56:E57) -> 450666 | N18: =AVERAGE(sahibinden_rent_price_ibbs!E60:E62) -> 384110.33 | O18: =AVERAGE(sahibinden_rent_price_ibbs!E66:E70) -> 363491 | P18: =AVERAGE(sahibinden_rent_price_ibbs!E76:E78) -> 349998.67 | Q18: =AVERAGE(sahibinden_rent_price_ibbs!E82:E84) -> 363620.67 | R18: =AVERAGE(sahibinden_rent_price_ibbs!E88:E90) -> 363507 | S18: =AVERAGE(sahibinden_rent_price_ibbs!E94:E97) -> 369778.75 | T18: =AVERAGE(sahibinden_rent_price_ibbs!E102:E107) -> 394289.67 | U18: =AVERAGE(sahibinden_rent_price_ibbs!E114:E116) -> 358033 | V18: =AVERAGE(sahibinden_rent_price_ibbs!E120:E122) -> 312589.67 | W18: =AVERAGE(sahibinden_rent_price_ibbs!E126:E128) -> 384197.33 | X18: =AVERAGE(sahibinden_rent_price_ibbs!E132:E134) -> 326190.67 | Y18: =AVERAGE(sahibinden_rent_price_ibbs!E138:E140) -> 448565.33 | Z18: =AVERAGE(sahibinden_rent_price_ibbs!E144:E145) -> 414060.5 | AA18: =AVERAGE(sahibinden_rent_price_ibbs!E148:E150) -> 380045
A19: 2022 | B19: =sahibinden_rent_price_ibbs!E3 -> 2133336 | C19: =AVERAGE(sahibinden_rent_price_ibbs!E7:E9) -> 957795.33 | D19: =AVERAGE(sahibinden_rent_price_ibbs!E12:E13) -> 1485634.5 | E19: =sahibinden_rent_price_ibbs!E15 -> 1639131 | F19: =AVERAGE(sahibinden_rent_price_ibbs!E18:E19) -> 1575100.5 | G19: =AVERAGE(sahibinden_rent_price_ibbs!E24:E27) -> 870040 | H19: =AVERAGE(sahibinden_rent_price_ibbs!E31:E33) -> 956672.33 | I19: =AVERAGE(sahibinden_rent_price_ibbs!E39:E43) -> 1073320.8 | J19: =sahibinden_rent_price_ibbs!E45 -> 1032435 | K19: =AVERAGE(sahibinden_rent_price_ibbs!E48:E49) -> 1057000 | L19: =AVERAGE(sahibinden_rent_price_ibbs!E53:E55) -> 1358871.3 | M19: =AVERAGE(sahibinden_rent_price_ibbs!E58:E59) -> 1474815 | N19: =AVERAGE(sahibinden_rent_price_ibbs!E63:E65) -> 908113 | O19: =AVERAGE(sahibinden_rent_price_ibbs!E71:E75) -> 898957 | P19: =AVERAGE(sahibinden_rent_price_ibbs!E79:E81) -> 909942.67 | Q19: =AVERAGE(sahibinden_rent_price_ibbs!E85:E87) -> 909276.67 | R19: =AVERAGE(sahibinden_rent_price_ibbs!E91:E93) -> 829513 | S19: =AVERAGE(sahibinden_rent_price_ibbs!E98:E101) -> 937381 | T19: =AVERAGE(sahibinden_rent_price_ibbs!E108:E113) -> 963686.5 | U19: =AVERAGE(sahibinden_rent_price_ibbs!E117:E119) -> 769357.33 | V19: =AVERAGE(sahibinden_rent_price_ibbs!E123:E125) -> 715594.67 | W19: =AVERAGE(sahibinden_rent_price_ibbs!E129:E131) -> 858141.33 | X19: =AVERAGE(sahibinden_rent_price_ibbs!E135:E137) -> 764899.33 | Y19: =AVERAGE(sahibinden_rent_price_ibbs!E141:E143) -> 1029322 | Z19: =AVERAGE(sahibinden_rent_price_ibbs!E146:E147) -> 1165267 | AA19: =AVERAGE(sahibinden_rent_price_ibbs!E151:E153) -> 849876.33

Sheet regional_houseprice_growth
A1: source | C1: TP KFE TR | D1: TP KFE TR10 | E1: TP KFE TR21 | F1: TP KFE TR22 | G1: TP KFE TR31 | H1: TP KFE TR32 | I1: TP KFE TR33 | J1: TP KFE TR41 | K1: TP KFE TR42 | L1: TP KFE TR51 | M1: TP KFE TR52 | N1: TP KFE TR61 | O1: TP KFE TR62 | P1: TP KFE TR63 | Q1: TP KFE TR7 | R1: TP KFE TR8 | S1: TP KFE TR9 | T1: TP KFE TRA | U1: TP KFE TRB | V1: TP KFE TRC
A2: extrapolated from hbs national | B2: 2005 | C2: =turkey_rental_multiplier!G3 -> 0.38559669 | D2: =C2+(AVERAGE(D3:D15)-AVERAGE(C3:C15)) -> 0.40185792 | E2: =C2+(AVERAGE(E3:E15)-AVERAGE(C3:C15)) -> 0.38928153 | F2: =C2+(AVERAGE(F3:F15)-AVERAGE(C3:C15)) -> 0.38756624 | G2: =C2+(AVERAGE(G3:G15)-AVERAGE(C3:C15)) -> 0.40162892 | H2: =C2+(AVERAGE(H3:H15)-AVERAGE(C3:C15)) -> 0.40055802 | I2: =C2+(AVERAGE(I3:I15)-AVERAGE(C3:C15)) -> 0.37490868 | J2: =C2+(AVERAGE(J3:J15)-AVERAGE(C3:C15)) -> 0.37596354 | K2: =C2+(AVERAGE(K3:K15)-AVERAGE(C3:C15)) -> 0.37808081 | L2: =C2+(AVERAGE(L3:L15)-AVERAGE(C3:C15)) -> 0.36748321 | M2: =C2+(AVERAGE(M3:M15)-AVERAGE(C3:C15)) -> 0.38686447 | N2: =C2+(AVERAGE(N3:N15)-AVERAGE(C3:C15)) -> 0.40432026 | O2: =C2+(AVERAGE(O3:O15)-AVERAGE(C3:C15)) -> 0.3915796 | P2: =C2+(AVERAGE(P3:P15)-AVERAGE(C3:C15)) -> 0.36420895 | Q2: =C2+(AVERAGE(Q3:Q15)-AVERAGE(C3:C15)) -> 0.37452128 | R2: =C2+(AVERAGE(R3:R15)-AVERAGE(C3:C15)) -> 0.37231598 | S2: =C2+(AVERAGE(S3:S15)-AVERAGE(C3:C15)) -> 0.37106588 | T2: =C2+(AVERAGE(T3:T15)-AVERAGE(C3:C15)) -> 0.3700774 | U2: =C2+(AVERAGE(U3:U15)-AVERAGE(C3:C15)) -> 0.37317235 | V2: =C2+(AVERAGE(V3:V15)-AVERAGE(C3:C15)) -> 0.37996663
A3: extrapolated from hbs national | B3: 2006 | C3: =turkey_rental_multiplier!G4 -> 0.1387547 | D3: =C3+(AVERAGE(D4:D16)-AVERAGE(C4:C16)) -> 0.15118235 | E3: =C3+(AVERAGE(E4:E16)-AVERAGE(C4:C16)) -> 0.14066233 | F3: =C3+(AVERAGE(F4:F16)-AVERAGE(C4:C16)) -> 0.1412564 | G3: =C3+(AVERAGE(G4:G16)-AVERAGE(C4:C16)) -> 0.15498127 | H3: =C3+(AVERAGE(H4:H16)-AVERAGE(C4:C16)) -> 0.15583543 | I3: =C3+(AVERAGE(I4:I16)-AVERAGE(C4:C16)) -> 0.12832892 | J3: =C3+(AVERAGE(J4:J16)-AVERAGE(C4:C16)) -> 0.12984715 | K3: =C3+(AVERAGE(K4:K16)-AVERAGE(C4:C16)) -> 0.1291574 | L3: =C3+(AVERAGE(L4:L16)-AVERAGE(C4:C16)) -> 0.1215532 | M3: =C3+(AVERAGE(M4:M16)-AVERAGE(C4:C16)) -> 0.13995976 | N3: =C3+(AVERAGE(N4:N16)-AVERAGE(C4:C16)) -> 0.16290845 | O3: =C3+(AVERAGE(O4:O16)-AVERAGE(C4:C16)) -> 0.14369094 | P3: =C3+(AVERAGE(P4:P16)-AVERAGE(C4:C16)) -> 0.12221639 | Q3: =C3+(AVERAGE(Q4:Q16)-AVERAGE(C4:C16)) -> 0.12823194 | R3: =C3+(AVERAGE(R4:R16)-AVERAGE(C4:C16)) -> 0.12752903 | S3: =C3+(AVERAGE(S4:S16)-AVERAGE(C4:C16)) -> 0.1233389 | T3: =C3+(AVERAGE(T4:T16)-AVERAGE(C4:C16)) -> 0.12249506 | U3: =C3+(AVERAGE(U4:U16)-AVERAGE(C4:C16)) -> 0.12970003 | V3: =C3+(AVERAGE(V4:V16)-AVERAGE(C4:C16)) -> 0.13824775
A4: extrapolated from hbs national | B4: 2007 | C4: =turkey_rental_multiplier!G5 -> 0.19879298 | D4: =C4+(AVERAGE(D5:D17)-AVERAGE(C5:C17)) -> 0.20843701 | E4: =C4+(AVERAGE(E5:E17)-AVERAGE(C5:C17)) -> 0.19737498 | F4: =C4+(AVERAGE(F5:F17)-AVERAGE(C5:C17)) -> 0.20445523 | G4: =C4+(AVERAGE(G5:G17)-AVERAGE(C5:C17)) -> 0.21470691 | H4: =C4+(AVERAGE(H5:H17)-AVERAGE(C5:C17)) -> 0.22194795 | I4: =C4+(AVERAGE(I5:I17)-AVERAGE(C5:C17)) -> 0.18655088 | J4: =C4+(AVERAGE(J5:J17)-AVERAGE(C5:C17)) -> 0.18942099 | K4: =C4+(AVERAGE(K5:K17)-AVERAGE(C5:C17)) -> 0.1869522 | L4: =C4+(AVERAGE(L5:L17)-AVERAGE(C5:C17)) -> 0.18029959 | M4: =C4+(AVERAGE(M5:M17)-AVERAGE(C5:C17)) -> 0.20130338 | N4: =C4+(AVERAGE(N5:N17)-AVERAGE(C5:C17)) -> 0.22925136 | O4: =C4+(AVERAGE(O5:O17)-AVERAGE(C5:C17)) -> 0.20588261 | P4: =C4+(AVERAGE(P5:P17)-AVERAGE(C5:C17)) -> 0.18670725 | Q4: =C4+(AVERAGE(Q5:Q17)-AVERAGE(C5:C17)) -> 0.18839176 | R4: =C4+(AVERAGE(R5:R17)-AVERAGE(C5:C17)) -> 0.18638317 | S4: =C4+(AVERAGE(S5:S17)-AVERAGE(C5:C17)) -> 0.18123615 | T4: =C4+(AVERAGE(T5:T17)-AVERAGE(C5:C17)) -> 0.18041196 | U4: =C4+(AVERAGE(U5:U17)-AVERAGE(C5:C17)) -> 0.18732354 | V4: =C4+(AVERAGE(V5:V17)-AVERAGE(C5:C17)) -> 0.20472386
A5: extrapolated from hbs national | B5: 2008 | C5: =turkey_rental_multiplier!G6 -> -0.047355505 | D5: =C5+(AVERAGE(D6:D18)-AVERAGE(C6:C18)) -> -0.021898753 | E5: =C5+(AVERAGE(E6:E18)-AVERAGE(C6:C18)) -> -0.048204057 | F5: =C5+(AVERAGE(F6:F18)-AVERAGE(C6:C18)) -> -0.048944337 | G5: =C5+(AVERAGE(G6:G18)-AVERAGE(C6:C18)) -> -0.037813882 | H5: =C5+(AVERAGE(H6:H18)-AVERAGE(C6:C18)) -> -0.028029698 | I5: =C5+(AVERAGE(I6:I18)-AVERAGE(C6:C18)) -> -0.07484421 | J5: =C5+(AVERAGE(J6:J18)-AVERAGE(C6:C18)) -> -0.063566136 | K5: =C5+(AVERAGE(K6:K18)-AVERAGE(C6:C18)) -> -0.055007456 | L5: =C5+(AVERAGE(L6:L18)-AVERAGE(C6:C18)) -> -0.056271164 | M5: =C5+(AVERAGE(M6:M18)-AVERAGE(C6:C18)) -> -0.050457379 | N5: =C5+(AVERAGE(N6:N18)-AVERAGE(C6:C18)) -> -0.002249131 | O5: =C5+(AVERAGE(O6:O18)-AVERAGE(C6:C18)) -> -0.0306751 | P5: =C5+(AVERAGE(P6:P18)-AVERAGE(C6:C18)) -> -0.073602877 | Q5: =C5+(AVERAGE(Q6:Q18)-AVERAGE(C6:C18)) -> -0.073117422 | R5: =C5+(AVERAGE(R6:R18)-AVERAGE(C6:C18)) -> -0.072253685 | S5: =C5+(AVERAGE(S6:S18)-AVERAGE(C6:C18)) -> -0.079215549 | T5: =C5+(AVERAGE(T6:T18)-AVERAGE(C6:C18)) -> -0.089349879 | U5: =C5+(AVERAGE(U6:U18)-AVERAGE(C6:C18)) -> -0.083385506 | V5: =C5+(AVERAGE(V6:V18)-AVERAGE(C6:C18)) -> -0.050277537
A6: extrapolated from hbs national | B6: 2009 | C6: =turkey_rental_multiplier!G7 -> 0.067783924 | D6: =C6+(AVERAGE(D7:D19)-AVERAGE(C7:C19)) -> 0.082839443 | E6: =C6+(AVERAGE(E7:E19)-AVERAGE(C7:C19)) -> 0.078624407 | F6: =C6+(AVERAGE(F7:F19)-AVERAGE(C7:C19)) -> 0.070120789 | G6: =C6+(AVERAGE(G7:G19)-AVERAGE(C7:C19)) -> 0.077912618 | H6: =C6+(AVERAGE(H7:H19)-AVERAGE(C7:C19)) -> 0.089234072 | I6: =C6+(AVERAGE(I7:I19)-AVERAGE(C7:C19)) -> 0.050350117 | J6: =C6+(AVERAGE(J7:J19)-AVERAGE(C7:C19)) -> 0.053702801 | K6: =C6+(AVERAGE(K7:K19)-AVERAGE(C7:C19)) -> 0.069754638 | L6: =C6+(AVERAGE(L7:L19)-AVERAGE(C7:C19)) -> 0.066785543 | M6: =C6+(AVERAGE(M7:M19)-AVERAGE(C7:C19)) -> 0.070809161 | N6: =C6+(AVERAGE(N7:N19)-AVERAGE(C7:C19)) -> 0.11444189 | O6: =C6+(AVERAGE(O7:O19)-AVERAGE(C7:C19)) -> 0.082748354 | P6: =C6+(AVERAGE(P7:P19)-AVERAGE(C7:C19)) -> 0.047873399 | Q6: =C6+(AVERAGE(Q7:Q19)-AVERAGE(C7:C19)) -> 0.041957346 | R6: =C6+(AVERAGE(R7:R19)-AVERAGE(C7:C19)) -> 0.057081828 | S6: =C6+(AVERAGE(S7:S19)-AVERAGE(C7:C19)) -> 0.055598694 | T6: =C6+(AVERAGE(T7:T19)-AVERAGE(C7:C19)) -> 0.036457783 | U6: =C6+(AVERAGE(U7:U19)-AVERAGE(C7:C19)) -> 0.036464339 | V6: =C6+(AVERAGE(V7:V19)-AVERAGE(C7:C19)) -> 0.054123131
A7: evds | B7: 2010 | C7: =(house_price_index_evds!C8-house_price_index_evds!C7)/house_price_index_evds!C7 -> 0.087234043 | D7: =(house_price_index_evds!D8-house_price_index_evds!D7)/house_price_index_evds!D7 -> 0.10747664 | E7: =(house_price_index_evds!G8-house_price_index_evds!G7)/house_price_index_evds!G7 -> 0.065315315 | F7: =(house_price_index_evds!H8-house_price_index_evds!H7)/house_price_index_evds!H7 -> 0.044247788 | G7: =(house_price_index_evds!F8-house_price_index_evds!F7)/house_price_index_evds!F7 -> 0.095588235 | H7: =(house_price_index_evds!I8-house_price_index_evds!I7)/house_price_index_evds!I7 -> 0.063492063 | I7: =(house_price_index_evds!J8-house_price_index_evds!J7)/house_price_index_evds!J7 -> 0.094795539 | J7: =(house_price_index_evds!K8-house_price_index_evds!K7)/house_price_index_evds!K7 -> 0.06805293 | K7: =(house_price_index_evds!L8-house_price_index_evds!L7)/house_price_index_evds!L7 -> 0.050607287 | L7: =(house_price_index_evds!E8-house_price_index_evds!E7)/house_price_index_evds!E7 -> 0.078393881 | M7: =(house_price_index_evds!M8-house_price_index_evds!M7)/house_price_index_evds!M7 -> 0.081677704 | N7: =(house_price_index_evds!N8-house_price_index_evds!N7)/house_price_index_evds!N7 -> 0.091743119 | O7: =(house_price_index_evds!O8-house_price_index_evds!O7)/house_price_index_evds!O7 -> 0.10798122 | P7: =(house_price_index_evds!P8-house_price_index_evds!P7)/house_price_index_evds!P7 -> 0.071684588 | Q7: =(house_price_index_evds!Q8-house_price_index_evds!Q7)/house_price_index_evds!Q7 -> 0.088967972 | R7: =(house_price_index_evds!R8-house_price_index_evds!R7)/house_price_index_evds!R7 -> 0.055555556 | S7: =(house_price_index_evds!S8-house_price_index_evds!S7)/house_price_index_evds!S7 -> 0.048327138 | T7: =(house_price_index_evds!T8-house_price_index_evds!T7)/house_price_index_evds!T7 -> 0.11725293 | ... V7: =(house_price_index_evds!V8-house_price_index_evds!V7)/house_price_index_evds!V7 -> 0.15612648
A8: evds | B8: 2011 | C8: =(house_price_index_evds!C9-house_price_index_evds!C8)/house_price_index_evds!C8 -> 0.10958904 | D8: =(house_price_index_evds!D9-house_price_index_evds!D8)/house_price_index_evds!D8 -> 0.11814346 | E8: =(house_price_index_evds!G9-house_price_index_evds!G8)/house_price_index_evds!G8 -> 0.061310782 | F8: =(house_price_index_evds!H9-house_price_index_evds!H8)/house_price_index_evds!H8 -> 0.065677966 | G8: =(house_price_index_evds!F9-house_price_index_evds!F8)/house_price_index_evds!F8 -> 0.091722595 | H8: =(house_price_index_evds!I9-house_price_index_evds!I8)/house_price_index_evds!I8 -> 0.067164179 | I8: =(house_price_index_evds!J9-house_price_index_evds!J8)/house_price_index_evds!J8 -> 0.13752122 | J8: =(house_price_index_evds!K9-house_price_index_evds!K8)/house_price_index_evds!K8 -> 0.060176991 | K8: =(house_price_index_evds!L9-house_price_index_evds!L8)/house_price_index_evds!L8 -> 0.04238921 | L8: =(house_price_index_evds!E9-house_price_index_evds!E8)/house_price_index_evds!E8 -> 0.088652482 | M8: =(house_price_index_evds!M9-house_price_index_evds!M8)/house_price_index_evds!M8 -> 0.13061224 | N8: =(house_price_index_evds!N9-house_price_index_evds!N8)/house_price_index_evds!N8 -> 0.095238095 | O8: =(house_price_index_evds!O9-house_price_index_evds!O8)/house_price_index_evds!O8 -> 0.10381356 | P8: =(house_price_index_evds!P9-house_price_index_evds!P8)/house_price_index_evds!P8 -> 0.073578595 | Q8: =(house_price_index_evds!Q9-house_price_index_evds!Q8)/house_price_index_evds!Q8 -> 0.10784314 | R8: =(house_price_index_evds!R9-house_price_index_evds!R8)/house_price_index_evds!R8 -> 0.085299456 | S8: =(house_price_index_evds!S9-house_price_index_evds!S8)/house_price_index_evds!S8 -> 0.058510638 | T8: =(house_price_index_evds!T9-house_price_index_evds!T8)/house_price_index_evds!T8 -> 0.17241379 | ... V8: =(house_price_index_evds!V9-house_price_index_evds!V8)/house_price_index_evds!V8 -> 0.2017094
A9: evds | B9: 2012 | C9: =(house_price_index_evds!C10-house_price_index_evds!C9)/house_price_index_evds!C9 -> 0.11287478 | D9: =(house_price_index_evds!D10-house_price_index_evds!D9)/house_price_index_evds!D9 -> 0.15283019 | E9: =(house_price_index_evds!G10-house_price_index_evds!G9)/house_price_index_evds!G9 -> 0.071713147 | F9: =(house_price_index_evds!H10-house_price_index_evds!H9)/house_price_index_evds!H9 -> 0.069582505 | G9: =(house_price_index_evds!F10-house_price_index_evds!F9)/house_price_index_evds!F9 -> 0.11680328 | H9: =(house_price_index_evds!I10-house_price_index_evds!I9)/house_price_index_evds!I9 -> 0.1025641 | I9: =(house_price_index_evds!J10-house_price_index_evds!J9)/house_price_index_evds!J9 -> 0.11641791 | J9: =(house_price_index_evds!K10-house_price_index_evds!K9)/house_price_index_evds!K9 -> 0.080133556 | K9: =(house_price_index_evds!L10-house_price_index_evds!L9)/house_price_index_evds!L9 -> 0.073937153 | L9: =(house_price_index_evds!E10-house_price_index_evds!E9)/house_price_index_evds!E9 -> 0.094462541 | M9: =(house_price_index_evds!M10-house_price_index_evds!M9)/house_price_index_evds!M9 -> 0.10649819 | N9: =(house_price_index_evds!N10-house_price_index_evds!N9)/house_price_index_evds!N9 -> 0.11253197 | O9: =(house_price_index_evds!O10-house_price_index_evds!O9)/house_price_index_evds!O9 -> 0.10364683 | P9: =(house_price_index_evds!P10-house_price_index_evds!P9)/house_price_index_evds!P9 -> 0.065420561 | Q9: =(house_price_index_evds!Q10-house_price_index_evds!Q9)/house_price_index_evds!Q9 -> 0.098820059 | R9: =(house_price_index_evds!R10-house_price_index_evds!R9)/house_price_index_evds!R9 -> 0.08361204 | S9: =(house_price_index_evds!S10-house_price_index_evds!S9)/house_price_index_evds!S9 -> 0.075376884 | T9: =(house_price_index_evds!T10-house_price_index_evds!T9)/house_price_index_evds!T9 -> 0.081841432 | ... V9: =(house_price_index_evds!V10-house_price_index_evds!V9)/house_price_index_evds!V9 -> 0.11948791
A10: evds | B10: 2013 | C10: =(house_price_index_evds!C11-house_price_index_evds!C10)/house_price_index_evds!C10 -> 0.1251981 | D10: =(house_price_index_evds!D11-house_price_index_evds!D10)/house_price_index_evds!D10 -> 0.19803601 | E10: =(house_price_index_evds!G11-house_price_index_evds!G10)/house_price_index_evds!G10 -> 0.092936803 | F10: =(house_price_index_evds!H11-house_price_index_evds!H10)/house_price_index_evds!H10 -> 0.076208178 | G10: =(house_price_index_evds!F11-house_price_index_evds!F10)/house_price_index_evds!F10 -> 0.12110092 | H10: =(house_price_index_evds!I11-house_price_index_evds!I10)/house_price_index_evds!I10 -> 0.12896406 | I10: =(house_price_index_evds!J11-house_price_index_evds!J10)/house_price_index_evds!J10 -> 0.082887701 | J10: =(house_price_index_evds!K11-house_price_index_evds!K10)/house_price_index_evds!K10 -> 0.089644513 | K10: =(house_price_index_evds!L11-house_price_index_evds!L10)/house_price_index_evds!L10 -> 0.10843373 | L10: =(house_price_index_evds!E11-house_price_index_evds!E10)/house_price_index_evds!E10 -> 0.09375 | M10: =(house_price_index_evds!M11-house_price_index_evds!M10)/house_price_index_evds!M10 -> 0.1141925 | N10: =(house_price_index_evds!N11-house_price_index_evds!N10)/house_price_index_evds!N10 -> 0.14712644 | O10: =(house_price_index_evds!O11-house_price_index_evds!O10)/house_price_index_evds!O10 -> 0.14086957 | P10: =(house_price_index_evds!P11-house_price_index_evds!P10)/house_price_index_evds!P10 -> 0.11842105 | Q10: =(house_price_index_evds!Q11-house_price_index_evds!Q10)/house_price_index_evds!Q10 -> 0.11006711 | R10: =(house_price_index_evds!R11-house_price_index_evds!R10)/house_price_index_evds!R10 -> 0.072530864 | S10: =(house_price_index_evds!S11-house_price_index_evds!S10)/house_price_index_evds!S10 -> 0.087227414 | T10: =(house_price_index_evds!T11-house_price_index_evds!T10)/house_price_index_evds!T10 -> 0.094562648 | ... V10: =(house_price_index_evds!V11-house_price_index_evds!V10)/house_price_index_evds!V10 -> 0.086404066
A11: evds | B11: 2014 | C11: =(house_price_index_evds!C12-house_price_index_evds!C11)/house_price_index_evds!C11 -> 0.15774648 | D11: =(house_price_index_evds!D12-house_price_index_evds!D11)/house_price_index_evds!D11 -> 0.25273224 | E11: =(house_price_index_evds!G12-house_price_index_evds!G11)/house_price_index_evds!G11 -> 0.15646259 | F11: =(house_price_index_evds!H12-house_price_index_evds!H11)/house_price_index_evds!H11 -> 0.15544041 | G11: =(house_price_index_evds!F12-house_price_index_evds!F11)/house_price_index_evds!F11 -> 0.15548282 | H11: =(house_price_index_evds!I12-house_price_index_evds!I11)/house_price_index_evds!I11 -> 0.19101124 | I11: =(house_price_index_evds!J12-house_price_index_evds!J11)/house_price_index_evds!J11 -> 0.097530864 | J11: =(house_price_index_evds!K12-house_price_index_evds!K11)/house_price_index_evds!K11 -> 0.11489362 | K11: =(house_price_index_evds!L12-house_price_index_evds!L11)/house_price_index_evds!L11 -> 0.15993789 | L11: =(house_price_index_evds!E12-house_price_index_evds!E11)/house_price_index_evds!E11 -> 0.10884354 | M11: =(house_price_index_evds!M12-house_price_index_evds!M11)/house_price_index_evds!M11 -> 0.12884334 | N11: =(house_price_index_evds!N12-house_price_index_evds!N11)/house_price_index_evds!N11 -> 0.17034068 | O11: =(house_price_index_evds!O12-house_price_index_evds!O11)/house_price_index_evds!O11 -> 0.16768293 | P11: =(house_price_index_evds!P12-house_price_index_evds!P11)/house_price_index_evds!P11 -> 0.11633987 | Q11: =(house_price_index_evds!Q12-house_price_index_evds!Q11)/house_price_index_evds!Q11 -> 0.10519952 | R11: =(house_price_index_evds!R12-house_price_index_evds!R11)/house_price_index_evds!R11 -> 0.10215827 | S11: =(house_price_index_evds!S12-house_price_index_evds!S11)/house_price_index_evds!S11 -> 0.11891117 | T11: =(house_price_index_evds!T12-house_price_index_evds!T11)/house_price_index_evds!T11 -> 0.064794816 | ... V11: =(house_price_index_evds!V12-house_price_index_evds!V11)/house_price_index_evds!V11 -> 0.073684211
A12: evds | B12: 2015 | C12: =(house_price_index_evds!C13-house_price_index_evds!C12)/house_price_index_evds!C12 -> 0.12773723 | D12: =(house_price_index_evds!D13-house_price_index_evds!D12)/house_price_index_evds!D12 -> 0.16139586 | E12: =(house_price_index_evds!G13-house_price_index_evds!G12)/house_price_index_evds!G12 -> 0.20294118 | F12: =(house_price_index_evds!H13-house_price_index_evds!H12)/house_price_index_evds!H12 -> 0.16442451 | G12: =(house_price_index_evds!F13-house_price_index_evds!F12)/house_price_index_evds!F12 -> 0.1529745 | H12: =(house_price_index_evds!I13-house_price_index_evds!I12)/house_price_index_evds!I12 -> 0.15880503 | I12: =(house_price_index_evds!J13-house_price_index_evds!J12)/house_price_index_evds!J12 -> 0.089988751 | J12: =(house_price_index_evds!K13-house_price_index_evds!K12)/house_price_index_evds!K12 -> 0.13104326 | K12: =(house_price_index_evds!L13-house_price_index_evds!L12)/house_price_index_evds!L12 -> 0.17804552 | L12: =(house_price_index_evds!E13-house_price_index_evds!E12)/house_price_index_evds!E12 -> 0.093251534 | M12: =(house_price_index_evds!M13-house_price_index_evds!M12)/house_price_index_evds!M12 -> 0.11802853 | N12: =(house_price_index_evds!N13-house_price_index_evds!N12)/house_price_index_evds!N12 -> 0.13869863 | O12: =(house_price_index_evds!O13-house_price_index_evds!O12)/house_price_index_evds!O12 -> 0.14229765 | P12: =(house_price_index_evds!P13-house_price_index_evds!P12)/house_price_index_evds!P12 -> 0.069086651 | Q12: =(house_price_index_evds!Q13-house_price_index_evds!Q12)/house_price_index_evds!Q12 -> 0.079868709 | R12: =(house_price_index_evds!R13-house_price_index_evds!R12)/house_price_index_evds!R12 -> 0.10182768 | S12: =(house_price_index_evds!S13-house_price_index_evds!S12)/house_price_index_evds!S12 -> 0.12548015 | T12: =(house_price_index_evds!T13-house_price_index_evds!T12)/house_price_index_evds!T12 -> 0.081135903 | ... V12: =(house_price_index_evds!V13-house_price_index_evds!V12)/house_price_index_evds!V12 -> 0.038126362
A13: evds | B13: 2016 | C13: =(house_price_index_evds!C14-house_price_index_evds!C13)/house_price_index_evds!C13 -> 0.10895361 | D13: =(house_price_index_evds!D14-house_price_index_evds!D13)/house_price_index_evds!D13 -> 0.084507042 | E13: =(house_price_index_evds!G14-house_price_index_evds!G13)/house_price_index_evds!G13 -> 0.16136919 | F13: =(house_price_index_evds!H14-house_price_index_evds!H13)/house_price_index_evds!H13 -> 0.16944801 | G13: =(house_price_index_evds!F14-house_price_index_evds!F13)/house_price_index_evds!F13 -> 0.18427518 | H13: =(house_price_index_evds!I14-house_price_index_evds!I13)/house_price_index_evds!I13 -> 0.15061058 | I13: =(house_price_index_evds!J14-house_price_index_evds!J13)/house_price_index_evds!J13 -> 0.10939112 | J13: =(house_price_index_evds!K14-house_price_index_evds!K13)/house_price_index_evds!K13 -> 0.16872891 | K13: =(house_price_index_evds!L14-house_price_index_evds!L13)/house_price_index_evds!L13 -> 0.13522727 | L13: =(house_price_index_evds!E14-house_price_index_evds!E13)/house_price_index_evds!E13 -> 0.086419753 | M13: =(house_price_index_evds!M14-house_price_index_evds!M13)/house_price_index_evds!M13 -> 0.12180974 | N13: =(house_price_index_evds!N14-house_price_index_evds!N13)/house_price_index_evds!N13 -> 0.11428571 | O13: =(house_price_index_evds!O14-house_price_index_evds!O13)/house_price_index_evds!O13 -> 0.11771429 | P13: =(house_price_index_evds!P14-house_price_index_evds!P13)/house_price_index_evds!P13 -> 0.067907996 | Q13: =(house_price_index_evds!Q14-house_price_index_evds!Q13)/house_price_index_evds!Q13 -> 0.10536981 | R13: =(house_price_index_evds!R14-house_price_index_evds!R13)/house_price_index_evds!R13 -> 0.13388626 | S13: =(house_price_index_evds!S14-house_price_index_evds!S13)/house_price_index_evds!S13 -> 0.15017065 | T13: =(house_price_index_evds!T14-house_price_index_evds!T13)/house_price_index_evds!T13 -> 0.095684803 | ... V13: =(house_price_index_evds!V14-house_price_index_evds!V13)/house_price_index_evds!V13 -> 0.045120672
A14: evds | B14: 2017 | C14: =(house_price_index_evds!C15-house_price_index_evds!C14)/house_price_index_evds!C14 -> 0.077821012 | D14: =(house_price_index_evds!D15-house_price_index_evds!D14)/house_price_index_evds!D14 -> 0.032034632 | E14: =(house_price_index_evds!G15-house_price_index_evds!G14)/house_price_index_evds!G14 -> 0.13684211 | F14: =(house_price_index_evds!H15-house_price_index_evds!H14)/house_price_index_evds!H14 -> 0.1273326 | G14: =(house_price_index_evds!F15-house_price_index_evds!F14)/house_price_index_evds!F14 -> 0.13900415 | H14: =(house_price_index_evds!I15-house_price_index_evds!I14)/house_price_index_evds!I14 -> 0.12853774 | I14: =(house_price_index_evds!J15-house_price_index_evds!J14)/house_price_index_evds!J14 -> 0.091162791 | J14: =(house_price_index_evds!K15-house_price_index_evds!K14)/house_price_index_evds!K14 -> 0.1174206 | K14: =(house_price_index_evds!L15-house_price_index_evds!L14)/house_price_index_evds!L14 -> 0.085085085 | L14: =(house_price_index_evds!E15-house_price_index_evds!E14)/house_price_index_evds!E14 -> 0.066115702 | M14: =(house_price_index_evds!M15-house_price_index_evds!M14)/house_price_index_evds!M14 -> 0.10237849 | N14: =(house_price_index_evds!N15-house_price_index_evds!N14)/house_price_index_evds!N14 -> 0.09851552 | O14: =(house_price_index_evds!O15-house_price_index_evds!O14)/house_price_index_evds!O14 -> 0.074642127 | P14: =(house_price_index_evds!P15-house_price_index_evds!P14)/house_price_index_evds!P14 -> 0.077948718 | Q14: =(house_price_index_evds!Q15-house_price_index_evds!Q14)/house_price_index_evds!Q14 -> 0.09715857 | R14: =(house_price_index_evds!R15-house_price_index_evds!R14)/house_price_index_evds!R14 -> 0.10971787 | S14: =(house_price_index_evds!S15-house_price_index_evds!S14)/house_price_index_evds!S14 -> 0.10286845 | T14: =(house_price_index_evds!T15-house_price_index_evds!T14)/house_price_index_evds!T14 -> 0.064212329 | ... V14: =(house_price_index_evds!V15-house_price_index_evds!V14)/house_price_index_evds!V14 -> 0.086345382
A15: evds | B15: 2018 | C15: =(house_price_index_evds!C16-house_price_index_evds!C15)/house_price_index_evds!C15 -> 0.047833935 | D15: =(house_price_index_evds!D16-house_price_index_evds!D15)/house_price_index_evds!D15 -> -0.0033557047 | E15: =(house_price_index_evds!G16-house_price_index_evds!G15)/house_price_index_evds!G15 -> 0.043518519 | F15: =(house_price_index_evds!H16-house_price_index_evds!H15)/house_price_index_evds!H15 -> 0.099318403 | G15: =(house_price_index_evds!F16-house_price_index_evds!F15)/house_price_index_evds!F15 -> 0.054644809 | H15: =(house_price_index_evds!I16-house_price_index_evds!I15)/house_price_index_evds!I15 -> 0.077324974 | I15: =(house_price_index_evds!J16-house_price_index_evds!J15)/house_price_index_evds!J15 -> 0.063938619 | J15: =(house_price_index_evds!K16-house_price_index_evds!K15)/house_price_index_evds!K15 -> 0.048234281 | K15: =(house_price_index_evds!L16-house_price_index_evds!L15)/house_price_index_evds!L15 -> 0.050738007 | L15: =(house_price_index_evds!E16-house_price_index_evds!E15)/house_price_index_evds!E15 -> 0.055232558 | M15: =(house_price_index_evds!M16-house_price_index_evds!M15)/house_price_index_evds!M15 -> 0.063789869 | N15: =(house_price_index_evds!N16-house_price_index_evds!N15)/house_price_index_evds!N15 -> 0.083538084 | O15: =(house_price_index_evds!O16-house_price_index_evds!O15)/house_price_index_evds!O15 -> 0.030447193 | P15: =(house_price_index_evds!P16-house_price_index_evds!P15)/house_price_index_evds!P15 -> 0.091341579 | Q15: =(house_price_index_evds!Q16-house_price_index_evds!Q15)/house_price_index_evds!Q15 -> 0.090225564 | R15: =(house_price_index_evds!R16-house_price_index_evds!R15)/house_price_index_evds!R15 -> 0.096986817 | S15: =(house_price_index_evds!S16-house_price_index_evds!S15)/house_price_index_evds!S15 -> 0.076233184 | T15: =(house_price_index_evds!T16-house_price_index_evds!T15)/house_price_index_evds!T15 -> 0.08930008 | ... V15: =(house_price_index_evds!V16-house_price_index_evds!V15)/house_price_index_evds!V15 -> 0.085951941
A16: evds | B16: 2019 | C16: =(house_price_index_evds!C17-house_price_index_evds!C16)/house_price_index_evds!C16 -> 0.23858742 | D16: =(house_price_index_evds!D17-house_price_index_evds!D16)/house_price_index_evds!D16 -> 0.20117845 | E16: =(house_price_index_evds!G17-house_price_index_evds!G16)/house_price_index_evds!G16 -> 0.2173913 | F16: =(house_price_index_evds!H17-house_price_index_evds!H16)/house_price_index_evds!H16 -> 0.24800709 | G16: =(house_price_index_evds!F17-house_price_index_evds!F16)/house_price_index_evds!F16 -> 0.25734024 | H16: =(house_price_index_evds!I17-house_price_index_evds!I16)/house_price_index_evds!I16 -> 0.28322017 | I16: =(house_price_index_evds!J17-house_price_index_evds!J16)/house_price_index_evds!J16 -> 0.23157051 | J16: =(house_price_index_evds!K17-house_price_index_evds!K16)/house_price_index_evds!K16 -> 0.23911257 | K16: =(house_price_index_evds!L17-house_price_index_evds!L16)/house_price_index_evds!L16 -> 0.20193152 | L16: =(house_price_index_evds!E17-house_price_index_evds!E16)/house_price_index_evds!E16 -> 0.23324151 | M16: =(house_price_index_evds!M17-house_price_index_evds!M16)/house_price_index_evds!M16 -> 0.23897707 | N16: =(house_price_index_evds!N17-house_price_index_evds!N16)/house_price_index_evds!N16 -> 0.33333333 | O16: =(house_price_index_evds!O17-house_price_index_evds!O16)/house_price_index_evds!O16 -> 0.2299169 | P16: =(house_price_index_evds!P17-house_price_index_evds!P16)/house_price_index_evds!P16 -> 0.28509154 | Q16: =(house_price_index_evds!Q17-house_price_index_evds!Q16)/house_price_index_evds!Q16 -> 0.23524904 | R16: =(house_price_index_evds!R17-house_price_index_evds!R16)/house_price_index_evds!R16 -> 0.25407725 | S16: =(house_price_index_evds!S17-house_price_index_evds!S16)/house_price_index_evds!S16 -> 0.21166667 | T16: =(house_price_index_evds!T17-house_price_index_evds!T16)/house_price_index_evds!T16 -> 0.2127031 | ... V16: =(house_price_index_evds!V17-house_price_index_evds!V16)/house_price_index_evds!V16 -> 0.30468085
A17: evds | B17: 2020 | C17: =(house_price_index_evds!C18-house_price_index_evds!C17)/house_price_index_evds!C17 -> 0.37482615 | D17: =(house_price_index_evds!D18-house_price_index_evds!D17)/house_price_index_evds!D17 -> 0.34828311 | E17: =(house_price_index_evds!G18-house_price_index_evds!G17)/house_price_index_evds!G17 -> 0.33017493 | F17: =(house_price_index_evds!H18-house_price_index_evds!H17)/house_price_index_evds!H17 -> 0.42157559 | G17: =(house_price_index_evds!F18-house_price_index_evds!F17)/house_price_index_evds!F17 -> 0.38667582 | H17: =(house_price_index_evds!I18-house_price_index_evds!I17)/house_price_index_evds!I17 -> 0.47694633 | I17: =(house_price_index_evds!J18-house_price_index_evds!J17)/house_price_index_evds!J17 -> 0.33897202 | J17: =(house_price_index_evds!K18-house_price_index_evds!K17)/house_price_index_evds!K17 -> 0.35941645 | K17: =(house_price_index_evds!L18-house_price_index_evds!L17)/house_price_index_evds!L17 -> 0.33382031 | L17: =(house_price_index_evds!E18-house_price_index_evds!E17)/house_price_index_evds!E17 -> 0.33953835 | M17: =(house_price_index_evds!M18-house_price_index_evds!M17)/house_price_index_evds!M17 -> 0.39430605 | N17: =(house_price_index_evds!N18-house_price_index_evds!N17)/house_price_index_evds!N17 -> 0.4872449 | O17: =(house_price_index_evds!O18-house_price_index_evds!O17)/house_price_index_evds!O17 -> 0.40990991 | P17: =(house_price_index_evds!P18-house_price_index_evds!P17)/house_price_index_evds!P17 -> 0.42062415 | Q17: =(house_price_index_evds!Q18-house_price_index_evds!Q17)/house_price_index_evds!Q17 -> 0.36600496 | R17: =(house_price_index_evds!R18-house_price_index_evds!R17)/house_price_index_evds!R17 -> 0.34702259 | S17: =(house_price_index_evds!S18-house_price_index_evds!S17)/house_price_index_evds!S17 -> 0.32943604 | T17: =(house_price_index_evds!T18-house_price_index_evds!T17)/house_price_index_evds!T17 -> 0.32886724 | ... V17: =(house_price_index_evds!V18-house_price_index_evds!V17)/house_price_index_evds!V17 -> 0.46444879
A18: evds | B18: 2021 | C18: =(house_price_index_evds!C19-house_price_index_evds!C18)/house_price_index_evds!C18 -> 1.4997471 | D18: =(house_price_index_evds!D19-house_price_index_evds!D18)/house_price_index_evds!D18 -> 1.7307692 | E18: =(house_price_index_evds!G19-house_price_index_evds!G18)/house_price_index_evds!G18 -> 1.5063014 | F18: =(house_price_index_evds!H19-house_price_index_evds!H18)/house_price_index_evds!H18 -> 1.4038942 | G18: =(house_price_index_evds!F19-house_price_index_evds!F18)/house_price_index_evds!F18 -> 1.4264487 | H18: =(house_price_index_evds!I19-house_price_index_evds!I18)/house_price_index_evds!I18 -> 1.4692938 | I18: =(house_price_index_evds!J19-house_price_index_evds!J18)/house_price_index_evds!J18 -> 1.2740525 | J18: =(house_price_index_evds!K19-house_price_index_evds!K18)/house_price_index_evds!K18 -> 1.3946341 | K18: =(house_price_index_evds!L19-house_price_index_evds!L18)/house_price_index_evds!L18 -> 1.5465498 | L18: =(house_price_index_evds!E19-house_price_index_evds!E18)/house_price_index_evds!E18 -> 1.6153419 | M18: =(house_price_index_evds!M19-house_price_index_evds!M18)/house_price_index_evds!M18 -> 1.4236856 | N18: =(house_price_index_evds!N19-house_price_index_evds!N18)/house_price_index_evds!N18 -> 1.7352773 | O18: =(house_price_index_evds!O19-house_price_index_evds!O18)/house_price_index_evds!O18 -> 1.6411076 | P18: =(house_price_index_evds!P19-house_price_index_evds!P18)/house_price_index_evds!P18 -> 1.2893983 | Q18: =(house_price_index_evds!Q19-house_price_index_evds!Q18)/house_price_index_evds!Q18 -> 1.2742961 | R18: =(house_price_index_evds!R19-house_price_index_evds!R18)/house_price_index_evds!R18 -> 1.3125 | S18: =(house_price_index_evds!S19-house_price_index_evds!S18)/house_price_index_evds!S18 -> 1.2819452 | T18: =(house_price_index_evds!T19-house_price_index_evds!T18)/house_price_index_evds!T18 -> 1.1507791 | ... V18: =(house_price_index_evds!V19-house_price_index_evds!V18)/house_price_index_evds!V18 -> 1.3817372
A19: evds | B19: 2022 | C19: =(house_price_index_evds!C20-house_price_index_evds!C19)/house_price_index_evds!C19 -> 1.0234723 | D19: =(house_price_index_evds!D20-house_price_index_evds!D19)/house_price_index_evds!D19 -> 0.90331176 | E19: =(house_price_index_evds!G20-house_price_index_evds!G19)/house_price_index_evds!G19 -> 1.1862702 | F19: =(house_price_index_evds!H20-house_price_index_evds!H19)/house_price_index_evds!H19 -> 1.0768432 | G19: =(house_price_index_evds!F20-house_price_index_evds!F19)/house_price_index_evds!F19 -> 1.0412329 | H19: =(house_price_index_evds!I20-house_price_index_evds!I19)/house_price_index_evds!I19 -> 1.0725389 | I19: =(house_price_index_evds!J20-house_price_index_evds!J19)/house_price_index_evds!J19 -> 1.1367521 | J19: =(house_price_index_evds!K20-house_price_index_evds!K19)/house_price_index_evds!K19 -> 1.0370748 | K19: =(house_price_index_evds!L20-house_price_index_evds!L19)/house_price_index_evds!L19 -> 1.1505376 | L19: =(house_price_index_evds!E20-house_price_index_evds!E19)/house_price_index_evds!E19 -> 1.1253985 | M19: =(house_price_index_evds!M20-house_price_index_evds!M19)/house_price_index_evds!M19 -> 1.10615 | N19: =(house_price_index_evds!N20-house_price_index_evds!N19)/house_price_index_evds!N19 -> 1.090301 | O19: =(house_price_index_evds!O20-house_price_index_evds!O19)/house_price_index_evds!O19 -> 1.016129 | P19: =(house_price_index_evds!P20-house_price_index_evds!P19)/house_price_index_evds!P19 -> 1.0859408 | Q19: =(house_price_index_evds!Q20-house_price_index_evds!Q19)/house_price_index_evds!Q19 -> 0.99680511 | R19: =(house_price_index_evds!R20-house_price_index_evds!R19)/house_price_index_evds!R19 -> 1.1973193 | S19: =(house_price_index_evds!S20-house_price_index_evds!S19)/house_price_index_evds!S19 -> 1.2670596 | T19: =(house_price_index_evds!T20-house_price_index_evds!T19)/house_price_index_evds!T19 -> 1.1308332 | ... V19: =(house_price_index_evds!V20-house_price_index_evds!V19)/house_price_index_evds!V19 -> 0.87020759

Sheet sahibinden_rent_price_ibbs
A1: year | B1: month | C1: province | D1: rent | E1: house_value | F1: ibbs_1 | G1: ibbs_2
A2: 2021 | B2: 6 | C2: istanbul | D2: 3149 | E2: 621852 | F2: TR1 | G2: TR10
A3: 2022 | B3: 6 | C3: istanbul | D3: 8513 | E3: 2133336 | F3: TR1 | G3: TR10
A4: 2021 | B4: 6 | C4: edirne | D4: 1421 | E4: 389999 | F4: TR2 | G4: TR21
A5: 2021 | B5: 6 | C5: kırklareli | D5: 1131 | E5: 320000 | F5: TR2 | G5: TR21
A6: 2021 | B6: 6 | C6: tekirdağ | D6: 1439 | E6: 357721 | F6: TR2 | G6: TR21
A7: 2022 | B7: 6 | C7: edirne | D7: 2685 | E7: 979636 | F7: TR2 | G7: TR21
A8: 2022 | B8: 6 | C8: kırklareli | D8: 2350 | E8: 843750 | F8: TR2 | G8: TR21
A9: 2022 | B9: 6 | C9: tekirdağ | D9: 3794 | E9: 1050000 | F9: TR2 | G9: TR21
A10: 2021 | B10: 6 | C10: balıkesir | D10: 1560 | E10: 517044 | F10: TR2 | G10: TR22
A11: 2021 | B11: 6 | C11: çanakkale | D11: 1320 | E11: 464841 | F11: TR2 | G11: TR22
A12: 2022 | B12: 6 | C12: balıkesir | D12: 3832 | E12: 1522692 | F12: TR2 | G12: TR22
A13: 2022 | B13: 6 | C13: çanakkale | D13: 3900 | E13: 1448577 | F13: TR2 | G13: TR22
... A153: 2022 | B153: 6 | C153: siirt | D153: 1843 | E153: 669640 | F153: TRC | G153: TRC3

Sheet regional_rent
A1: year | B1: TR10 (İstanbul) | C1: TR21 (Tekirdağ, Edirne, Kırklareli) | D1: TR22 (Balıkesir, Çanakkale) | E1: TR31 (İzmir) | F1: TR32 (Aydın, Denizli, Muğla) | G1: TR33 (Manisa, Afyon, Kütahya, Uşak) | H1: TR41 (Bursa, Eskişehir, Bilecik) | I1: TR42 (Kocaeli, Sakarya, Düzce, Bolu, Yalova) | J1: TR51 (Ankara) | K1: TR52 (Konya, Karaman) | L1: TR61 (Antalya, Isparta, Burdur) | M1: TR62 (Adana, Mersin) | N1: TR63 (Hatay, K.Maraş, Osmaniye) | O1: TR71 (Kırıkkale, Aksaray, Niğde, Nevşehir, Kırşehir) | P1: TR72 (Kayseri, Sivas, Yozgat) | Q1: TR81 (Zonguldak, Karabük, Bartın) | R1: TR82 (Kastamonu, Çankırı, Sinop) | S1: TR83 (Samsun, Tokat, Çorum, Amasya) | T1: TR90 (Trabzon, Ordu, Giresun, Rize, Artvin, Gümüşhane) | U1: TRA1 (Erzurum, Erzincan, Bayburt) | V1: TRA2 (Ağrı, Kars, Iğdır, Ardahan) | W1: TRB1 (Malatya, Elazığ, Bingöl, Tunceli) | X1: TRB2 (Van, Muş, Bitlis, Hakkari) | Y1: TRC1 (Gaziantep, Adıyaman, Kilis) | Z1: TRC2 (Şanlıurfa, Diyarbakır) | AA1: TRC3 (Mardin, Batman, Şırnak, Siirt)
A2: 2005 | B2: =B3/(1+regional_rent_growth!B2) -> 925.7609 | C2: =C3/(1+regional_rent_growth!C2) -> 314.62169 | D2: =D3/(1+regional_rent_growth!D2) -> 333.20084 | E2: =E3/(1+regional_rent_growth!E2) -> 595.22508 | F2: =F3/(1+regional_rent_growth!F2) -> 378.25529 | G2: =G3/(1+regional_rent_growth!G2) -> 242.42344 | H2: =H3/(1+regional_rent_growth!H2) -> 283.00851 | I2: =I3/(1+regional_rent_growth!I2) -> 328.03807 | ... AA2: =AA3/(1+regional_rent_growth!AA2) -> 279.04346
A3: 2006 | B3: =B4/(1+regional_rent_growth!B3) -> 1063.9573 | C3: =C4/(1+regional_rent_growth!C3) -> 377.75825 | D3: =D4/(1+regional_rent_growth!D3) -> 401.9994 | E3: =E4/(1+regional_rent_growth!E3) -> 696.22097 | F3: =F4/(1+regional_rent_growth!F3) -> 451.09086 | G3: =G4/(1+regional_rent_growth!G3) -> 293.21286 | H3: =H4/(1+regional_rent_growth!H3) -> 339.01408 | I3: =I4/(1+regional_rent_growth!I3) -> 392.50798 | ... AA3: =AA4/(1+regional_rent_growth!AA3) -> 342.13309
A4: 2007 | B4: =B5/(1+regional_rent_growth!B4) -> 1223.7831 | C4: =C5/(1+regional_rent_growth!C4) -> 450.77648 | D4: =D5/(1+regional_rent_growth!D4) -> 481.56579 | E4: =E5/(1+regional_rent_growth!E4) -> 813.02399 | F4: =F5/(1+regional_rent_growth!F4) -> 535.3261 | G4: =G5/(1+regional_rent_growth!G4) -> 351.95147 | H4: =H5/(1+regional_rent_growth!H4) -> 403.78522 | I4: =I5/(1+regional_rent_growth!I4) -> 467.06824 | ... AA4: =AA5/(1+regional_rent_growth!AA4) -> 415.09703
A5: 2008 | B5: =B6/(1+regional_rent_growth!B5) -> 1361.9311 | C5: =C6/(1+regional_rent_growth!C5) -> 513.89093 | D5: =D6/(1+regional_rent_growth!D5) -> 550.34026 | E5: =E6/(1+regional_rent_growth!E5) -> 913.98452 | F5: =F6/(1+regional_rent_growth!F5) -> 608.13617 | G5: =G6/(1+regional_rent_growth!G5) -> 402.7231 | H5: =H6/(1+regional_rent_growth!H5) -> 459.77117 | I5: =I6/(1+regional_rent_growth!I5) -> 531.51558 | ... AA5: =AA6/(1+regional_rent_growth!AA5) -> 478.16457
A6: 2009 | B6: =B7/(1+regional_rent_growth!B6) -> 1459.7718 | C6: =C7/(1+regional_rent_growth!C6) -> 558.59056 | D6: =D7/(1+regional_rent_growth!D6) -> 599.04848 | E6: =E7/(1+regional_rent_growth!E6) -> 985.48791 | F6: =F7/(1+regional_rent_growth!F6) -> 659.70252 | G6: =G7/(1+regional_rent_growth!G6) -> 438.68116 | H6: =H7/(1+regional_rent_growth!H6) -> 499.42217 | I6: =I7/(1+regional_rent_growth!I6) -> 577.15919 | ... AA6: =AA7/(1+regional_rent_growth!AA6) -> 522.83096
A7: 2010 | B7: =B8/(1+regional_rent_growth!B7) -> 1511.0632 | C7: =C8/(1+regional_rent_growth!C7) -> 582.0236 | D7: =D8/(1+regional_rent_growth!D7) -> 624.58296 | E7: =E8/(1+regional_rent_growth!E7) -> 1022.9724 | F7: =F8/(1+regional_rent_growth!F7) -> 686.73533 | G7: =G8/(1+regional_rent_growth!G7) -> 457.53157 | H7: =H8/(1+regional_rent_growth!H7) -> 520.20855 | I7: =I8/(1+regional_rent_growth!I7) -> 601.0871 | ... AA7: =AA8/(1+regional_rent_growth!AA7) -> 546.24658
A8: 2011 | B8: =B9/(1+regional_rent_growth!B8) -> 1567.2418 | C8: =C9/(1+regional_rent_growth!C8) -> 607.6894 | D8: =D9/(1+regional_rent_growth!D8) -> 652.55044 | E8: =E9/(1+regional_rent_growth!E8) -> 1064.0285 | F8: =F9/(1+regional_rent_growth!F8) -> 716.34391 | G8: =G9/(1+regional_rent_growth!G8) -> 478.17811 | H8: =H9/(1+regional_rent_growth!H8) -> 542.97552 | I8: =I9/(1+regional_rent_growth!I8) -> 627.29493 | ... AA8: =AA9/(1+regional_rent_growth!AA8) -> 571.8933
A9: 2012 | B9: =B10/(1+regional_rent_growth!B9) -> 1630.9205 | C9: =C10/(1+regional_rent_growth!C9) -> 636.78174 | D9: =D10/(1+regional_rent_growth!D9) -> 684.25173 | E9: =E10/(1+regional_rent_growth!E9) -> 1110.5658 | F9: =F10/(1+regional_rent_growth!F9) -> 749.90539 | G9: =G10/(1+regional_rent_growth!G9) -> 501.58108 | H9: =H10/(1+regional_rent_growth!H9) -> 568.78201 | I9: =I10/(1+regional_rent_growth!I9) -> 657.00165 | ... AA9: =AA10/(1+regional_rent_growth!AA9) -> 600.96401
A10: 2013 | B10: =B11/(1+regional_rent_growth!B10) -> 1716.5674 | C10: =C11/(1+regional_rent_growth!C10) -> 675.91049 | D10: =D11/(1+regional_rent_growth!D10) -> 726.88949 | E10: =E11/(1+regional_rent_growth!E10) -> 1173.1578 | F10: =F11/(1+regional_rent_growth!F10) -> 795.04508 | G10: =G11/(1+regional_rent_growth!G10) -> 533.05771 | H10: =H11/(1+regional_rent_growth!H10) -> 603.49134 | I10: =I11/(1+regional_rent_growth!I10) -> 696.95674 | ... AA10: =AA11/(1+regional_rent_growth!AA10) -> 640.06368
A11: 2014 | B11: =B12/(1+regional_rent_growth!B11) -> 1816.8759 | C11: =C12/(1+regional_rent_growth!C11) -> 721.73756 | D11: =D12/(1+regional_rent_growth!D11) -> 776.82626 | E11: =E12/(1+regional_rent_growth!E11) -> 1246.4647 | F11: =F12/(1+regional_rent_growth!F11) -> 847.91207 | G11: =G12/(1+regional_rent_growth!G11) -> 569.92272 | H11: =H12/(1+regional_rent_growth!H11) -> 644.14244 | I11: =I12/(1+regional_rent_growth!I11) -> 743.75161 | ... AA11: =AA12/(1+regional_rent_growth!AA11) -> 685.85667
A12: 2015 | B12: =B13/(1+regional_rent_growth!B12) -> 1934.459 | C12: =C13/(1+regional_rent_growth!C12) -> 775.45669 | D12: =D13/(1+regional_rent_growth!D12) -> 835.36284 | E12: =E13/(1+regional_rent_growth!E12) -> 1332.3961 | F12: =F13/(1+regional_rent_growth!F12) -> 909.88351 | G12: =G13/(1+regional_rent_growth!G12) -> 613.13641 | H12: =H13/(1+regional_rent_growth!H12) -> 691.79423 | I12: =I13/(1+regional_rent_growth!I12) -> 798.60521 | ... AA12: =AA13/(1+regional_rent_growth!AA12) -> 739.53587
A13: 2016 | B13: =B14/(1+regional_rent_growth!B13) -> 2083.8814 | C13: =C14/(1+regional_rent_growth!C13) -> 843.72199 | D13: =D14/(1+regional_rent_growth!D13) -> 909.75008 | E13: =E14/(1+regional_rent_growth!E13) -> 1441.5961 | F13: =F14/(1+regional_rent_growth!F13) -> 988.63569 | G13: =G14/(1+regional_rent_growth!G13) -> 668.05158 | H13: =H14/(1+regional_rent_growth!H13) -> 752.34927 | I13: =I14/(1+regional_rent_growth!I13) -> 868.31217 | ... AA13: =AA14/(1+regional_rent_growth!AA13) -> 807.75042
... A17: 2020 | B17: =B18/(1+regional_rent_growth!B17) -> 2886.3011 | C17: =C18/(1+regional_rent_growth!C17) -> 1210.3164 | D17: =D18/(1+regional_rent_growth!D17) -> 1309.2201 | E17: =E18/(1+regional_rent_growth!E17) -> 2028.0159 | F17: =F18/(1+regional_rent_growth!F17) -> 1411.5461 | G17: =G18/(1+regional_rent_growth!G17) -> 962.95387 | H17: =H18/(1+regional_rent_growth!H17) -> 1077.5384 | I17: =I18/(1+regional_rent_growth!I17) -> 1242.6485 | ... AA17: =AA18/(1+regional_rent_growth!AA17) -> 1174.0723
A18: 2021 | B18: =AVERAGE(sahibinden_rent_price_ibbs!D2) -> 3149 | C18: =AVERAGE(sahibinden_rent_price_ibbs!D4:D6) -> 1330.3333 | D18: =AVERAGE(sahibinden_rent_price_ibbs!D10:D11) -> 1440 | E18: =AVERAGE(sahibinden_rent_price_ibbs!D14) -> 2220 | F18: =AVERAGE(sahibinden_rent_price_ibbs!D16:D17) -> 1550 | G18: =AVERAGE(sahibinden_rent_price_ibbs!D20:D23) -> 1059.5 | H18: =AVERAGE(sahibinden_rent_price_ibbs!D28:D30) -> 1184 | I18: =AVERAGE([1]sahibinden_rent_price_ibbs!D35:D39) -> 1365.2 | J18: =AVERAGE([1]sahibinden_rent_price_ibbs!D45) -> 1700 | K18: =AVERAGE([1]sahibinden_rent_price_ibbs!D47:D48) -> 1123 | L18: =AVERAGE([1]sahibinden_rent_price_ibbs!D51:D53) -> 1549.3333 | M18: =AVERAGE([1]sahibinden_rent_price_ibbs!D57:D58) -> 1699 | N18: =AVERAGE([1]sahibinden_rent_price_ibbs!D61:D63) -> 1239.3333 | O18: =AVERAGE([1]sahibinden_rent_price_ibbs!D67:D69) -> 917.33333 | P18: =AVERAGE([1]sahibinden_rent_price_ibbs!D77:D79) -> 1038.6667 | Q18: =AVERAGE([1]sahibinden_rent_price_ibbs!D83:D85) -> 996 | R18: =AVERAGE([1]sahibinden_rent_price_ibbs!D89:D91) -> 990.66667 | S18: =AVERAGE([1]sahibinden_rent_price_ibbs!D95:D98) -> 1070.5 | T18: =AVERAGE([1]sahibinden_rent_price_ibbs!D104:D108) -> 1146 | U18: =AVERAGE([1]sahibinden_rent_price_ibbs!D115:D117) -> 1035.6667 | V18: =AVERAGE([1]sahibinden_rent_price_ibbs!D121:D123) -> 1172 | W18: =AVERAGE([1]sahibinden_rent_price_ibbs!D127:D129) -> 1193.3333 | X18: =AVERAGE([1]sahibinden_rent_price_ibbs!D133:D135) -> 1228.3333 | Y18: =AVERAGE([1]sahibinden_rent_price_ibbs!D139:D141) -> 1505.6667 | Z18: =AVERAGE([1]sahibinden_rent_price_ibbs!D145:D146) -> 1731 | AA18: =AVERAGE([1]sahibinden_rent_price_ibbs!D149:D151) -> 1294
A19: 2022 | B19: =sahibinden_rent_price_ibbs!D3 -> 8513 | C19: =AVERAGE(sahibinden_rent_price_ibbs!D7:D9) -> 2943 | D19: =AVERAGE(sahibinden_rent_price_ibbs!D12:D13) -> 3866 | E19: =AVERAGE(sahibinden_rent_price_ibbs!D15) -> 6200 | F19: =AVERAGE(sahibinden_rent_price_ibbs!D18:D19) -> 3421.5 | G19: =AVERAGE(sahibinden_rent_price_ibbs!D24:D27) -> 2360 | H19: =AVERAGE(sahibinden_rent_price_ibbs!D31:D33) -> 3067 | I19: =AVERAGE([1]sahibinden_rent_price_ibbs!D40:D44) -> 3500.8 | J19: =AVERAGE([1]sahibinden_rent_price_ibbs!D46) -> 4556 | K19: =AVERAGE([1]sahibinden_rent_price_ibbs!D49:D50) -> 2701 | L19: =AVERAGE([1]sahibinden_rent_price_ibbs!D54:D56) -> 4917.6667 | M19: =AVERAGE([1]sahibinden_rent_price_ibbs!D59:D60) -> 4629 | N19: =AVERAGE([1]sahibinden_rent_price_ibbs!D64:D66) -> 2448.6667 | O19: =AVERAGE([1]sahibinden_rent_price_ibbs!D64:D66) -> 2448.6667 | P19: =AVERAGE([1]sahibinden_rent_price_ibbs!D80:D82) -> 2399.6667 | Q19: =AVERAGE([1]sahibinden_rent_price_ibbs!D86:D88) -> 2337.3333 | R19: =AVERAGE([1]sahibinden_rent_price_ibbs!D92:D94) -> 2158.3333 | S19: =AVERAGE([1]sahibinden_rent_price_ibbs!D99:D102) -> 2274.5 | T19: =AVERAGE([1]sahibinden_rent_price_ibbs!D109:D114) -> 2207.6667 | U19: =AVERAGE([1]sahibinden_rent_price_ibbs!D118:D120) -> 1921.3333 | V19: =AVERAGE([1]sahibinden_rent_price_ibbs!D124:D126) -> 1916 | W19: =AVERAGE([1]sahibinden_rent_price_ibbs!D130:D132) -> 1799.3333 | X19: =AVERAGE([1]sahibinden_rent_price_ibbs!D136:D138) -> 1924 | Y19: =AVERAGE([1]sahibinden_rent_price_ibbs!D142:D144) -> 2734 | Z19: =AVERAGE([1]sahibinden_rent_price_ibbs!D147:D148) -> 3084.5 | AA19: =AVERAGE([1]sahibinden_rent_price_ibbs!D152:D154) -> 2125

Sheet regional_rent_growth
A1: year | B1: TR10 (İstanbul) | C1: TR21 (Tekirdağ, Edirne, Kırklareli) | D1: TR22 (Balıkesir, Çanakkale) | E1: TR31 (İzmir) | F1: TR32 (Aydın, Denizli, Muğla) | G1: TR33 (Manisa, Afyon, Kütahya, Uşak) | H1: TR41 (Bursa, Eskişehir, Bilecik) | I1: TR42 (Kocaeli, Sakarya, Düzce, Bolu, Yalova) | J1: TR51 (Ankara) | K1: TR52 (Konya, Karaman) | L1: TR61 (Antalya, Isparta, Burdur) | M1: TR62 (Adana, Mersin) | N1: TR63 (Hatay, K.Maraş, Osmaniye) | O1: TR71 (Kırıkkale, Aksaray, Niğde, Nevşehir, Kırşehir) | P1: TR72 (Kayseri, Sivas, Yozgat) | Q1: TR81 (Zonguldak, Karabük, Bartın) | R1: TR82 (Kastamonu, Çankırı, Sinop) | S1: TR83 (Samsun, Tokat, Çorum, Amasya) | T1: TR90 (Trabzon, Ordu, Giresun, Rize, Artvin, Gümüşhane) | U1: TRA1 (Erzurum, Erzincan, Bayburt) | V1: TRA2 (Ağrı, Kars, Iğdır, Ardahan) | W1: TRB1 (Malatya, Elazığ, Bingöl, Tunceli) | X1: TRB2 (Van, Muş, Bitlis, Hakkari) | Y1: TRC1 (Gaziantep, Adıyaman, Kilis) | Z1: TRC2 (Şanlıurfa, Diyarbakır) | AA1: TRC3 (Mardin, Batman, Şırnak, Siirt)
A2: 2005 | B2: =(regional_rental_cpi_transposed!B3-regional_rental_cpi_transposed!B2)/regional_rental_cpi_transposed!B2 -> 0.1492787 | C2: =(regional_rental_cpi_transposed!C3-regional_rental_cpi_transposed!C2)/regional_rental_cpi_transposed!C2 -> 0.20067454 | D2: =(regional_rental_cpi_transposed!D3-regional_rental_cpi_transposed!D2)/regional_rental_cpi_transposed!D2 -> 0.20647773 | E2: =(regional_rental_cpi_transposed!E3-regional_rental_cpi_transposed!E2)/regional_rental_cpi_transposed!E2 -> 0.16967681 | F2: =(regional_rental_cpi_transposed!F3-regional_rental_cpi_transposed!F2)/regional_rental_cpi_transposed!F2 -> 0.19255663 | G2: =(regional_rental_cpi_transposed!G3-regional_rental_cpi_transposed!G2)/regional_rental_cpi_transposed!G2 -> 0.20950704 | H2: =(regional_rental_cpi_transposed!H3-regional_rental_cpi_transposed!H2)/regional_rental_cpi_transposed!H2 -> 0.19789357 | I2: =(regional_rental_cpi_transposed!I3-regional_rental_cpi_transposed!I2)/regional_rental_cpi_transposed!I2 -> 0.19653179 | ... AA2: =(regional_rental_cpi_transposed!AA3-regional_rental_cpi_transposed!AA2)/regional_rental_cpi_transposed!AA2 -> 0.22609246
A3: 2006 | B3: =(regional_rental_cpi_transposed!B4-regional_rental_cpi_transposed!B3)/regional_rental_cpi_transposed!B3 -> 0.1502183 | C3: =(regional_rental_cpi_transposed!C4-regional_rental_cpi_transposed!C3)/regional_rental_cpi_transposed!C3 -> 0.19329354 | D3: =(regional_rental_cpi_transposed!D4-regional_rental_cpi_transposed!D3)/regional_rental_cpi_transposed!D3 -> 0.19792665 | E3: =(regional_rental_cpi_transposed!E4-regional_rental_cpi_transposed!E3)/regional_rental_cpi_transposed!E3 -> 0.16776717 | F3: =(regional_rental_cpi_transposed!F4-regional_rental_cpi_transposed!F3)/regional_rental_cpi_transposed!F3 -> 0.18673677 | G3: =(regional_rental_cpi_transposed!G4-regional_rental_cpi_transposed!G3)/regional_rental_cpi_transposed!G3 -> 0.20032751 | H3: =(regional_rental_cpi_transposed!H4-regional_rental_cpi_transposed!H3)/regional_rental_cpi_transposed!H3 -> 0.19105738 | I3: =(regional_rental_cpi_transposed!I4-regional_rental_cpi_transposed!I3)/regional_rental_cpi_transposed!I3 -> 0.18995859 | ... AA3: =(regional_rental_cpi_transposed!AA4-regional_rental_cpi_transposed!AA3)/regional_rental_cpi_transposed!AA3 -> 0.21326188
A4: 2007 | B4: =(regional_rental_cpi_transposed!B5-regional_rental_cpi_transposed!B4)/regional_rental_cpi_transposed!B4 -> 0.11288601 | C4: =(regional_rental_cpi_transposed!C5-regional_rental_cpi_transposed!C4)/regional_rental_cpi_transposed!C4 -> 0.14001275 | D4: =(regional_rental_cpi_transposed!D5-regional_rental_cpi_transposed!D4)/regional_rental_cpi_transposed!D4 -> 0.14281427 | E4: =(regional_rental_cpi_transposed!E5-regional_rental_cpi_transposed!E4)/regional_rental_cpi_transposed!E4 -> 0.12417903 | F4: =(regional_rental_cpi_transposed!F5-regional_rental_cpi_transposed!F4)/regional_rental_cpi_transposed!F4 -> 0.13601067 | G4: =(regional_rental_cpi_transposed!G5-regional_rental_cpi_transposed!G4)/regional_rental_cpi_transposed!G4 -> 0.14425749 | H4: =(regional_rental_cpi_transposed!H5-regional_rental_cpi_transposed!H4)/regional_rental_cpi_transposed!H4 -> 0.13865281 | I4: =(regional_rental_cpi_transposed!I5-regional_rental_cpi_transposed!I4)/regional_rental_cpi_transposed!I4 -> 0.1379827 | ... AA4: =(regional_rental_cpi_transposed!AA5-regional_rental_cpi_transposed!AA4)/regional_rental_cpi_transposed!AA4 -> 0.15193444
A5: 2008 | B5: =(regional_rental_cpi_transposed!B6-regional_rental_cpi_transposed!B5)/regional_rental_cpi_transposed!B5 -> 0.071839693 | C5: =(regional_rental_cpi_transposed!C6-regional_rental_cpi_transposed!C5)/regional_rental_cpi_transposed!C5 -> 0.086982707 | D5: =(regional_rental_cpi_transposed!D6-regional_rental_cpi_transposed!D5)/regional_rental_cpi_transposed!D5 -> 0.088505647 | E5: =(regional_rental_cpi_transposed!E6-regional_rental_cpi_transposed!E5)/regional_rental_cpi_transposed!E5 -> 0.078232609 | F5: =(regional_rental_cpi_transposed!F6-regional_rental_cpi_transposed!F5)/regional_rental_cpi_transposed!F5 -> 0.084794095 | G5: =(regional_rental_cpi_transposed!G6-regional_rental_cpi_transposed!G5)/regional_rental_cpi_transposed!G5 -> 0.089287291 | H5: =(regional_rental_cpi_transposed!H6-regional_rental_cpi_transposed!H5)/regional_rental_cpi_transposed!H5 -> 0.086240723 | I5: =(regional_rental_cpi_transposed!I6-regional_rental_cpi_transposed!I5)/regional_rental_cpi_transposed!I5 -> 0.085874459 | ... AA5: =(regional_rental_cpi_transposed!AA6-regional_rental_cpi_transposed!AA5)/regional_rental_cpi_transposed!AA5 -> 0.093412178
A6: 2009 | B6: =(regional_rental_cpi_transposed!B7-regional_rental_cpi_transposed!B6)/regional_rental_cpi_transposed!B6 -> 0.035136569 | C6: =(regional_rental_cpi_transposed!C7-regional_rental_cpi_transposed!C6)/regional_rental_cpi_transposed!C6 -> 0.041950293 | D6: =(regional_rental_cpi_transposed!D7-regional_rental_cpi_transposed!D6)/regional_rental_cpi_transposed!D6 -> 0.04262506 | E6: =(regional_rental_cpi_transposed!E7-regional_rental_cpi_transposed!E6)/regional_rental_cpi_transposed!E6 -> 0.038036458 | F6: =(regional_rental_cpi_transposed!F7-regional_rental_cpi_transposed!F6)/regional_rental_cpi_transposed!F6 -> 0.040977269 | G6: =(regional_rental_cpi_transposed!G7-regional_rental_cpi_transposed!G6)/regional_rental_cpi_transposed!G6 -> 0.04297065 | H6: =(regional_rental_cpi_transposed!H7-regional_rental_cpi_transposed!H6)/regional_rental_cpi_transposed!H6 -> 0.041620858 | I6: =(regional_rental_cpi_transposed!I7-regional_rental_cpi_transposed!I6)/regional_rental_cpi_transposed!I6 -> 0.041458073 | ... AA6: =(regional_rental_cpi_transposed!AA7-regional_rental_cpi_transposed!AA6)/regional_rental_cpi_transposed!AA6 -> 0.044786209
A7: 2010 | B7: =(regional_rental_cpi_transposed!B8-regional_rental_cpi_transposed!B7)/regional_rental_cpi_transposed!B7 -> 0.037178173 | C7: =(regional_rental_cpi_transposed!C8-regional_rental_cpi_transposed!C7)/regional_rental_cpi_transposed!C7 -> 0.044097539 | D7: =(regional_rental_cpi_transposed!D8-regional_rental_cpi_transposed!D7)/regional_rental_cpi_transposed!D7 -> 0.044777846 | E7: =(regional_rental_cpi_transposed!E8-regional_rental_cpi_transposed!E7)/regional_rental_cpi_transposed!E7 -> 0.040134126 | F7: =(regional_rental_cpi_transposed!F8-regional_rental_cpi_transposed!F7)/regional_rental_cpi_transposed!F7 -> 0.043114973 | G7: =(regional_rental_cpi_transposed!G8-regional_rental_cpi_transposed!G7)/regional_rental_cpi_transposed!G7 -> 0.045125933 | H7: =(regional_rental_cpi_transposed!H8-regional_rental_cpi_transposed!H7)/regional_rental_cpi_transposed!H7 -> 0.043765078 | I7: =(regional_rental_cpi_transposed!I8-regional_rental_cpi_transposed!I7)/regional_rental_cpi_transposed!I7 -> 0.043600721 | ... AA7: =(regional_rental_cpi_transposed!AA8-regional_rental_cpi_transposed!AA7)/regional_rental_cpi_transposed!AA7 -> 0.046950825
A8: 2011 | B8: =(regional_rental_cpi_transposed!B9-regional_rental_cpi_transposed!B8)/regional_rental_cpi_transposed!B8 -> 0.040631078 | C8: =(regional_rental_cpi_transposed!C9-regional_rental_cpi_transposed!C8)/regional_rental_cpi_transposed!C8 -> 0.047873695 | D8: =(regional_rental_cpi_transposed!D9-regional_rental_cpi_transposed!D8)/regional_rental_cpi_transposed!D8 -> 0.048580605 | E8: =(regional_rental_cpi_transposed!E9-regional_rental_cpi_transposed!E8)/regional_rental_cpi_transposed!E8 -> 0.043736914 | F8: =(regional_rental_cpi_transposed!F9-regional_rental_cpi_transposed!F8)/regional_rental_cpi_transposed!F8 -> 0.04685108 | G8: =(regional_rental_cpi_transposed!G9-regional_rental_cpi_transposed!G8)/regional_rental_cpi_transposed!G8 -> 0.048941947 | H8: =(regional_rental_cpi_transposed!H9-regional_rental_cpi_transposed!H8)/regional_rental_cpi_transposed!H8 -> 0.047527899 | I8: =(regional_rental_cpi_transposed!I9-regional_rental_cpi_transposed!I8)/regional_rental_cpi_transposed!I8 -> 0.047356868 | ... AA8: =(regional_rental_cpi_transposed!AA9-regional_rental_cpi_transposed!AA8)/regional_rental_cpi_transposed!AA8 -> 0.0508324
A9: 2012 | B9: =(regional_rental_cpi_transposed!B10-regional_rental_cpi_transposed!B9)/regional_rental_cpi_transposed!B9 -> 0.052514464 | C9: =(regional_rental_cpi_transposed!C10-regional_rental_cpi_transposed!C9)/regional_rental_cpi_transposed!C9 -> 0.061447665 | D9: =(regional_rental_cpi_transposed!D10-regional_rental_cpi_transposed!D9)/regional_rental_cpi_transposed!D9 -> 0.062312973 | E9: =(regional_rental_cpi_transposed!E10-regional_rental_cpi_transposed!E9)/regional_rental_cpi_transposed!E9 -> 0.056360452 | F9: =(regional_rental_cpi_transposed!F10-regional_rental_cpi_transposed!F9)/regional_rental_cpi_transposed!F9 -> 0.060193845 | G9: =(regional_rental_cpi_transposed!G10-regional_rental_cpi_transposed!G9)/regional_rental_cpi_transposed!G9 -> 0.062754831 | H9: =(regional_rental_cpi_transposed!H10-regional_rental_cpi_transposed!H9)/regional_rental_cpi_transposed!H9 -> 0.061023961 | I9: =(regional_rental_cpi_transposed!I10-regional_rental_cpi_transposed!I9)/regional_rental_cpi_transposed!I9 -> 0.060814293 | ... AA9: =(regional_rental_cpi_transposed!AA10-regional_rental_cpi_transposed!AA9)/regional_rental_cpi_transposed!AA9 -> 0.06506157
A10: 2013 | B10: =(regional_rental_cpi_transposed!B11-regional_rental_cpi_transposed!B10)/regional_rental_cpi_transposed!B10 -> 0.058435518 | C10: =(regional_rental_cpi_transposed!C11-regional_rental_cpi_transposed!C10)/regional_rental_cpi_transposed!C10 -> 0.067800491 | D10: =(regional_rental_cpi_transposed!D11-regional_rental_cpi_transposed!D10)/regional_rental_cpi_transposed!D10 -> 0.068699254 | E10: =(regional_rental_cpi_transposed!E11-regional_rental_cpi_transposed!E10)/regional_rental_cpi_transposed!E10 -> 0.062486812 | F10: =(regional_rental_cpi_transposed!F11-regional_rental_cpi_transposed!F10)/regional_rental_cpi_transposed!F10 -> 0.066495589 | G10: =(regional_rental_cpi_transposed!G11-regional_rental_cpi_transposed!G10)/regional_rental_cpi_transposed!G10 -> 0.069157631 | H10: =(regional_rental_cpi_transposed!H11-regional_rental_cpi_transposed!H10)/regional_rental_cpi_transposed!H10 -> 0.06735987 | I10: =(regional_rental_cpi_transposed!I11-regional_rental_cpi_transposed!I10)/regional_rental_cpi_transposed!I10 -> 0.0671417 | ... AA10: =(regional_rental_cpi_transposed!AA11-regional_rental_cpi_transposed!AA10)/regional_rental_cpi_transposed!AA10 -> 0.071544435
A11: 2014 | B11: =(regional_rental_cpi_transposed!B12-regional_rental_cpi_transposed!B11)/regional_rental_cpi_transposed!B11 -> 0.064717162 | C11: =(regional_rental_cpi_transposed!C12-regional_rental_cpi_transposed!C11)/regional_rental_cpi_transposed!C11 -> 0.074430287 | D11: =(regional_rental_cpi_transposed!D12-regional_rental_cpi_transposed!D11)/regional_rental_cpi_transposed!D11 -> 0.07535351 | E11: =(regional_rental_cpi_transposed!E12-regional_rental_cpi_transposed!E11)/regional_rental_cpi_transposed!E11 -> 0.068940082 | F11: =(regional_rental_cpi_transposed!F12-regional_rental_cpi_transposed!F11)/regional_rental_cpi_transposed!F11 -> 0.073087103 | G11: =(regional_rental_cpi_transposed!G12-regional_rental_cpi_transposed!G11)/regional_rental_cpi_transposed!G11 -> 0.075823764 | H11: =(regional_rental_cpi_transposed!H12-regional_rental_cpi_transposed!H11)/regional_rental_cpi_transposed!H11 -> 0.073977107 | I11: =(regional_rental_cpi_transposed!I12-regional_rental_cpi_transposed!I11)/regional_rental_cpi_transposed!I11 -> 0.07375258 | ... AA11: =(regional_rental_cpi_transposed!AA12-regional_rental_cpi_transposed!AA11)/regional_rental_cpi_transposed!AA11 -> 0.078265911
A12: 2015 | B12: =(regional_rental_cpi_transposed!B13-regional_rental_cpi_transposed!B12)/regional_rental_cpi_transposed!B12 -> 0.077242483 | C12: =(regional_rental_cpi_transposed!C13-regional_rental_cpi_transposed!C12)/regional_rental_cpi_transposed!C12 -> 0.088032385 | D12: =(regional_rental_cpi_transposed!D13-regional_rental_cpi_transposed!D12)/regional_rental_cpi_transposed!D12 -> 0.089047811 | E12: =(regional_rental_cpi_transposed!E13-regional_rental_cpi_transposed!E12)/regional_rental_cpi_transposed!E12 -> 0.081957641 | F12: =(regional_rental_cpi_transposed!F13-regional_rental_cpi_transposed!F12)/regional_rental_cpi_transposed!F12 -> 0.086551937 | G12: =(regional_rental_cpi_transposed!G13-regional_rental_cpi_transposed!G12)/regional_rental_cpi_transposed!G12 -> 0.08956436 | H12: =(regional_rental_cpi_transposed!H13-regional_rental_cpi_transposed!H12)/regional_rental_cpi_transposed!H12 -> 0.087533307 | I12: =(regional_rental_cpi_transposed!I13-regional_rental_cpi_transposed!I12)/regional_rental_cpi_transposed!I12 -> 0.087285884 | ... AA12: =(regional_rental_cpi_transposed!AA13-regional_rental_cpi_transposed!AA12)/regional_rental_cpi_transposed!AA12 -> 0.09223968
A13: 2016 | B13: =(regional_rental_cpi_transposed!B14-regional_rental_cpi_transposed!B13)/regional_rental_cpi_transposed!B13 -> 0.077880463 | C13: =(regional_rental_cpi_transposed!C14-regional_rental_cpi_transposed!C13)/regional_rental_cpi_transposed!C13 -> 0.087879264 | D13: =(regional_rental_cpi_transposed!D14-regional_rental_cpi_transposed!D13)/regional_rental_cpi_transposed!D13 -> 0.088810041 | E13: =(regional_rental_cpi_transposed!E14-regional_rental_cpi_transposed!E13)/regional_rental_cpi_transposed!E13 -> 0.082274444 | F13: =(regional_rental_cpi_transposed!F14-regional_rental_cpi_transposed!F13)/regional_rental_cpi_transposed!F13 -> 0.086519115 | G13: =(regional_rental_cpi_transposed!G14-regional_rental_cpi_transposed!G13)/regional_rental_cpi_transposed!G13 -> 0.089282862 | H13: =(regional_rental_cpi_transposed!H14-regional_rental_cpi_transposed!H13)/regional_rental_cpi_transposed!H13 -> 0.087421154 | I13: =(regional_rental_cpi_transposed!I14-regional_rental_cpi_transposed!I13)/regional_rental_cpi_transposed!I13 -> 0.087193886 | ... AA13: =(regional_rental_cpi_transposed!AA14-regional_rental_cpi_transposed!AA13)/regional_rental_cpi_transposed!AA13 -> 0.091724553
... A19: 2022 | B19: =(regional_rental_cpi_transposed!B20-regional_rental_cpi_transposed!B19)/regional_rental_cpi_transposed!B19 -> 0.71087274 | C19: =(regional_rental_cpi_transposed!C20-regional_rental_cpi_transposed!C19)/regional_rental_cpi_transposed!C19 -> 0.75802369 | D19: =(regional_rental_cpi_transposed!D20-regional_rental_cpi_transposed!D19)/regional_rental_cpi_transposed!D19 -> 0.76215039 | E19: =(regional_rental_cpi_transposed!E20-regional_rental_cpi_transposed!E19)/regional_rental_cpi_transposed!E19 -> 0.73225237 | F19: =(regional_rental_cpi_transposed!F20-regional_rental_cpi_transposed!F19)/regional_rental_cpi_transposed!F19 -> 0.75191675 | G19: =(regional_rental_cpi_transposed!G20-regional_rental_cpi_transposed!G19)/regional_rental_cpi_transposed!G19 -> 0.76423064 | H19: =(regional_rental_cpi_transposed!H20-regional_rental_cpi_transposed!H19)/regional_rental_cpi_transposed!H19 -> 0.75597705 | I19: =(regional_rental_cpi_transposed!I20-regional_rental_cpi_transposed!I19)/regional_rental_cpi_transposed!I19 -> 0.75495787 | ... AA19: =(regional_rental_cpi_transposed!AA20-regional_rental_cpi_transposed!AA19)/regional_rental_cpi_transposed!AA19 -> 0.77480457

Sheet house_price_index_evds
A1: source | B1: year | C1: TP KFE TR | D1: TP KFE TR10 | E1: TP KFE TR51 | F1: TP KFE TR31 | G1: TP KFE TR21 | H1: TP KFE TR22 | I1: TP KFE TR32 | J1: TP KFE TR33 | K1: TP KFE TR41 | L1: TP KFE TR42 | M1: TP KFE TR52 | N1: TP KFE TR61 | O1: TP KFE TR62 | P1: TP KFE TR63 | Q1: TP KFE TR7 | R1: TP KFE TR8 | S1: TP KFE TR9 | T1: TP KFE TRA | U1: TP KFE TRB | V1: TP KFE TRC
B2: 2005
B3: 2006
B4: 2007
B5: 2008
B6: 2009
A7: evds | B7: 2010 | C7: 4.7 | D7: 4.28 | E7: 5.23 | F7: 4.08 | G7: 4.44 | H7: 4.52 | I7: 3.78 | J7: 5.38 | K7: 5.29 | L7: 4.94 | M7: 4.53 | N7: 3.27 | O7: 4.26 | P7: 5.58 | Q7: 5.62 | R7: 5.22 | S7: 5.38 | T7: 5.97 | U7: 5.8 | V7: 5.06
A8: evds | B8: 2011 | C8: 5.11 | D8: 4.74 | E8: 5.64 | F8: 4.47 | G8: 4.73 | H8: 4.72 | I8: 4.02 | J8: 5.89 | K8: 5.65 | L8: 5.19 | M8: 4.9 | N8: 3.57 | O8: 4.72 | P8: 5.98 | Q8: 6.12 | R8: 5.51 | S8: 5.64 | T8: 6.67 | U8: 6.1 | V8: 5.85
A9: evds | B9: 2012 | C9: 5.67 | D9: 5.3 | E9: 6.14 | F9: 4.88 | G9: 5.02 | H9: 5.03 | I9: 4.29 | J9: 6.7 | K9: 5.99 | L9: 5.41 | M9: 5.54 | N9: 3.91 | O9: 5.21 | P9: 6.42 | Q9: 6.78 | R9: 5.98 | S9: 5.97 | T9: 7.82 | U9: 6.61 | V9: 7.03
A10: evds | B10: 2013 | C10: 6.31 | D10: 6.11 | E10: 6.72 | F10: 5.45 | G10: 5.38 | H10: 5.38 | I10: 4.73 | J10: 7.48 | K10: 6.47 | L10: 5.81 | M10: 6.13 | N10: 4.35 | O10: 5.75 | P10: 6.84 | Q10: 7.45 | R10: 6.48 | S10: 6.42 | T10: 8.46 | U10: 7.18 | V10: 7.87
A11: evds | B11: 2014 | C11: 7.1 | D11: 7.32 | E11: 7.35 | F11: 6.11 | G11: 5.88 | H11: 5.79 | I11: 5.34 | J11: 8.1 | K11: 7.05 | L11: 6.44 | M11: 6.83 | N11: 4.99 | O11: 6.56 | P11: 7.65 | Q11: 8.27 | R11: 6.95 | S11: 6.98 | T11: 9.26 | U11: 7.62 | V11: 8.55
A12: evds | B12: 2015 | C12: 8.22 | D12: 9.17 | E12: 8.15 | F12: 7.06 | G12: 6.8 | H12: 6.69 | I12: 6.36 | J12: 8.89 | K12: 7.86 | L12: 7.47 | M12: 7.71 | N12: 5.84 | O12: 7.66 | P12: 8.54 | Q12: 9.14 | R12: 7.66 | S12: 7.81 | T12: 9.86 | U12: 8.39 | V12: 9.18
A13: evds | B13: 2016 | C13: 9.27 | D13: 10.65 | E13: 8.91 | F13: 8.14 | G13: 8.18 | H13: 7.79 | I13: 7.37 | J13: 9.69 | K13: 8.89 | L13: 8.8 | M13: 8.62 | N13: 6.65 | O13: 8.75 | P13: 9.13 | Q13: 9.87 | R13: 8.44 | S13: 8.79 | T13: 10.66 | U13: 9.04 | V13: 9.53
A14: evds | B14: 2017 | C14: 10.28 | D14: 11.55 | E14: 9.68 | F14: 9.64 | G14: 9.5 | H14: 9.11 | I14: 8.48 | J14: 10.75 | K14: 10.39 | L14: 9.99 | M14: 9.67 | N14: 7.41 | O14: 9.78 | P14: 9.75 | Q14: 10.91 | R14: 9.57 | S14: 10.11 | T14: 11.68 | U14: 10.23 | V14: 9.96
A15: evds | B15: 2018 | C15: 11.08 | D15: 11.92 | E15: 10.32 | F15: 10.98 | G15: 10.8 | H15: 10.27 | I15: 9.57 | J15: 11.73 | K15: 11.61 | L15: 10.84 | M15: 10.66 | N15: 8.14 | O15: 10.51 | P15: 10.51 | Q15: 11.97 | R15: 10.62 | S15: 11.15 | T15: 12.43 | U15: 11.86 | V15: 10.82
A16: evds | B16: 2019 | C16: 11.61 | D16: 11.88 | E16: 10.89 | F16: 11.58 | G16: 11.27 | H16: 11.29 | I16: 10.31 | J16: 12.48 | K16: 12.17 | L16: 11.39 | M16: 11.34 | N16: 8.82 | O16: 10.83 | P16: 11.47 | Q16: 13.05 | R16: 11.65 | S16: 12 | T16: 13.54 | U16: 13.39 | V16: 11.75
A17: evds | B17: 2020 | C17: 14.38 | D17: 14.27 | E17: 13.43 | F17: 14.56 | G17: 13.72 | H17: 14.09 | I17: 13.23 | J17: 15.37 | K17: 15.08 | L17: 13.69 | M17: 14.05 | N17: 11.76 | O17: 13.32 | P17: 14.74 | Q17: 16.12 | R17: 14.61 | S17: 14.54 | T17: 16.42 | U17: 17.05 | V17: 15.33
A18: evds | B18: 2021 | C18: 19.77 | D18: 19.24 | E18: 17.99 | F18: 20.19 | G18: 18.25 | H18: 20.03 | I18: 19.54 | J18: 20.58 | K18: 20.5 | L18: 18.26 | M18: 19.59 | N18: 17.49 | O18: 18.78 | P18: 20.94 | Q18: 22.02 | R18: 19.68 | S18: 19.33 | T18: 21.82 | U18: 22.71 | V18: 22.45
... A22: evds | B22: 2025 | C22: 171.68 | D22: 159.01 | E22: 184.54 | F22: 167.73 | G22: 172.81 | H22: 179.03 | I22: 170.57 | J22: 194.51 | K22: 171.56 | L22: 177 | M22: 176.43 | N22: 147.76 | O22: 159.53 | P22: 181.03 | Q22: 180 | R22: 182.39 | S22: 183.65 | T22: 205.47 | U22: 204.51 | V22: 177.07

Sheet sahibinden_rent_and_price_june
A1: year | B1: month | C1: province | D1: rental | E1: house_value | F1: ibbs_1 | G1: ibbs_2
A2: 2021 | B2: 6 | C2: istanbul | D2: 3149 | E2: 621852 | F2: TR1 | G2: TR10
A3: 2021 | B3: 6 | C3: ankara | D3: 1700 | E3: 371250 | F3: TR5 | G3: TR51
A4: 2021 | B4: 6 | C4: izmir | D4: 2220 | E4: 611908 | F4: TR3 | G4: TR31
A5: 2021 | B5: 6 | C5: adana | D5: 1431 | E5: 448000 | F5: TR6 | G5: TR62
A6: 2021 | B6: 6 | C6: adıyaman | D6: 1160 | E6: 414907 | F6: TRC | G6: TRC1
A7: 2021 | B7: 6 | C7: afyonkarahisar | D7: 1124 | E7: 339286 | F7: TR3 | G7: TR33
A8: 2021 | B8: 6 | C8: ağrı | D8: 1099 | E8: 291808 | F8: TRA | G8: TRA2
A9: 2021 | B9: 6 | C9: aksaray | D9: 915 | E9: 436256 | F9: TR7 | G9: TR71
A10: 2021 | B10: 6 | C10: amasya | D10: 938 | E10: 369115 | F10: TR8 | G10: TR83
A11: 2021 | B11: 6 | C11: antalya | D11: 2360 | E11: 578125 | F11: TR6 | G11: TR61
A12: 2021 | B12: 6 | C12: artvin | D12: 1176 | E12: 398125 | F12: TR9 | G12: TR90
A13: 2021 | B13: 6 | C13: aydın | D13: 1714 | E13: 787500 | F13: TR3 | G13: TR32
... A154: 2022 | B154: 6 | C154: zonguldak | D154: 2308 | E154: 953332 | F154: TR8 | G154: TR81

Sheet sahibinden_rent_and_price
A1: year | B1: month | C1: province | D1: rent | E1: house_value | F1: ibbs_1 | G1: ibbs_2
A2: 2021 | B2: 4 | C2: istanbul | D2: 2775 | E2: 586960 | F2: TR1 | G2: TR10
A3: 2021 | B3: 5 | C3: istanbul | D3: 3039 | E3: 598000 | F3: TR1 | G3: TR10
A4: 2021 | B4: 6 | C4: istanbul | D4: 3149 | E4: 621852 | F4: TR1 | G4: TR10
A5: 2021 | B5: 7 | C5: istanbul | D5: 3357 | E5: 660800 | F5: TR1 | G5: TR10
A6: 2021 | B6: 8 | C6: istanbul | D6: 3722 | E6: 689660 | F6: TR1 | G6: TR10
A7: 2021 | B7: 9 | C7: istanbul | D7: 3999 | E7: 750000 | F7: TR1 | G7: TR10
A8: 2021 | B8: 10 | C8: istanbul | D8: 4473 | E8: 808420 | F8: TR1 | G8: TR10
A9: 2021 | B9: 11 | C9: istanbul | D9: 4679 | E9: 920000 | F9: TR1 | G9: TR10
A10: 2021 | B10: 12 | C10: istanbul | D10: 4953 | E10: 1166786 | F10: TR1 | G10: TR10
A11: 2022 | B11: 1 | C11: istanbul | D11: 5413 | E11: 1308000 | F11: TR1 | G11: TR10
A12: 2022 | B12: 2 | C12: istanbul | D12: 6037 | E12: 1389480 | F12: TR1 | G12: TR10
A13: 2022 | B13: 3 | C13: istanbul | D13: 6677 | E13: 1536588 | F13: TR1 | G13: TR10
... A156: 2023 | B156: 2 | C156: adıyaman | D156: 3697 | E156: 1452244 | F156: TRC | G156: TRC1
A157: 2023 | B157: 3 | C157: adıyaman | D157: =(D158+D156)/2 -> 4709.5 | E157: 1453125 | F157: TRC | G157: TRC1
A158: 2023 | B158: 4 | C158: adıyaman | D158: 5722 | E158: 1524448 | F158: TRC | G158: TRC1
A159: 2023 | B159: 5 | C159: adıyaman | D159: 5652 | E159: 1710000 | F159: TRC | G159: TRC1
A160: 2023 | B160: 6 | C160: adıyaman | D160: 7805 | E160: 1850002 | F160: TRC | G160: TRC1
A161: 2023 | B161: 7 | C161: adıyaman | D161: 8707 | E161: 1992850 | F161: TRC | G161: TRC1
A162: 2023 | B162: 8 | C162: adıyaman | D162: 9418 | E162: 2110821 | F162: TRC | G162: TRC1
A163: 2023 | B163: 9 | C163: adıyaman | D163: 9562 | E163: 2156515 | F163: TRC | G163: TRC1
A164: 2023 | B164: 10 | C164: adıyaman | D164: 9394 | E164: 2119170 | F164: TRC | G164: TRC1
A165: 2023 | B165: 11 | C165: adıyaman | D165: 9562 | E165: 2130345 | F165: TRC | G165: TRC1
A166: 2023 | B166: 12 | C166: adıyaman | D166: 9227 | E166: 2163210 | F166: TRC | G166: TRC1
A167: 2021 | B167: 4 | C167: afyonkarahisar | D167: 1005 | E167: 323743 | F167: TR3 | G167: TR33
A168: 2021 | B168: 5 | C168: afyonkarahisar | D168: 1053 | E168: 334077 | F168: TR3 | G168: TR33
A169: 2021 | B169: 6 | C169: afyonkarahisar | D169: 1124 | E169: 339286 | F169: TR3 | G169: TR33
... A1651: 2022 | B1651: 12 | C1651: zonguldak | D1651: 4270 | E1651: 1399996 | F1651: TR8 | G1651: TR81

Sheet regional_rental_cpi_transposed
A1: İstatistiki Bölge Birimleri Sınıflaması (2. Düzey) Statistical Regions (Level 2) | B1: TR10 (İstanbul) | C1: TR21 (Tekirdağ, Edirne, Kırklareli) | D1: TR22 (Balıkesir, Çanakkale) | E1: TR31 (İzmir) | F1: TR32 (Aydın, Denizli, Muğla) | G1: TR33 (Manisa, Afyon, Kütahya, Uşak) | H1: TR41 (Bursa, Eskişehir, Bilecik) | I1: TR42 (Kocaeli, Sakarya, Düzce, Bolu, Yalova) | J1: TR51 (Ankara) | K1: TR52 (Konya, Karaman) | L1: TR61 (Antalya, Isparta, Burdur) | M1: TR62 (Adana, Mersin) | N1: TR63 (Hatay, K.Maraş, Osmaniye) | O1: TR71 (Kırıkkale, Aksaray, Niğde, Nevşehir, Kırşehir) | P1: TR72 (Kayseri, Sivas, Yozgat) | Q1: TR81 (Zonguldak, Karabük, Bartın) | R1: TR82 (Kastamonu, Çankırı, Sinop) | S1: TR83 (Samsun, Tokat, Çorum, Amasya) | T1: TR90 (Trabzon, Ordu, Giresun, Rize, Artvin, Gümüşhane) | U1: TRA1 (Erzurum, Erzincan, Bayburt) | V1: TRA2 (Ağrı, Kars, Iğdır, Ardahan) | W1: TRB1 (Malatya, Elazığ, Bingöl, Tunceli) | X1: TRB2 (Van, Muş, Bitlis, Hakkari) | Y1: TRC1 (Gaziantep, Adıyaman, Kilis) | Z1: TRC2 (Şanlıurfa, Diyarbakır) | AA1: TRC3 (Mardin, Batman, Şırnak, Siirt)
A2: 2005 | B2: 191.32 | C2: 142.32 | D2: 138.32 | E2: 168.32 | F2: 148.32 | G2: 136.32 | H2: 144.32 | I2: 145.32 | J2: 161.32 | K2: 143.32 | L2: 138.32 | M2: 150.32 | N2: 133.32 | O2: 127.32 | P2: 132.32 | Q2: 137.32 | R2: 135.32 | S2: 135.32 | T2: 143.32 | U2: 131.32 | V2: 129.32 | W2: 131.32 | X2: 129.32 | Y2: 142.32 | Z2: 135.32 | AA2: 126.32
A3: 2006 | B3: 219.88 | C3: 170.88 | D3: 166.88 | E3: 196.88 | F3: 176.88 | G3: 164.88 | H3: 172.88 | I3: 173.88 | J3: 189.88 | K3: 171.88 | L3: 166.88 | M3: 178.88 | N3: 161.88 | O3: 155.88 | P3: 160.88 | Q3: 165.88 | R3: 163.88 | S3: 163.88 | T3: 171.88 | U3: 159.88 | V3: 157.88 | W3: 159.88 | X3: 157.88 | Y3: 170.88 | Z3: 163.88 | AA3: 154.88
A4: 2007 | B4: 252.91 | C4: 203.91 | D4: 199.91 | E4: 229.91 | F4: 209.91 | G4: 197.91 | H4: 205.91 | I4: 206.91 | J4: 222.91 | K4: 204.91 | L4: 199.91 | M4: 211.91 | N4: 194.91 | O4: 188.91 | P4: 193.91 | Q4: 198.91 | R4: 196.91 | S4: 196.91 | T4: 204.91 | U4: 192.91 | V4: 190.91 | W4: 192.91 | X4: 190.91 | Y4: 203.91 | Z4: 196.91 | AA4: 187.91
A5: 2008 | B5: 281.46 | C5: 232.46 | D5: 228.46 | E5: 258.46 | F5: 238.46 | G5: 226.46 | H5: 234.46 | I5: 235.46 | J5: 251.46 | K5: 233.46 | L5: 228.46 | M5: 240.46 | N5: 223.46 | O5: 217.46 | P5: 222.46 | Q5: 227.46 | R5: 225.46 | S5: 225.46 | T5: 233.46 | U5: 221.46 | V5: 219.46 | W5: 221.46 | X5: 219.46 | Y5: 232.46 | Z5: 225.46 | AA5: 216.46
A6: 2009(1) | B6: 301.68 | C6: 252.68 | D6: 248.68 | E6: 278.68 | F6: 258.68 | G6: 246.68 | H6: 254.68 | I6: 255.68 | J6: 271.68 | K6: 253.68 | L6: 248.68 | M6: 260.68 | N6: 243.68 | O6: 237.68 | P6: 242.68 | Q6: 247.68 | R6: 245.68 | S6: 245.68 | T6: 253.68 | U6: 241.68 | V6: 239.68 | W6: 241.68 | X6: 239.68 | Y6: 252.68 | Z6: 245.68 | AA6: 236.68
A7: 2010(1) | B7: 312.28 | C7: 263.28 | D7: 259.28 | E7: 289.28 | F7: 269.28 | G7: 257.28 | H7: 265.28 | I7: 266.28 | J7: 282.28 | K7: 264.28 | L7: 259.28 | M7: 271.28 | N7: 254.28 | O7: 248.28 | P7: 253.28 | Q7: 258.28 | R7: 256.28 | S7: 256.28 | T7: 264.28 | U7: 252.28 | V7: 250.28 | W7: 252.28 | X7: 250.28 | Y7: 263.28 | Z7: 256.28 | AA7: 247.28
A8: 2011(1) | B8: 323.89 | C8: 274.89 | D8: 270.89 | E8: 300.89 | F8: 280.89 | G8: 268.89 | H8: 276.89 | I8: 277.89 | J8: 293.89 | K8: 275.89 | L8: 270.89 | M8: 282.89 | N8: 265.89 | O8: 259.89 | P8: 264.89 | Q8: 269.89 | R8: 267.89 | S8: 267.89 | T8: 275.89 | U8: 263.89 | V8: 261.89 | W8: 263.89 | X8: 261.89 | Y8: 274.89 | Z8: 267.89 | AA8: 258.89
A9: 2012 | B9: 337.05 | C9: 288.05 | D9: 284.05 | E9: 314.05 | F9: 294.05 | G9: 282.05 | H9: 290.05 | I9: 291.05 | J9: 307.05 | K9: 289.05 | L9: 284.05 | M9: 296.05 | N9: 279.05 | O9: 273.05 | P9: 278.05 | Q9: 283.05 | R9: 281.05 | S9: 281.05 | T9: 289.05 | U9: 277.05 | V9: 275.05 | W9: 277.05 | X9: 275.05 | Y9: 288.05 | Z9: 281.05 | AA9: 272.05
A10: 2013(2) | B10: 354.75 | C10: 305.75 | D10: 301.75 | E10: 331.75 | F10: 311.75 | G10: 299.75 | H10: 307.75 | I10: 308.75 | J10: 324.75 | K10: 306.75 | L10: 301.75 | M10: 313.75 | N10: 296.75 | O10: 290.75 | P10: 295.75 | Q10: 300.75 | R10: 298.75 | S10: 298.75 | T10: 306.75 | U10: 294.75 | V10: 292.75 | W10: 294.75 | X10: 292.75 | Y10: 305.75 | Z10: 298.75 | AA10: 289.75
A11: 2014(2) | B11: 375.48 | C11: 326.48 | D11: 322.48 | E11: 352.48 | F11: 332.48 | G11: 320.48 | H11: 328.48 | I11: 329.48 | J11: 345.48 | K11: 327.48 | L11: 322.48 | M11: 334.48 | N11: 317.48 | O11: 311.48 | P11: 316.48 | Q11: 321.48 | R11: 319.48 | S11: 319.48 | T11: 327.48 | U11: 315.48 | V11: 313.48 | W11: 315.48 | X11: 313.48 | Y11: 326.48 | Z11: 319.48 | AA11: 310.48
A12: 2015(2) | B12: 399.78 | C12: 350.78 | D12: 346.78 | E12: 376.78 | F12: 356.78 | G12: 344.78 | H12: 352.78 | I12: 353.78 | J12: 369.78 | K12: 351.78 | L12: 346.78 | M12: 358.78 | N12: 341.78 | O12: 335.78 | P12: 340.78 | Q12: 345.78 | R12: 343.78 | S12: 343.78 | T12: 351.78 | U12: 339.78 | V12: 337.78 | W12: 339.78 | X12: 337.78 | Y12: 350.78 | Z12: 343.78 | AA12: 334.78
A13: 2016(2) | B13: 430.66 | C13: 381.66 | D13: 377.66 | E13: 407.66 | F13: 387.66 | G13: 375.66 | H13: 383.66 | I13: 384.66 | J13: 400.66 | K13: 382.66 | L13: 377.66 | M13: 389.66 | N13: 372.66 | O13: 366.66 | P13: 371.66 | Q13: 376.66 | R13: 374.66 | S13: 374.66 | T13: 382.66 | U13: 370.66 | V13: 368.66 | W13: 370.66 | X13: 368.66 | Y13: 381.66 | Z13: 374.66 | AA13: 365.66
A14: 2017 | B14: 464.2 | C14: 415.2 | D14: 411.2 | E14: 441.2 | F14: 421.2 | G14: 409.2 | H14: 417.2 | I14: 418.2 | J14: 434.2 | K14: 416.2 | L14: 411.2 | M14: 423.2 | N14: 406.2 | O14: 400.2 | P14: 405.2 | Q14: 410.2 | R14: 408.2 | S14: 408.2 | T14: 416.2 | U14: 404.2 | V14: 402.2 | W14: 404.2 | X14: 402.2 | Y14: 415.2 | Z14: 408.2 | AA14: 399.2
A15: 2018(3) | B15: 504.04 | C15: 455.04 | D15: 451.04 | E15: 481.04 | F15: 461.04 | G15: 449.04 | H15: 457.04 | I15: 458.04 | J15: 474.04 | K15: 456.04 | L15: 451.04 | M15: 463.04 | N15: 446.04 | O15: 440.04 | P15: 445.04 | Q15: 450.04 | R15: 448.04 | S15: 448.04 | T15: 456.04 | U15: 444.04 | V15: 442.04 | W15: 444.04 | X15: 442.04 | Y15: 455.04 | Z15: 448.04 | AA15: 439.04
A16: 2019(3) | B16: 550.36 | C16: 501.36 | D16: 497.36 | E16: 527.36 | F16: 507.36 | G16: 495.36 | H16: 503.36 | I16: 504.36 | J16: 520.36 | K16: 502.36 | L16: 497.36 | M16: 509.36 | N16: 492.36 | O16: 486.36 | P16: 491.36 | Q16: 496.36 | R16: 494.36 | S16: 494.36 | T16: 502.36 | U16: 490.36 | V16: 488.36 | W16: 490.36 | X16: 488.36 | Y16: 501.36 | Z16: 494.36 | AA16: 485.36
A17: 2020(3) | B17: 596.49 | C17: 547.49 | D17: 543.49 | E17: 573.49 | F17: 553.49 | G17: 541.49 | H17: 549.49 | I17: 550.49 | J17: 566.49 | K17: 548.49 | L17: 543.49 | M17: 555.49 | N17: 538.49 | O17: 532.49 | P17: 537.49 | Q17: 542.49 | R17: 540.49 | S17: 540.49 | T17: 548.49 | U17: 536.49 | V17: 534.49 | W17: 536.49 | X17: 534.49 | Y17: 547.49 | Z17: 540.49 | AA17: 531.49
A18: 2021(3) | B18: 650.78 | C18: 601.78 | D18: 597.78 | E18: 627.78 | F18: 607.78 | G18: 595.78 | H18: 603.78 | I18: 604.78 | J18: 620.78 | K18: 602.78 | L18: 597.78 | M18: 609.78 | N18: 592.78 | O18: 586.78 | P18: 591.78 | Q18: 596.78 | R18: 594.78 | S18: 594.78 | T18: 602.78 | U18: 590.78 | V18: 588.78 | W18: 590.78 | X18: 588.78 | Y18: 601.78 | Z18: 594.78 | AA18: 585.78
A19: 2022(3) | B19: 787.75 | C19: 738.75 | D19: 734.75 | E19: 764.75 | F19: 744.75 | G19: 732.75 | H19: 740.75 | I19: 741.75 | J19: 757.75 | K19: 739.75 | L19: 734.75 | M19: 746.75 | N19: 729.75 | O19: 723.75 | P19: 728.75 | Q19: 733.75 | R19: 731.75 | S19: 731.75 | T19: 739.75 | U19: 727.75 | V19: 725.75 | W19: 727.75 | X19: 725.75 | Y19: 738.75 | Z19: 731.75 | AA19: 722.75
A20: 2023(3) | B20: 1347.74 | C20: 1298.74 | D20: 1294.74 | E20: 1324.74 | F20: 1304.74 | G20: 1292.74 | H20: 1300.74 | I20: 1301.74 | J20: 1317.74 | K20: 1299.74 | L20: 1294.74 | M20: 1306.74 | N20: 1289.74 | O20: 1283.74 | P20: 1288.74 | Q20: 1293.74 | R20: 1291.74 | S20: 1291.74 | T20: 1299.74 | U20: 1287.74 | V20: 1285.74 | W20: 1287.74 | X20: 1285.74 | Y20: 1298.74 | Z20: 1291.74 | AA20: 1282.74

Sheet regional_rental_cpi
A1: İstatistiki Bölge Birimleri Sınıflaması (2. Düzey) Statistical Regions (Level 2) | C1: 2005 | D1: 2006 | E1: 2007 | F1: 2008 | G1: 2009(1) | H1: 2010(1) | I1: 2011(1) | J1: 2012 | K1: 2013(2) | L1: 2014(2) | M1: 2015(2) | N1: 2016(2) | O1: 2017 | P1: 2018(3) | Q1: 2019(3) | R1: 2020(3) | S1: 2021(3) | T1: 2022(3) | U1: 2023(3)
A2: TR Türkiye
A3: TR10 (İstanbul) | C3: =cpi_june!E$2+regional_rent_relative_tuik!P5 -> 191.32 | D3: =cpi_june!E$3+regional_rent_relative_tuik!P5 -> 219.88 | E3: =cpi_june!E$4+regional_rent_relative_tuik!P5 -> 252.91 | F3: =cpi_june!E$5+regional_rent_relative_tuik!P5 -> 281.46 | G3: =cpi_june!E$6+regional_rent_relative_tuik!P5 -> 301.68 | H3: =cpi_june!E$7+regional_rent_relative_tuik!P5 -> 312.28 | I3: =cpi_june!E$8+regional_rent_relative_tuik!P5 -> 323.89 | J3: =cpi_june!E$9+regional_rent_relative_tuik!P5 -> 337.05 | K3: =cpi_june!E$10+regional_rent_relative_tuik!P5 -> 354.75 | L3: =cpi_june!E$11+regional_rent_relative_tuik!P5 -> 375.48 | M3: =cpi_june!E$12+regional_rent_relative_tuik!P5 -> 399.78 | N3: =cpi_june!E$13+regional_rent_relative_tuik!P5 -> 430.66 | O3: =cpi_june!E$14+regional_rent_relative_tuik!P5 -> 464.2 | P3: =cpi_june!E$15+regional_rent_relative_tuik!P5 -> 504.04 | Q3: =cpi_june!E$16+regional_rent_relative_tuik!P5 -> 550.36 | R3: =cpi_june!E$17+regional_rent_relative_tuik!P5 -> 596.49 | S3: =cpi_june!E$18+regional_rent_relative_tuik!P5 -> 650.78 | T3: =cpi_june!E$19+regional_rent_relative_tuik!P5 -> 787.75 | U3: =cpi_june!E$20+regional_rent_relative_tuik!P5 -> 1347.74
A4: TR21 (Tekirdağ, Edirne, Kırklareli) | C4: =cpi_june!E$2+regional_rent_relative_tuik!P6 -> 142.32 | D4: =cpi_june!E$3+regional_rent_relative_tuik!P6 -> 170.88 | E4: =cpi_june!E$4+regional_rent_relative_tuik!P6 -> 203.91 | F4: =cpi_june!E$5+regional_rent_relative_tuik!P6 -> 232.46 | G4: =cpi_june!E$6+regional_rent_relative_tuik!P6 -> 252.68 | H4: =cpi_june!E$7+regional_rent_relative_tuik!P6 -> 263.28 | I4: =cpi_june!E$8+regional_rent_relative_tuik!P6 -> 274.89 | J4: =cpi_june!E$9+regional_rent_relative_tuik!P6 -> 288.05 | K4: =cpi_june!E$10+regional_rent_relative_tuik!P6 -> 305.75 | L4: =cpi_june!E$11+regional_rent_relative_tuik!P6 -> 326.48 | M4: =cpi_june!E$12+regional_rent_relative_tuik!P6 -> 350.78 | N4: =cpi_june!E$13+regional_rent_relative_tuik!P6 -> 381.66 | O4: =cpi_june!E$14+regional_rent_relative_tuik!P6 -> 415.2 | P4: =cpi_june!E$15+regional_rent_relative_tuik!P6 -> 455.04 | Q4: =cpi_june!E$16+regional_rent_relative_tuik!P6 -> 501.36 | R4: =cpi_june!E$17+regional_rent_relative_tuik!P6 -> 547.49 | S4: =cpi_june!E$18+regional_rent_relative_tuik!P6 -> 601.78 | T4: =cpi_june!E$19+regional_rent_relative_tuik!P6 -> 738.75 | U4: =cpi_june!E$20+regional_rent_relative_tuik!P6 -> 1298.74
A5: TR22 (Balıkesir, Çanakkale) | C5: =cpi_june!E$2+regional_rent_relative_tuik!P7 -> 138.32 | D5: =cpi_june!E$3+regional_rent_relative_tuik!P7 -> 166.88 | E5: =cpi_june!E$4+regional_rent_relative_tuik!P7 -> 199.91 | F5: =cpi_june!E$5+regional_rent_relative_tuik!P7 -> 228.46 | G5: =cpi_june!E$6+regional_rent_relative_tuik!P7 -> 248.68 | H5: =cpi_june!E$7+regional_rent_relative_tuik!P7 -> 259.28 | I5: =cpi_june!E$8+regional_rent_relative_tuik!P7 -> 270.89 | J5: =cpi_june!E$9+regional_rent_relative_tuik!P7 -> 284.05 | K5: =cpi_june!E$10+regional_rent_relative_tuik!P7 -> 301.75 | L5: =cpi_june!E$11+regional_rent_relative_tuik!P7 -> 322.48 | M5: =cpi_june!E$12+regional_rent_relative_tuik!P7 -> 346.78 | N5: =cpi_june!E$13+regional_rent_relative_tuik!P7 -> 377.66 | O5: =cpi_june!E$14+regional_rent_relative_tuik!P7 -> 411.2 | P5: =cpi_june!E$15+regional_rent_relative_tuik!P7 -> 451.04 | Q5: =cpi_june!E$16+regional_rent_relative_tuik!P7 -> 497.36 | R5: =cpi_june!E$17+regional_rent_relative_tuik!P7 -> 543.49 | S5: =cpi_june!E$18+regional_rent_relative_tuik!P7 -> 597.78 | T5: =cpi_june!E$19+regional_rent_relative_tuik!P7 -> 734.75 | U5: =cpi_june!E$20+regional_rent_relative_tuik!P7 -> 1294.74
A6: TR31 (İzmir) | C6: =cpi_june!E$2+regional_rent_relative_tuik!P8 -> 168.32 | D6: =cpi_june!E$3+regional_rent_relative_tuik!P8 -> 196.88 | E6: =cpi_june!E$4+regional_rent_relative_tuik!P8 -> 229.91 | F6: =cpi_june!E$5+regional_rent_relative_tuik!P8 -> 258.46 | G6: =cpi_june!E$6+regional_rent_relative_tuik!P8 -> 278.68 | H6: =cpi_june!E$7+regional_rent_relative_tuik!P8 -> 289.28 | I6: =cpi_june!E$8+regional_rent_relative_tuik!P8 -> 300.89 | J6: =cpi_june!E$9+regional_rent_relative_tuik!P8 -> 314.05 | K6: =cpi_june!E$10+regional_rent_relative_tuik!P8 -> 331.75 | L6: =cpi_june!E$11+regional_rent_relative_tuik!P8 -> 352.48 | M6: =cpi_june!E$12+regional_rent_relative_tuik!P8 -> 376.78 | N6: =cpi_june!E$13+regional_rent_relative_tuik!P8 -> 407.66 | O6: =cpi_june!E$14+regional_rent_relative_tuik!P8 -> 441.2 | P6: =cpi_june!E$15+regional_rent_relative_tuik!P8 -> 481.04 | Q6: =cpi_june!E$16+regional_rent_relative_tuik!P8 -> 527.36 | R6: =cpi_june!E$17+regional_rent_relative_tuik!P8 -> 573.49 | S6: =cpi_june!E$18+regional_rent_relative_tuik!P8 -> 627.78 | T6: =cpi_june!E$19+regional_rent_relative_tuik!P8 -> 764.75 | U6: =cpi_june!E$20+regional_rent_relative_tuik!P8 -> 1324.74
A7: TR32 (Aydın, Denizli, Muğla) | C7: =cpi_june!E$2+regional_rent_relative_tuik!P9 -> 148.32 | D7: =cpi_june!E$3+regional_rent_relative_tuik!P9 -> 176.88 | E7: =cpi_june!E$4+regional_rent_relative_tuik!P9 -> 209.91 | F7: =cpi_june!E$5+regional_rent_relative_tuik!P9 -> 238.46 | G7: =cpi_june!E$6+regional_rent_relative_tuik!P9 -> 258.68 | H7: =cpi_june!E$7+regional_rent_relative_tuik!P9 -> 269.28 | I7: =cpi_june!E$8+regional_rent_relative_tuik!P9 -> 280.89 | J7: =cpi_june!E$9+regional_rent_relative_tuik!P9 -> 294.05 | K7: =cpi_june!E$10+regional_rent_relative_tuik!P9 -> 311.75 | L7: =cpi_june!E$11+regional_rent_relative_tuik!P9 -> 332.48 | M7: =cpi_june!E$12+regional_rent_relative_tuik!P9 -> 356.78 | N7: =cpi_june!E$13+regional_rent_relative_tuik!P9 -> 387.66 | O7: =cpi_june!E$14+regional_rent_relative_tuik!P9 -> 421.2 | P7: =cpi_june!E$15+regional_rent_relative_tuik!P9 -> 461.04 | Q7: =cpi_june!E$16+regional_rent_relative_tuik!P9 -> 507.36 | R7: =cpi_june!E$17+regional_rent_relative_tuik!P9 -> 553.49 | S7: =cpi_june!E$18+regional_rent_relative_tuik!P9 -> 607.78 | T7: =cpi_june!E$19+regional_rent_relative_tuik!P9 -> 744.75 | U7: =cpi_june!E$20+regional_rent_relative_tuik!P9 -> 1304.74
A8: TR33 (Manisa, Afyon, Kütahya, Uşak) | C8: =cpi_june!E$2+regional_rent_relative_tuik!P10 -> 136.32 | D8: =cpi_june!E$3+regional_rent_relative_tuik!P10 -> 164.88 | E8: =cpi_june!E$4+regional_rent_relative_tuik!P10 -> 197.91 | F8: =cpi_june!E$5+regional_rent_relative_tuik!P10 -> 226.46 | G8: =cpi_june!E$6+regional_rent_relative_tuik!P10 -> 246.68 | H8: =cpi_june!E$7+regional_rent_relative_tuik!P10 -> 257.28 | I8: =cpi_june!E$8+regional_rent_relative_tuik!P10 -> 268.89 | J8: =cpi_june!E$9+regional_rent_relative_tuik!P10 -> 282.05 | K8: =cpi_june!E$10+regional_rent_relative_tuik!P10 -> 299.75 | L8: =cpi_june!E$11+regional_rent_relative_tuik!P10 -> 320.48 | M8: =cpi_june!E$12+regional_rent_relative_tuik!P10 -> 344.78 | N8: =cpi_june!E$13+regional_rent_relative_tuik!P10 -> 375.66 | O8: =cpi_june!E$14+regional_rent_relative_tuik!P10 -> 409.2 | P8: =cpi_june!E$15+regional_rent_relative_tuik!P10 -> 449.04 | Q8: =cpi_june!E$16+regional_rent_relative_tuik!P10 -> 495.36 | R8: =cpi_june!E$17+regional_rent_relative_tuik!P10 -> 541.49 | S8: =cpi_june!E$18+regional_rent_relative_tuik!P10 -> 595.78 | T8: =cpi_june!E$19+regional_rent_relative_tuik!P10 -> 732.75 | U8: =cpi_june!E$20+regional_rent_relative_tuik!P10 -> 1292.74
A9: TR41 (Bursa, Eskişehir, Bilecik) | C9: =cpi_june!E$2+regional_rent_relative_tuik!P11 -> 144.32 | D9: =cpi_june!E$3+regional_rent_relative_tuik!P11 -> 172.88 | E9: =cpi_june!E$4+regional_rent_relative_tuik!P11 -> 205.91 | F9: =cpi_june!E$5+regional_rent_relative_tuik!P11 -> 234.46 | G9: =cpi_june!E$6+regional_rent_relative_tuik!P11 -> 254.68 | H9: =cpi_june!E$7+regional_rent_relative_tuik!P11 -> 265.28 | I9: =cpi_june!E$8+regional_rent_relative_tuik!P11 -> 276.89 | J9: =cpi_june!E$9+regional_rent_relative_tuik!P11 -> 290.05 | K9: =cpi_june!E$10+regional_rent_relative_tuik!P11 -> 307.75 | L9: =cpi_june!E$11+regional_rent_relative_tuik!P11 -> 328.48 | M9: =cpi_june!E$12+regional_rent_relative_tuik!P11 -> 352.78 | N9: =cpi_june!E$13+regional_rent_relative_tuik!P11 -> 383.66 | O9: =cpi_june!E$14+regional_rent_relative_tuik!P11 -> 417.2 | P9: =cpi_june!E$15+regional_rent_relative_tuik!P11 -> 457.04 | Q9: =cpi_june!E$16+regional_rent_relative_tuik!P11 -> 503.36 | R9: =cpi_june!E$17+regional_rent_relative_tuik!P11 -> 549.49 | S9: =cpi_june!E$18+regional_rent_relative_tuik!P11 -> 603.78 | T9: =cpi_june!E$19+regional_rent_relative_tuik!P11 -> 740.75 | U9: =cpi_june!E$20+regional_rent_relative_tuik!P11 -> 1300.74
A10: TR42 (Kocaeli, Sakarya, Düzce, Bolu, Yalova) | C10: =cpi_june!E$2+regional_rent_relative_tuik!P12 -> 145.32 | D10: =cpi_june!E$3+regional_rent_relative_tuik!P12 -> 173.88 | E10: =cpi_june!E$4+regional_rent_relative_tuik!P12 -> 206.91 | F10: =cpi_june!E$5+regional_rent_relative_tuik!P12 -> 235.46 | G10: =cpi_june!E$6+regional_rent_relative_tuik!P12 -> 255.68 | H10: =cpi_june!E$7+regional_rent_relative_tuik!P12 -> 266.28 | I10: =cpi_june!E$8+regional_rent_relative_tuik!P12 -> 277.89 | J10: =cpi_june!E$9+regional_rent_relative_tuik!P12 -> 291.05 | K10: =cpi_june!E$10+regional_rent_relative_tuik!P12 -> 308.75 | L10: =cpi_june!E$11+regional_rent_relative_tuik!P12 -> 329.48 | M10: =cpi_june!E$12+regional_rent_relative_tuik!P12 -> 353.78 | N10: =cpi_june!E$13+regional_rent_relative_tuik!P12 -> 384.66 | O10: =cpi_june!E$14+regional_rent_relative_tuik!P12 -> 418.2 | P10: =cpi_june!E$15+regional_rent_relative_tuik!P12 -> 458.04 | Q10: =cpi_june!E$16+regional_rent_relative_tuik!P12 -> 504.36 | R10: =cpi_june!E$17+regional_rent_relative_tuik!P12 -> 550.49 | S10: =cpi_june!E$18+regional_rent_relative_tuik!P12 -> 604.78 | T10: =cpi_june!E$19+regional_rent_relative_tuik!P12 -> 741.75 | U10: =cpi_june!E$20+regional_rent_relative_tuik!P12 -> 1301.74
A11: TR51 (Ankara) | C11: =cpi_june!E$2+regional_rent_relative_tuik!P13 -> 161.32 | D11: =cpi_june!E$3+regional_rent_relative_tuik!P13 -> 189.88 | E11: =cpi_june!E$4+regional_rent_relative_tuik!P13 -> 222.91 | F11: =cpi_june!E$5+regional_rent_relative_tuik!P13 -> 251.46 | G11: =cpi_june!E$6+regional_rent_relative_tuik!P13 -> 271.68 | H11: =cpi_june!E$7+regional_rent_relative_tuik!P13 -> 282.28 | I11: =cpi_june!E$8+regional_rent_relative_tuik!P13 -> 293.89 | J11: =cpi_june!E$9+regional_rent_relative_tuik!P13 -> 307.05 | K11: =cpi_june!E$10+regional_rent_relative_tuik!P13 -> 324.75 | L11: =cpi_june!E$11+regional_rent_relative_tuik!P13 -> 345.48 | M11: =cpi_june!E$12+regional_rent_relative_tuik!P13 -> 369.78 | N11: =cpi_june!E$13+regional_rent_relative_tuik!P13 -> 400.66 | O11: =cpi_june!E$14+regional_rent_relative_tuik!P13 -> 434.2 | P11: =cpi_june!E$15+regional_rent_relative_tuik!P13 -> 474.04 | Q11: =cpi_june!E$16+regional_rent_relative_tuik!P13 -> 520.36 | R11: =cpi_june!E$17+regional_rent_relative_tuik!P13 -> 566.49 | S11: =cpi_june!E$18+regional_rent_relative_tuik!P13 -> 620.78 | T11: =cpi_june!E$19+regional_rent_relative_tuik!P13 -> 757.75 | U11: =cpi_june!E$20+regional_rent_relative_tuik!P13 -> 1317.74
A12: TR52 (Konya, Karaman) | C12: =cpi_june!E$2+regional_rent_relative_tuik!P14 -> 143.32 | D12: =cpi_june!E$3+regional_rent_relative_tuik!P14 -> 171.88 | E12: =cpi_june!E$4+regional_rent_relative_tuik!P14 -> 204.91 | F12: =cpi_june!E$5+regional_rent_relative_tuik!P14 -> 233.46 | G12: =cpi_june!E$6+regional_rent_relative_tuik!P14 -> 253.68 | H12: =cpi_june!E$7+regional_rent_relative_tuik!P14 -> 264.28 | I12: =cpi_june!E$8+regional_rent_relative_tuik!P14 -> 275.89 | J12: =cpi_june!E$9+regional_rent_relative_tuik!P14 -> 289.05 | K12: =cpi_june!E$10+regional_rent_relative_tuik!P14 -> 306.75 | L12: =cpi_june!E$11+regional_rent_relative_tuik!P14 -> 327.48 | M12: =cpi_june!E$12+regional_rent_relative_tuik!P14 -> 351.78 | N12: =cpi_june!E$13+regional_rent_relative_tuik!P14 -> 382.66 | O12: =cpi_june!E$14+regional_rent_relative_tuik!P14 -> 416.2 | P12: =cpi_june!E$15+regional_rent_relative_tuik!P14 -> 456.04 | Q12: =cpi_june!E$16+regional_rent_relative_tuik!P14 -> 502.36 | R12: =cpi_june!E$17+regional_rent_relative_tuik!P14 -> 548.49 | S12: =cpi_june!E$18+regional_rent_relative_tuik!P14 -> 602.78 | T12: =cpi_june!E$19+regional_rent_relative_tuik!P14 -> 739.75 | U12: =cpi_june!E$20+regional_rent_relative_tuik!P14 -> 1299.74
A13: TR61 (Antalya, Isparta, Burdur) | C13: =cpi_june!E$2+regional_rent_relative_tuik!P15 -> 138.32 | D13: =cpi_june!E$3+regional_rent_relative_tuik!P15 -> 166.88 | E13: =cpi_june!E$4+regional_rent_relative_tuik!P15 -> 199.91 | F13: =cpi_june!E$5+regional_rent_relative_tuik!P15 -> 228.46 | G13: =cpi_june!E$6+regional_rent_relative_tuik!P15 -> 248.68 | H13: =cpi_june!E$7+regional_rent_relative_tuik!P15 -> 259.28 | I13: =cpi_june!E$8+regional_rent_relative_tuik!P15 -> 270.89 | J13: =cpi_june!E$9+regional_rent_relative_tuik!P15 -> 284.05 | K13: =cpi_june!E$10+regional_rent_relative_tuik!P15 -> 301.75 | L13: =cpi_june!E$11+regional_rent_relative_tuik!P15 -> 322.48 | M13: =cpi_june!E$12+regional_rent_relative_tuik!P15 -> 346.78 | N13: =cpi_june!E$13+regional_rent_relative_tuik!P15 -> 377.66 | O13: =cpi_june!E$14+regional_rent_relative_tuik!P15 -> 411.2 | P13: =cpi_june!E$15+regional_rent_relative_tuik!P15 -> 451.04 | Q13: =cpi_june!E$16+regional_rent_relative_tuik!P15 -> 497.36 | R13: =cpi_june!E$17+regional_rent_relative_tuik!P15 -> 543.49 | S13: =cpi_june!E$18+regional_rent_relative_tuik!P15 -> 597.78 | T13: =cpi_june!E$19+regional_rent_relative_tuik!P15 -> 734.75 | U13: =cpi_june!E$20+regional_rent_relative_tuik!P15 -> 1294.74
A14: TR62 (Adana, Mersin) | C14: =cpi_june!E$2+regional_rent_relative_tuik!P16 -> 150.32 | D14: =cpi_june!E$3+regional_rent_relative_tuik!P16 -> 178.88 | E14: =cpi_june!E$4+regional_rent_relative_tuik!P16 -> 211.91 | F14: =cpi_june!E$5+regional_rent_relative_tuik!P16 -> 240.46 | G14: =cpi_june!E$6+regional_rent_relative_tuik!P16 -> 260.68 | H14: =cpi_june!E$7+regional_rent_relative_tuik!P16 -> 271.28 | I14: =cpi_june!E$8+regional_rent_relative_tuik!P16 -> 282.89 | J14: =cpi_june!E$9+regional_rent_relative_tuik!P16 -> 296.05 | K14: =cpi_june!E$10+regional_rent_relative_tuik!P16 -> 313.75 | L14: =cpi_june!E$11+regional_rent_relative_tuik!P16 -> 334.48 | M14: =cpi_june!E$12+regional_rent_relative_tuik!P16 -> 358.78 | N14: =cpi_june!E$13+regional_rent_relative_tuik!P16 -> 389.66 | O14: =cpi_june!E$14+regional_rent_relative_tuik!P16 -> 423.2 | P14: =cpi_june!E$15+regional_rent_relative_tuik!P16 -> 463.04 | Q14: =cpi_june!E$16+regional_rent_relative_tuik!P16 -> 509.36 | R14: =cpi_june!E$17+regional_rent_relative_tuik!P16 -> 555.49 | S14: =cpi_june!E$18+regional_rent_relative_tuik!P16 -> 609.78 | T14: =cpi_june!E$19+regional_rent_relative_tuik!P16 -> 746.75 | U14: =cpi_june!E$20+regional_rent_relative_tuik!P16 -> 1306.74
... A28: TRC3 (Mardin, Batman, Şırnak, Siirt) | C28: =cpi_june!E$2+regional_rent_relative_tuik!P30 -> 126.32 | D28: =cpi_june!E$3+regional_rent_relative_tuik!P30 -> 154.88 | E28: =cpi_june!E$4+regional_rent_relative_tuik!P30 -> 187.91 | F28: =cpi_june!E$5+regional_rent_relative_tuik!P30 -> 216.46 | G28: =cpi_june!E$6+regional_rent_relative_tuik!P30 -> 236.68 | H28: =cpi_june!E$7+regional_rent_relative_tuik!P30 -> 247.28 | I28: =cpi_june!E$8+regional_rent_relative_tuik!P30 -> 258.89 | J28: =cpi_june!E$9+regional_rent_relative_tuik!P30 -> 272.05 | K28: =cpi_june!E$10+regional_rent_relative_tuik!P30 -> 289.75 | L28: =cpi_june!E$11+regional_rent_relative_tuik!P30 -> 310.48 | M28: =cpi_june!E$12+regional_rent_relative_tuik!P30 -> 334.78 | N28: =cpi_june!E$13+regional_rent_relative_tuik!P30 -> 365.66 | O28: =cpi_june!E$14+regional_rent_relative_tuik!P30 -> 399.2 | P28: =cpi_june!E$15+regional_rent_relative_tuik!P30 -> 439.04 | Q28: =cpi_june!E$16+regional_rent_relative_tuik!P30 -> 485.36 | R28: =cpi_june!E$17+regional_rent_relative_tuik!P30 -> 531.49 | S28: =cpi_june!E$18+regional_rent_relative_tuik!P30 -> 585.78 | T28: =cpi_june!E$19+regional_rent_relative_tuik!P30 -> 722.75 | U28: =cpi_june!E$20+regional_rent_relative_tuik!P30 -> 1282.74

Sheet cpi_june
A1: year | C1: month | D1: cpi | E1: rental_cpi
A2: 2005 | B2: Haziran | C2: June | D2: 116.81 | E2: 141.32 | F2: =E2/D2 -> 1.2098279
A3: 2006 | B3: Haziran | C3: June | D3: 128.63 | E3: 169.88 | F3: =E3/D3 -> 1.3206872
A4: 2007 | B4: Haziran | C4: June | D4: 139.69 | E4: 202.91 | F4: =E4/D4 -> 1.4525736
A5: 2008 | B5: Haziran | C5: June | D5: 154.51 | E5: 231.46 | F5: =E5/D5 -> 1.498026
A6: 2009 | B6: Haziran | C6: June | D6: 163.37 | E6: 251.68 | F6: =E6/D6 -> 1.5405521
A7: 2010 | B7: Haziran | C7: June | D7: 177.04 | E7: 262.28 | F7: =E7/D7 -> 1.4814731
A8: 2011 | B8: Haziran | C8: June | D8: 188.08 | E8: 273.89 | F8: =E8/D8 -> 1.456242
A9: 2012 | B9: Haziran | C9: June | D9: 204.76 | E9: 287.05 | F9: =E9/D9 -> 1.4018851
A10: 2013 | B10: Haziran | C10: June | D10: 221.75 | E10: 304.75 | F10: =E10/D10 -> 1.3742954
A11: 2014 | B11: Haziran | C11: June | D11: 242.07 | E11: 325.48 | F11: =E11/D11 -> 1.3445698
A12: 2015 | B12: Haziran | C12: June | D12: 259.51 | E12: 349.78 | F12: =E12/D12 -> 1.3478479
A13: 2016 | B13: Haziran | C13: June | D13: 279.33 | E13: 380.66 | F13: =E13/D13 -> 1.3627609
... A21: 2024 | B21: Haziran | C21: June | D21: 2319.29 | E21: 2902.27 | F21: =E21/D21 -> 1.2513614

Sheet cpi
A1: Tüketici fiyat endeksi (2003=100) ana grup ve alt ana gruplara göre endeks rakamları, 2005-2025
A2: Consumer price index (2003=100) according to main and sub-main groups, 2005-2025
D3: 0 | E3: 01 | F3: 02 | G3: 03 | H3: 04 | I3: 05 | J3: 06 | K3: 07 | L3: 08 | M3: 09 | N3: 10 | O3: 11 | P3: 12 | Q3: 011 | R3: 012 | S3: 021 | T3: 022 | U3: 031 | V3: 032 | W3: 041 | X3: 043 | Y3: 044 | Z3: 045 | AA3: 051 | AB3: 052 | AC3: 053 | AD3: 054 | AE3: 055 | AF3: 056 | AG3: 061 | AH3: 062 | AI3: 063 | AJ3: 071 | AK3: 072 | AL3: 073 | AM3: 081 | AN3: 082 | AO3: 083 | AP3: 091 | AQ3: 092 | AR3: 093 | AS3: 094 | AT3: 095 | AU3: 096 | AV3: 101 | AW3: 102 | AX3: 104 | AY3: 105 | AZ3: 111 | BA3: 112 | BB3: 121 | BC3: 123 | BD3: 124 | BE3: 125 | BF3: 126 | BG3: 127 | BH3: 0111 | BI3: 0112 | BJ3: 0113 | BK3: 0114 | BL3: 0115 | BM3: 0116 | BN3: 0117 | BO3: 0118 | BP3: 0119 | BQ3: 0121 | BR3: 0122 | BS3: 0211 | BT3: 0212 | BU3: 0213 | BV3: 0220 | BW3: 0312 | BX3: 0313 | BY3: 0314 | BZ3: 0321 | CA3: 0322 | CB3: 0411 | CC3: 0431 | CD3: 0441 | CE3: 0451 | CF3: 0452 | CG3: 0454 | CH3: 0511 | CI3: 0512 | CJ3: 0520 | CK3: 0531 | CL3: 0532 | CM3: 0533 | CN3: 0540 | CO3: 0552 | CP3: 0561 | CQ3: 0562 | CR3: 0611 | CS3: 0612 | CT3: 0613 | CU3: 0621 | CV3: 0622 | CW3: 0623 | CX3: 0630 | CY3: 0711 | CZ3: 0712 | DA3: 0713 | DB3: 0721 | DC3: 0722 | DD3: 0723 | DE3: 0724 | DF3: 0731 | DG3: 0732 | DH3: 0733 | DI3: 0734 | DJ3: 0736 | DK3: 0810 | DL3: 0820 | DM3: 0830 | DN3: 0911 | DO3: 0913 | DP3: 0915 | DQ3: 0922 | DR3: 0931 | DS3: 0932 | DT3: 0934 | DU3: 0935 | DV3: 0941 | DW3: 0942 | DX3: 0943 | DY3: 0951 | DZ3: 0952 | EA3: 0954 | EB3: 0960 | EC3: 1010 | ED3: 1020 | EE3: 1040 | EF3: 1050 | EG3: 1110 | EH3: 1120 | EI3: 1211 | EJ3: 1212 | EK3: 1213 | EL3: 1231 | EM3: 1232 | EN3: 1240 | EO3: 1252 | EP3: 1253 | EQ3: 1254 | ER3: 1262 | ES3: 1270 | ET3: 01111 | EU3: 01112 | EV3: 01113 | EW3: 01114 | EX3: 01115 | EY3: 01116 | EZ3: 01122 | FA3: 01124 | FB3: 01125 | FC3: 01126 | FD3: 01127 | FE3: 01131 | FF3: 01133 | FG3: 01141 | FH3: 01143 | FI3: 01144 | FJ3: 01145 | FK3: 01151 | FL3: 01152 | FM3: 01153 | FN3: 01161 | FO3: 01162 | FP3: 01171 | FQ3: 01172 | FR3: 01174 | FS3: 01175 | FT3: 01181 | FU3: 01182 | FV3: 01183 | FW3: 01184 | FX3: 01190 | FY3: 01211 | FZ3: 01212 | GA3: 01213 | GB3: 01221 | GC3: 01222 | GD3: 01223 | GE3: 02110 | GF3: 02121 | GG3: 02130 | GH3: 02201 | GI3: 03121 | GJ3: 03122 | GK3: 03123 | GL3: 03124 | GM3: 03130 | GN3: 03140 | GO3: 03211 | GP3: 03212 | GQ3: 03213 | GR3: 03220 | GS3: 04111 | GT3: 04310 | GU3: 04410 | GV3: 04510 | GW3: 04521 | GX3: 04522 | GY3: 04540 | GZ3: 05111 | HA3: 05112 | HB3: 05113 | HC3: 05120 | HD3: 05200 | HE3: 05311 | HF3: 05312 | HG3: 05313 | HH3: 05314 | HI3: 05315 | HJ3: 05320 | HK3: 05330 | HL3: 05401 | HM3: 05402 | HN3: 05403 | HO3: 05521 | HP3: 05522 | HQ3: 05611 | HR3: 05612 | HS3: 05621 | HT3: 05622 | HU3: 06110 | HV3: 06120 | HW3: 06131 | HX3: 06132 | HY3: 06212 | HZ3: 06220 | IA3: 06231 | IB3: 06300 | IC3: 07111 | ID3: 07113 | IE3: 07120 | IF3: 07130 | IG3: 07210 | IH3: 07220 | II3: 07230 | IJ3: 07240 | IK3: 07311 | IL3: 07312 | IM3: 07321 | IN3: 07322 | IO3: 07323 | IP3: 07330 | IQ3: 07340 | IR3: 07360 | IS3: 08100 | IT3: 08200 | IU3: 08300 | IV3: 09111 | IW3: 09130 | IX3: 09150 | IY3: 09220 | IZ3: 09310 | JA3: 09320 | JB3: 09340 | JC3: 09350 | JD3: 09410 | JE3: 09421 | JF3: 09422 | JG3: 09430 | JH3: 09510 | JI3: 09520 | JJ3: 09540 | JK3: 09600 | JL3: 10100 | JM3: 10200 | JN3: 10400 | JO3: 10500 | JP3: 11101 | JQ3: 11102 | JR3: 11201 | JS3: 11202 | JT3: 12111 | JU3: 12112 | JV3: 12120 | JW3: 12130 | JX3: 12310 | JY3: 12321 | JZ3: 12322 | KA3: 12400 | KB3: 12520 | KC3: 12530 | KD3: 12540 | KE3: 12620 | KF3: 12700
A4: Yıl | B4: Ay | D4: Genel | E4: Gıda ve alkolsüz içecekler | F4: Alkollü içecekler ve tütün | G4: Giyim ve ayakkabı | H4: Konut, su, elektrik, gaz ve diğer yakıtlar | I4: Mobilya, ev aletleri ve ev bakım hizmetleri | J4: Sağlık | K4: Ulaştırma | L4: Haberleşme | M4: Eğlence ve kültür | N4: Eğitim | O4: Lokanta ve oteller | P4: Çeşitli mal ve hizmetler | Q4: Gıda | R4: Alkolsüz içecekler | S4: Alkollü içecekler | T4: Tütün | U4: Giyim | V4: Ayakkabı | W4: Gerçek kira | X4: Konutun bakım ve onarımı | Y4: Su (Şebeke suyu) ve konutla ilgili çeşitli hizmetler | Z4: Elektrik, gaz ve diğer yakıtlar | AA4: Mobilya, mefruşat, halı ve diğer yer döşemeleri | AB4: Ev içi tekstil | AC4: Ev aletleri | AD4: Züccaciye, yemek takımı ve hanehalkı aletleri | AE4: Ev ve bahçe araç gereçleri | AF4: Ev bakım için mal ve hizmetler | AG4: Tıbbi ürünler, aletler ve malzemeler | AH4: Ayakta tedavi hizmetleri | AI4: Yataklı tedavi hizmetleri | AJ4: Araç satın alımı | AK4: Kişisel ulaştırma araçlarının işletimi | AL4: Ulaştırma hizmetleri | AM4: Posta hizmetleri | AN4: Telefon ve telefaks ekipmanı | AO4: Telefon ve telefaks hizmetleri | AP4: Görsel-işitsel sistemle (audıo-vısual), fotoğrafla ve veri işlemle ile ilgili ekipman | AQ4: Diğer temel dayanıklı eğlence ve kültür araçları | AR4: Diğer eğlence araçları ve malzemeleri, bahçe ve evcil hayvanlara ilişkin ürünler, hizmetler | AS4: Eğlence ve kültür hizmetleri | AT4: Gazete, kitap ve kırtasiye | AU4: Paket turlar | AV4: Okul öncesi eğitim ve ilköğretim | AW4: Orta öğretim | AX4: Üniversite eğitimi | AY4: Düzeyi belirlenemeyen eğitim programları | AZ4: Yemek hizmetleri | BA4: Konaklama hizmetleri | BB4: Kişisel bakım | BC4: Başka yerde sınıflandırılamayan kişisel bakım ürünleri | BD4: Sosyal hizmetler | BE4: Sigorta | BF4: Başka yerde sınıflandırılmayan mali hizmetler | BG4: Başka yerde sınıflandırılmayan diğer hizmetler | BH4: Ekmek ve tahıllar | BI4: Et | BJ4: Balık | BK4: Süt, peynir ve yumurta | BL4: Katı ve sıvı yağlar | BM4: Meyveler | BN4: Sebze | BO4: Şeker, reçel, bal, çikolata ve şekerlemeler | BP4: Başka yerde sınıflandırılamayan diğer gıda ürünleri | BQ4: Kahve, çay ve kakao | BR4: Maden suyu, alkolsüz içecekler, meyve ve sebze suları | BS4: İçkiler | BT4: Şarap | BU4: Bira | BV4: Tütün | BW4: Giysiler | BX4: Diğer giysi çeşitleri ve giysi aksesuarları | BY4: Kuru temizleme, giysi onarımı, dikişi ve kiralanması | BZ4: Ayakkabı ve diğer ayak giyecekleri | CA4: Ayakkabı onarımı ve kiralanması | CB4: Kiracı tarafından ödenen gerçek kira | CC4: Konutun bakım ve onarımı için malzemeler | CD4: Su (şebeke suyu) | CE4: Elektrik | CF4: Gaz | CG4: Katı yakıtlar | CH4: Mobilya ve mefruşat | CI4: Halı ve diğer yer döşemeleri | CJ4: Ev içi tekstil | CK4: Elektrikli ve elektriksiz büyük ev aletleri | CL4: Elektrikli küçük ev aletleri | CM4: Ev aletlerinin onarımı | CN4: Züccaciye, yemek takımı ve hanehalkı aletleri | CO4: Küçük araçlar ve çeşitli aksesuarlar | CP4: Dayanıksız ev malzemeleri | CQ4: Ev işi ve hanehalkı hizmetleri | CR4: İlaçlar | CS4: Diğer sağlık ürünleri | CT4: Tedavi edici aletler ve malzemeler | CU4: Tıbbi hizmetler | CV4: Dişçilik ücreti | CW4: Diğer tıbbi hizmetler | CX4: Temel hastahane hizmetleri | CY4: Motorlu araçlar | CZ4: Motosikletler | DA4: Bisikletler | DB4: Kişisel ulaştırma araçlarının yedek parça ve aksesuarları | DC4: Kişisel ulaştırma araçlarının yakıt ve yağları | DD4: Kişisel ulaştırma araçlarının bakım ve onarımı | DE4: Kişisel ulaştırma araçları ile ilgili diğer hizmetler | DF4: Demiryolu ile yolcu taşımacılığı | DG4: Karayolu ile yolcu taşımacılığı | DH4: Havayolu ile yolcu taşımacılığı | DI4: Deniz ve yurtiçi su yolu ile yolcu taşımacılığı | DJ4: Diğer satınalınan ulaştırma hizmetleri | DK4: Posta hizmetleri | DL4: Telefon ve telefaks ekipmanı | DM4: Telefon ve telefaks hizmetleri | DN4: Ses alma, kayıt, ses ve resim kopyalama ile ilgili ekipman | DO4: Veri işlem ekipmanı | DP4: Görsel ve işitsel fotoğraf ve veri işleme ile ilgili araçların onarımı | DQ4: Müzik enstrümanları ve kapalı yerlerde kullanılan temel eğlence araçları | DR4: Oyunlar, oyuncaklar ve hobiler | DS4: Spor, kamp ve açık hava eğlence malzemeleri | DT4: Evcil hayvanlar ve bununla ilgili diğer ürünler | DU4: Evcil hayvanlarla ilgili veterinerlik ve diğer hizmetler | DV4: Eğlence ve spor hizmetleri | DW4: Kültür hizmetleri | DX4: Şans oyunları | DY4: Kitaplar | DZ4: Gazete ve dergiler | EA4: Kırtasiye ve çizim malzemeleri | EB4: Paket turlar | EC4: Okul öncesi eğitim ve ilköğretim | ED4: Orta öğretim | EE4: Üniversite eğitimi | EF4: Düzeyi belirlenemeyen eğitim programları | EG4: Yiyecek ve içecek hizmetleri | EH4: Konaklama hizmetleri | EI4: Kuaförler ve kişisel bakım merkezleri | EJ4: Kişisel bakımda kullanılan elektrikli aletler | EK4: Kişisel bakımda kullanılan diğer aletler, ürünler ve eşyalar | EL4: Mücevherler, saat ve kol saatleri | EM4: Diğer kişisel aksesuarlar | EN4: Sosyal hizmetler | EO4: Konut sigortası | EP4: Sağlık sigortası | EQ4: Ulaştırma sigortası | ER4: Başka yerde sınıflandırılmayan diğer mali hizmetler | ES4: Başka yerde sınıflandırılmayan diğer hizmetler | ET4: Pirinç | EU4: Un ve diğer tahıllar | EV4: Ekmek | EW4: Diğer fırıncılık ürünleri (bisküvi, kek, kraker, yufka, baklava vb.) | EX4: Makarna çeşitleri | EY4: Kahvaltılık tahıl ürünleri | EZ4: Dana eti | FA4: Kuzu eti | FB4: Tavuk eti | FC4: Diğer etler ve yenilebilir sakatatlar | FD4: Şarküteri ürünleri (sucuk, sosis, salam vb.) | FE4: Taze balık | FF4: Konserve edilmiş veya işlenmiş balık | FG4: Süt | FH4: Diğer süt ürünleri (yoğurt, hazır sütlü tatlı vb.) | FI4: Peynir | FJ4: Yumurta | FK4: Tereyağı | FL4: Margarin | FM4: Sıvı yağlar (zeytinyağı, ayçiçek yağı) | FN4: Taze meyveler | FO4: Kuru meyve ve sert kabuklu yemişler | FP4: Taze sebzeler (patates hariç) | FQ4: Patates | FR4: Kuru baklagiller | FS4: Konserve edilmiş veya işlenmiş sebze içerikli ürünler (salça, turşu, zeytin vb. dahil) | FT4: Şeker | FU4: Reçel, marmelat, bal vb. ürünler | FV4: Çikolata ve şekerlemeler | FW4: Dondurma | FX4: Başka yerde sınıflandırılamayan diğer gıda ürünleri (tuz, sirke, ketçap, mayonez vb.) | FY4: Kahve | FZ4: Çay ve bitki çayları | GA4: Toz kakao | GB4: Su ve maden suyu | GC4: Alkolsüz içecekler (meşrubat, ayran vb.) | GD4: Meyve ve sebze suları | GE4: Alkollü içecekler (rakı, viski, votka vb.) | GF4: Şarap | GG4: Bira | GH4: Sigaralar | GI4: Erkek giyim | GJ4: Kadın giyim | GK4: Çocuk giyim | GL4: Bebek giyim | GM4: Diğer giyim eşyaları ve aksesuarları (kravat, kemer, eşarp vb.) | GN4: Giyim eşyalarının temizlenmesi ve tadilatı | GO4: Erkek ayakkabısı | GP4: Kadın ayakkabısı | GQ4: Çocuk ve bebek ayakkabısı | GR4: Ayakkabı bakım ve tamiri | GS4: Gerçek kira | GT4: Konutun bakım ve onarımı için malzemeler | GU4: Su (şebeke suyu) | GV4: Elektrik | GW4: Doğalgaz ve ilgili abonelik ücretleri | GX4: Tüpgaz (ev tüpü) | GY4: Katı yakıtlar (odun, kömür) | GZ4: Mutfak mobilyaları | HA4: Yatak odası mobilyaları | HB4: Yemek odası ve oturma odası mobilyaları | HC4: Halı | HD4: Ev tekstili | HE4: Buzdolabı, derin dondurucu | HF4: Çamaşır ve bulaşık makineleri | HG4: Fırın, ocak ve fırınlı ocak | HH4: Klima ve ısıtıcılar | HI4: Diğer büyük ev aletleri (elektrikli süpürge vb.) | HJ4: Elektrikli küçük ev aletleri | HK4: Ev aletlerinin onarımı | HL4: Cam, porselen, seramik vb. mutfak eşyaları | HM4: Çatal-bıçak takımı | HN4: Elektriksiz mutfak eşyaları ve ev gereçleri (tencere, tava, çaydanlık vb.) | HO4: Çeşitli küçük aksesuarlar (pil, ampul vb.) | HP4: Evle ilgili küçük bakım-tamir mal ve hizmetleri | HQ4: Ev ile ilgili temizlik malzemeleri (deterjan, yumuşatıcı vb.) | HR4: Ev ile ilgili diğer temizlik malzemeleri (bulaşık süngeri, çöp torbası vb.) | HS4: Ev içi hizmetler (gündelikçi ücreti) | HT4: Ev eşyalarının yıkanması ve temizlenmesi hizmetleri | HU4: İlaçlar | HV4: Diğer sağlık ürünleri (hasta bezi vb.) | HW4: Gözlükler ve kontakt lensler | HX4: Diğer sağlık ekipmanları (tansiyon aleti vb.) | HY4: Ayakta tedavi hizmetleri (muayene ücreti, muayene katkı payı vb.) | HZ4: Diş hekimliği hizmetleri | IA4: Tıbbi tahlil, analiz ve röntgen çekim hizmetleri | IB4: Hastane hizmetleri | IC4: Dizel otomobiller (sıfır km) | ID4: Benzinli ve elektrikli otomobiller (sıfır km) | IE4: Motosikletler | IF4: Bisikletler | IG4: Kişisel ulaştırma araçlarının yedek parça ve aksesuarları | IH4: Kişisel ulaştırma araçlarının yakıt ve yağları (benzin, motorin, motor yağı) | II4: Kişisel ulaştırma araçlarının bakım ve onarımı | IJ4: Kişisel ulaştırma araçları ile ilgili diğer hizmetler (köprü ve otoban geçiş ücretleri dahil) | IK4: Demiryolu ile şehir içi yolcu taşımacılığı | IL4: Demiryolu ile şehirler arası yolcu taşımacılığı | IM4: Otobüs ile şehir içi yolcu taşımacılığı | IN4: Taksi ile şehir içi yolcu taşımacılığı | IO4: Karayolu ile şehirler arası yolcu taşımacılığı | IP4: Havayolu ile yolcu taşımacılığı | IQ4: Deniz ve yurt içi su yolu ile yolcu taşımacılığı | IR4: Diğer satın alınan ulaştırma hizmetleri (nakliye, kargo vb.) | IS4: Posta hizmetleri | IT4: Mobil telefon, ekipman ve aksesuarları | IU4: Telefon (mobil ve sabit hat) ve internet ücretleri | IV4: Televizyonlar | IW4: Bilgisayar ve ekipmanları | IX4: Görsel ve işitsel cihazların bakım ve onarımı | IY4: Müzik enstrümanları | IZ4: Oyunlar, oyuncaklar ve hobiler | JA4: Spor, kamp ve açık hava eğlence malzemeleri | JB4: Evcil hayvanlar ile ilgili ürünler | JC4: Evcil hayvanlarla ilgili veterinerlik ve diğer hizmetler | JD4: Eğlence ve spor hizmetleri | JE4: Fotoğrafçılık hizmetleri | JF4: Diğer eğlence ve kültür hizmetleri (sinema, tiyatro vb.) | JG4: Şans oyunları | JH4: Kitaplar | JI4: Gazete ve dergiler | JJ4: Kırtasiye malzemeleri | JK4: Paket turlar | JL4: Okul öncesi eğitim ve ilköğretim | JM4: Orta öğretim | JN4: Üniversite eğitimi | JO4: Yaygın eğitim hizmetleri (dershane ve kurslar) | JP4: Lokanta, pastane, kafe vb. yerlerde yenen yemekler | JQ4: Lokanta, pastane, kafe vb. yerlerde içilen içecekler | JR4: Otel, pansyion vb. yerlerde konaklama hizmetleri | JS4: Diğer konaklama hizmetleri (öğrenci yurtları) | JT4: Erkekler için kuaförlük hizmetleri | JU4: Kadınlar için kuaförlük hizmetleri | JV4: Kişisel bakımda kullanılan elektrikli aletler | JW4: Kişisel hijyen ve bakım için kullanılan ürünler, kozmetikler | JX4: Mücevheratlar, saat ve kol saatleri | JY4: Seyahat malzemeleri ve diğer kişisel aksesuarlar | JZ4: Başka yerde sınıflandırılmamış diğer kişisel aksesuarlar | KA4: Çocuk bakım hizmetleri (kreşler) | KB4: Konut sigortası | KC4: Sağlık sigortası | KD4: Ulaştırma sigortası | KE4: Başka yerde sınıflandırılmayan diğer mali hizmetler (para havale ücreti vb.) | KF4: Başka yerde sınıflandırılmayan diğer hizmetler (noterlik, avukatlık hizmetleri vb.)
A5: Year | B5: Months | D5: General | E5: Food and non-alcoholic beverages | F5: Alcoholic beverages and tobacco | G5: Clothing and footwear | H5: Housing, water, electricity, gas and other fuels | I5: Furnishings, household equipment, routine maintenance of the house | J5: Health | K5: Transport | L5: Communications | M5: Recreation and culture | N5: Education | O5: Hotels, cafes and restaurants | P5: Miscellaneous goods and services | Q5: Food | R5: Non-alcoholic beverages | S5: Alcoholic beverages | T5: Tobacco | U5: Clothing | V5: Footwear | W5: Actual rentals for housing | X5: Maintenance and repair of the dwelling | Y5: Water supply and miscellaneous services relating to the dwelling | Z5: Electricity, gas and other fuels | AA5: Furniture and furnishings, carpets and other floor coverings | AB5: Household textiles | AC5: Household appliances | AD5: Glassware, tableware and household utensils | AE5: Tools and equipment for house and garden | AF5: Goods and services for routine household maintenance | AG5: Medical products, appliances and equipment | AH5: Outpatient services | AI5: Hospital services | AJ5: Purchase of vehicles | AK5: Operation of personal transport equipment | AL5: Transport services | AM5: Postal services | AN5: Telephone and telefax equipment | AO5: Telephone and telefax services | AP5: Audio-visual, photographic and information processing equipment | AQ5: Other major durables for recreation and culture | AR5: Other recreational items and equipment, gardens and pets | AS5: Recreational and cultural services | AT5: Newspapers, books and stationery | AU5: Package holidays | AV5: Pre-primary and primary education | AW5: Secondary education | AX5: Tertiary education | AY5: Education not definable by level | AZ5: Catering services | BA5: Accommodation services | BB5: Personal care | BC5: Personal effects n.e.c. | BD5: Social protection | BE5: insurance | BF5: Financial services n.e.c. | BG5: Other services n.e.c. | BH5: Bread and cereals | BI5: Meat | BJ5: Fish and seafood | BK5: Milk, cheese and eggs | BL5: Oils and fats | BM5: Fruit | BN5: Vegetables | BO5: Sugar, jam, honey, chocolate and confectionery | BP5: Food products n.e.c. | BQ5: Coffee, tea and cacao | BR5: Mineral waters, soft drinks, fruit and vegetable juices | BS5: Spirits | BT5: Wine | BU5: Beer | BV5: Tobacco | BW5: Garments | BX5: Other articles of clothing and clothing accessories | BY5: Cleaning, repair and hire of clothing | BZ5: Shoes and other footwear | CA5: Repair and hire of footwear | CB5: Actual rentals paid by tenants | CC5: Materials for the maintenance and repair of the dwelling | CD5: Water supply | CE5: Electricity | CF5: Gas | CG5: Solid fuels | CH5: Furniture and furnishings | CI5: Carpets and other floor coverings | CJ5: Household textiles | CK5: Major household appliances whether electric or not | CL5: Small electric household appliances | CM5: Repair of household appliances | CN5: Glassware, tableware and household utensils | CO5: Small tools and miscellaneous accessories | CP5: Non-durable household goods | CQ5: Domestic services and household services | CR5: Pharmaceutical products | CS5: Other medical products | CT5: Therapeutic appliances and equipment | CU5: Medical services | CV5: Dental services | CW5: Paramedical services | CX5: Hospital services | CY5: Motor cars | CZ5: Motor cycles | DA5: Bicycles | DB5: Spare parts and accessories for personal transport equipment | DC5: Fuels and lubricants for personal transport equipment | DD5: Maintenance and repair of personal transport equipment | DE5: Other services in respect of personal transport equipment | DF5: Passenger transport by railway | DG5: Passenger transport by road | DH5: Passenger transport by air | DI5: Passenger transport by sea and inland waterway | DJ5: Other purchased transport services | DK5: Postal services | DL5: Telephone and telefax equipment | DM5: Telephone and telefax services | DN5: Equipment for the reception, recording and reproduction of sound and picture | DO5: Information processing equipment | DP5: Repair of audio-visual, photographic and information processing equipment | DQ5: Musical instruments and major durables for indoor recreation | DR5: Games, toys and hobbies | DS5: Equipment for sport, camping and open-air recreation | DT5: Pets and other related products | DU5: Veterinary and other services for pets | DV5: Recreational and sporting services | DW5: Cultural services | DX5: Games of chance | DY5: Books | DZ5: Newspapers and periodicals | EA5: Stationery and drawing materials | EB5: Package holidays | EC5: Pre-primary and primary education | ED5: Secondary education | EE5: Tertiary education | EF5: Education not definable by level | EG5: Catering services | EH5: Accommodation services | EI5: Hairdressing salons and personal grooming establishments | EJ5: Electric appliances for personal care | EK5: Other appliances, articles and products for personal care | EL5: Jewellery, clocks and watches | EM5: Other personal effects | EN5: Social protection | EO5: Insurance connected with the dwelling | EP5: Insurance connected with health | EQ5: Insurance connected with transport | ER5: Other financial services n.e.c. | ES5: Other services n.e.c. | ET5: Rice | EU5: Flours and other cereals | EV5: Bread | EW5: Other bakery products (biscuits, cakes, crackers, phyllo dough, baklava, etc.) | EX5: Pasta products | EY5: Breakfast cereals | EZ5: Beef and veal | FA5: Lamb | FB5: Chicken | FC5: Other meat and edible offal | FD5: Dried, salted or smoked meat | FE5: Fresh or chilled fish | FF5: Other preserved or processed fish | FG5: Milk | FH5: Other milk products (yoghurt, milk desserts etc.) | FI5: Cheese | FJ5: Eggs | FK5: Butter | FL5: Margarine | FM5: Other edible oils | FN5: Fresh fruit | FO5: Dried fruit and nuts | FP5: Fresh vegetables other than potatoes | FQ5: Potatoes | FR5: Legumes | FS5: Canned or processed vegetables (including tomato paste, pickles, olives, etc.) | FT5: Sugar | FU5: Jams, marmalades, honey etc. | FV5: Chocolates and confectionery products | FW5: Ice cream | FX5: Other food products n.e.c. (salt, vinegar, ketchup, mayonnaise etc.) | FY5: Coffee | FZ5: Tea and herbal tea | GA5: Cacao | GB5: Mineral or spring waters | GC5: Soft drinks | GD5: Fruit and vegetable juices | GE5: Alcoholic beverages (raki, whiskey, vodka, etc.) | GF5: Wine from grapes | GG5: Beer | GH5: Cigarettes | GI5: Garments for men | GJ5: Garments for women | GK5: Garments for children | GL5: Garments for baby | GM5: Other articles of clothing (tie, belt, scarf, etc.) | GN5: Dry cleaning and repairing of clothing | GO5: Footwear for men | GP5: Footwear for women | GQ5: Footwear for infants and children | GR5: Repair of footwear | GS5: Actual rentals paid by tenants | GT5: Materials for the maintenance and repair of the dwelling | GU5: Water supply | GV5: Electricity | GW5: Natural gas and related subscription fees | GX5: Liquefied hydrocarbons | GY5: Solid fuels (wood, coal) | GZ5: Kitchen furniture | HA5: Bedroom furniture | HB5: Dining and living room furniture | HC5: Carpets and rugs | HD5: Home textile | HE5: Refrigerators and freezers | HF5: Washing machines, dishwashers | HG5: Cookers | HH5: Air conditioners and heaters | HI5: Other large appliances (vacuum cleaner, etc.) | HJ5: Small electirical appliances | HK5: Repair of household appliances | HL5: Glassware, ceramic ware and chinaware | HM5: Cutlery | HN5: Non-electric kitchen utensils and articles (pots, pans, teapots, etc.) | HO5: Miscellaneous small tool accessories (battery, bulb, etc.) | HP5: Small maintenance and repair for home | HQ5: Cleaning and maintenance products (detergent, softener, etc.) | HR5: Other non-durable small household articles (sponge, garbage bag, etc.) | HS5: Domestic services (fee for homeworker) | HT5: Cleaning services of furnitures | HU5: Pharmaceutical products | HV5: Other medical products (patient diapers, etc.) | HW5: Corrective eye-glasses and contact lenses | HX5: Other therapeutic appliances and equipment | HY5: Outpatient treatment services (examination fee, examination contribution fee etc.) | HZ5: Dental services | IA5: Services of medical analysis laboratories and x-ray centres | IB5: Hospital services | IC5: New diesel motor cars | ID5: New gasoline and electric motor cars | IE5: Motor cycles | IF5: Bicycles | IG5: Spare parts for personal transport equipments | IH5: Fuel and oils of personal transportation vehicles (gasoline, diesel, engine oil) | II5: Maintenance and repair of personal transportation vehicles | IJ5: Other services related to personal transportation vehicles (including bridge and highway tolls) | IK5: Passenger transport by underground and tram | IL5: Passenger transport by train | IM5: Passenger transport by local bus | IN5: Taxi fees | IO5: Passenger transport between cities | IP5: Passenger transport by plane | IQ5: Passenger transport by sea | IR5: Other purchased transportation services (shipping, cargo, etc.) | IS5: Postal services | IT5: Mobile phones, equipment and accessories | IU5: Telephone (mobile and wired phone) and internet charges | IV5: Televisions | IW5: Computers and equipments | IX5: Maintenance and repair of visual and audio devices | IY5: Musical instruments | IZ5: Toys and celebration articles | JA5: Equipment for sport | JB5: Products for pets | JC5: Veterinary and other services for pets | JD5: Recreational and sporting services | JE5: Photographic services | JF5: Other cultural services (cinema, theatre etc.) | JG5: Game of chance | JH5: Books | JI5: Newspapers and magazines | JJ5: Stationery and drawing materials | JK5: Package tours | JL5: Primary education | JM5: Secondary education | JN5: Tertiary education | JO5: Non-formal education (courses etc.) | JP5: Restauranst and food services | JQ5: Cafes and beverage services | JR5: Hotels and other accomodation services | JS5: Accommodation services of other establishments | JT5: Hairdressing for men | JU5: Hairdressing for women | JV5: Electric appliances for personal care | JW5: Articles for personal hygiene and wellness and beauty products | JX5: Jewellery, clocks and watches | JY5: Travel goods | JZ5: Other personal effects n.e.c. | KA5: Child care services (nursery) | KB5: Insurance connected with the dwelling | KC5: Insurance connected with the health | KD5: Motor vehicle insurance | KE5: Legal services and accountancy | KF5: Other fees and services
A6: 2005 | B6: Ocak | C6: January | D6: 114.48558 | E6: 111.95445 | F6: 121.95386 | G6: 110.77344 | H6: 115.50849 | I6: 111.39876 | J6: 112.84033 | K6: 117.99135 | L6: 103.99317 | M6: 113.37379 | N6: 130.87015 | O6: 124.43608 | P6: 114.34235 | Q6: 111.71754 | R6: 115.22717 | S6: 134.45824 | T6: 121.03147 | U6: 109.61467 | V6: 114.08788 | W6: 133.13529 | X6: 112.68484 | Y6: 110.99517 | Z6: 109.32075 | AA6: 125.42689 | AB6: 110.99824 | AC6: 93.911994 | AD6: 117.42913 | AE6: 116.05104 | AF6: 106.64513 | AG6: 96.150501 | AH6: 129.25591 | AI6: 121.87732 | AJ6: 100.50703 | AK6: 124.99659 | AL6: 123.79945 | AM6: 125.4902 | AN6: 87.784961 | AO6: 105.58949 | AP6: 91.097736 | AQ6: 115.8259 | AR6: 120.98778 | AS6: 129.85667 | AT6: 121.89368 | AU6: 111.52183 | AV6: 133.36683 | AW6: 131.17156 | AX6: 129.66598 | AY6: 129.64215 | AZ6: 126.00357 | BA6: 122.448 | BB6: 112.80744 | BC6: 111.88921 | BD6: 131.30442 | BE6: 127.13796 | BF6: 124.54398 | BG6: 139.74654 | BH6: 110.1 | BI6: 107.99 | BJ6: 115.03 | BK6: 120.11 | BL6: 106.28 | BM6: 90.73 | BN6: 122.88 | BO6: 116.57 | BP6: 116.88 | BQ6: 123.59 | BR6: 106.74 | BS6: 140.93 | BT6: 123.77 | BU6: 126.03 | BV6: 121.03 | BW6: 109.19 | BX6: 111.87 | BY6: 128.77 | BZ6: 114.04 | CA6: 121.29 | CB6: 133.14 | CC6: 112.68 | CD6: 110.3 | CE6: 99.95 | CF6: 111.73 | CG6: 118.34 | CH6: 126.72 | CI6: 119.99 | CJ6: 111 | CK6: 88.69 | CL6: 100.82 | CM6: 131.17 | CN6: 117.43 | CO6: 116.05 | CP6: 99.12 | CQ6: 126.14 | CR6: 93.76 | CS6: 117.87 | CT6: 108.31 | CU6: 148.37 | CV6: 119.17 | CW6: 99.41 | CX6: 121.88 | CY6: 100.39 | CZ6: 0 | DA6: 104.77 | DB6: 110.17 | DC6: 125.78 | DD6: 123.77 | DE6: 127.88 | DF6: 124.23 | DG6: 125.54 | DH6: 85.47 | DI6: 87.63 | DJ6: 129.94 | DK6: 125.49 | DL6: 87.78 | DM6: 105.59 | DN6: 76.88 | DO6: 108.31 | DP6: 133.33 | DQ6: 115.83 | DR6: 122.07 | DS6: 115.04 | DU6: 123.87 | DV6: 126.97 | DW6: 117.5 | DX6: 165.02 | DY6: 134.2 | DZ6: 115.85 | EA6: 113.04 | EB6: 111.52 | EC6: 133.37 | ED6: 131.17 | EE6: 129.67 | EF6: 129.64 | EG6: 126 | EH6: 122.45 | EI6: 133.45 | EJ6: 103.26 | EK6: 106.15 | EL6: 106.56 | EM6: 124.89 | EN6: 131.3 | EO6: 124.19 | EP6: 126.26 | EQ6: 129.28 | ER6: 124.54 | ES6: 139.75 | ET6: 120.08 | EU6: 108.06 | EV6: 107.11 | EW6: 122.53 | EX6: 99.42 | EY6: 113.38 | EZ6: 114.31 | FA6: 111.4 | FB6: 90.63 | FC6: 119.45 | FD6: 117.54 | FE6: 115.03 | FG6: 119.03 | FH6: 117.84 | FI6: 122.44 | FJ6: 118.82 | FK6: 127.31 | FL6: 102.5 | FM6: 105.09 | FN6: 84.95 | FO6: 122.62 | FP6: 127.07 | FQ6: 78.34 | FR6: 137.04 | FS6: 128.14 | FT6: 115.01 | FU6: 115.61 | FV6: 122.63 | FW6: 114.83 | FX6: 116.88 | FY6: 115.87 | FZ6: 124.33 | GA6: 123.71 | GB6: 104.2 | GC6: 106.76 | GD6: 111.25 | GE6: 140.93 | GF6: 123.77 | GG6: 126.03 | GH6: 121.13 | GI6: 108.93 | GJ6: 109.07 | GK6: 109.37 | GL6: 120.92 | GM6: 111.87 | GN6: 128.77 | GO6: 113.4 | GP6: 116.22 | GQ6: 111.49 | GR6: 121.29 | GS6: 133.14 | GT6: 112.68 | GU6: 110.3 | GV6: 99.95 | GW6: 110.57 | GX6: 112.33 | GY6: 118.34 | GZ6: 119.94 | HA6: 134.23 | HB6: 124.56 | HC6: 119.99 | HD6: 111 | HE6: 76.7 | HF6: 79.4 | HG6: 84.77 | HH6: 114.55 | HI6: 88.36 | HJ6: 100.82 | HK6: 131.17 | HL6: 115.21 | HM6: 122.73 | HN6: 118.24 | HO6: 111.62 | HP6: 120.26 | HQ6: 97.42 | HR6: 114 | HS6: 126.19 | HT6: 123.89 | HU6: 93.76 | HV6: 117.87 | HW6: 108.83 | HX6: 107.2 | HY6: 148.37 | HZ6: 119.17 | IA6: 96.25 | IB6: 121.88 | IC6: 0 | ID6: 100.39 | IE6: 0 | IF6: 104.77 | IG6: 110.17 | IH6: 125.78 | II6: 123.77 | IJ6: 127.88 | IK6: 125.91 | IL6: 119.68 | IM6: 128.73 | IN6: 122.32 | IO6: 114.55 | IP6: 85.47 | IQ6: 87.63 | IR6: 129.94 | IS6: 125.49 | IT6: 87.78 | IU6: 105.59 | IV6: 76.35 | IW6: 108.31 | IX6: 133.33 | IY6: 115.83 | IZ6: 122.07 | JA6: 115.04 | JC6: 123.87 | JD6: 126.97 | JE6: 116.31 | JF6: 117.91 | JG6: 165.02 | JH6: 134.2 | JI6: 115.85 | JJ6: 113.04 | JK6: 111.52 | JL6: 133.37 | JM6: 131.17 | JN6: 129.67 | JO6: 129.64 | JP6: 128.44 | JQ6: 120.31 | JR6: 117.8 | JS6: 128.4 | JT6: 138.44 | JU6: 128.54 | JV6: 103.26 | JW6: 106.15 | JX6: 106.56 | JY6: 125.4 | JZ6: 123.64 | KA6: 131.3 | KB6: 124.19 | KC6: 126.26 | KD6: 129.28 | KE6: 124.54 | KF6: 139.75
A7: 2005 | B7: Şubat | C7: February | D7: 114.51307 | E7: 112.92027 | F7: 124.33064 | G7: 103.12807 | H7: 116.11247 | I7: 112.23775 | J7: 112.38279 | K7: 118.58193 | L7: 104.17062 | M7: 113.06911 | N7: 130.31324 | O7: 126.28103 | P7: 113.11501 | Q7: 112.74544 | R7: 115.27556 | S7: 157.06596 | T7: 122.05827 | U7: 101.85257 | V7: 106.78099 | W7: 134.78757 | X7: 114.02123 | Y7: 110.81982 | Z7: 109.65576 | AA7: 126.75329 | AB7: 110.55464 | AC7: 95.414725 | AD7: 118.02723 | AE7: 116.98541 | AF7: 106.95695 | AG7: 95.563489 | AH7: 126.52388 | AI7: 130.3626 | AJ7: 101.26307 | AK7: 125.60647 | AL7: 124.2182 | AM7: 125.4902 | AN7: 89.46613 | AO7: 105.58969 | AP7: 90.66783 | AQ7: 115.36379 | AR7: 122.41623 | AS7: 132.04024 | AT7: 120.26121 | AU7: 110.47407 | AV7: 132.85864 | AW7: 132.64517 | AX7: 129.66598 | AY7: 125.29382 | AZ7: 128.18103 | BA7: 123.87449 | BB7: 113.91338 | BC7: 108.22815 | BD7: 129.7042 | BE7: 130.53122 | BF7: 126.58604 | BG7: 139.87789 | BH7: 110.23 | BI7: 109.69 | BJ7: 126.31 | BK7: 120.49 | BL7: 106.73 | BM7: 94.36 | BN7: 122.9 | BO7: 116.96 | BP7: 117.57 | BQ7: 123.72 | BR7: 106.72 | BS7: 169.85 | BT7: 131.44 | BU7: 142.57 | BV7: 122.06 | BW7: 100.79 | BX7: 110.44 | BY7: 131.14 | BZ7: 106.66 | CA7: 122.83 | CB7: 134.79 | CC7: 114.02 | CD7: 110.11 | CE7: 99.92 | CF7: 112.88 | CG7: 117.7 | CH7: 128.21 | CI7: 120.63 | CJ7: 110.55 | CK7: 90.44 | CL7: 101.03 | CM7: 131.17 | CN7: 118.03 | CO7: 116.99 | CP7: 99.3 | CQ7: 126.84 | CR7: 93.33 | CS7: 118.17 | CT7: 106.34 | CU7: 148.77 | CV7: 117.72 | CW7: 91.97 | CX7: 130.36 | CY7: 100.96 | CZ7: 0 | DA7: 114.58 | DB7: 111.44 | DC7: 126.24 | DD7: 125.38 | DE7: 129.29 | DF7: 127.34 | DG7: 125.95 | DH7: 84.46 | DI7: 87.63 | DJ7: 130.74 | DK7: 125.49 | DL7: 89.47 | DM7: 105.59 | DN7: 76.99 | DO7: 107.23 | DP7: 129.6 | DQ7: 115.36 | DR7: 122.76 | DS7: 117.35 | DU7: 126.56 | DV7: 131.56 | DW7: 118.8 | DX7: 165.02 | DY7: 133.6 | DZ7: 111.3 | EA7: 113.09 | EB7: 110.47 | EC7: 132.86 | ED7: 132.65 | EE7: 129.67 | EF7: 125.29 | EG7: 128.18 | EH7: 123.87 | EI7: 135.1 | EJ7: 105.15 | EK7: 107.07 | EL7: 101.73 | EM7: 124.23 | EN7: 129.7 | EO7: 125.9 | EP7: 126.26 | EQ7: 134.1 | ER7: 126.59 | ES7: 139.88 | ET7: 120.87 | EU7: 108.49 | EV7: 106.85 | EW7: 123.56 | EX7: 100.08 | EY7: 113.03 | EZ7: 115.62 | FA7: 118.71 | FB7: 88.03 | FC7: 120.3 | FD7: 119.14 | FE7: 126.31 | FG7: 121.54 | FH7: 119.2 | FI7: 122.79 | FJ7: 115.6 | FK7: 127.72 | FL7: 102.72 | FM7: 105.6 | FN7: 88.61 | FO7: 125.53 | FP7: 126.15 | FQ7: 77.37 | FR7: 140.25 | FS7: 131.38 | FT7: 115.14 | FU7: 114.89 | FV7: 123.91 | FW7: 118.26 | FX7: 117.57 | FY7: 116.29 | FZ7: 124.41 | GA7: 124.54 | GB7: 103.39 | GC7: 106.97 | GD7: 111.55 | GE7: 169.85 | GF7: 131.44 | GG7: 142.57 | GH7: 122.16 | GI7: 101.33 | GJ7: 100.48 | GK7: 98.95 | GL7: 118.93 | GM7: 110.44 | GN7: 131.14 | GO7: 106.23 | GP7: 107.9 | GQ7: 105.33 | GR7: 122.83 | GS7: 134.79 | GT7: 114.02 | GU7: 110.11 | GV7: 99.92 | GW7: 110.26 | GX7: 114.29 | GY7: 117.7 | GZ7: 120.19 | HA7: 135.11 | HB7: 126.53 | HC7: 120.63 | HD7: 110.55 | HE7: 78.87 | HF7: 82.76 | HG7: 84.69 | HH7: 114.64 | HI7: 88.96 | HJ7: 101.03 | HK7: 131.17 | HL7: 115.24 | HM7: 124.5 | HN7: 119.09 | HO7: 112.24 | HP7: 121.51 | HQ7: 97.53 | HR7: 115.04 | HS7: 126.87 | HT7: 124.95 | HU7: 93.33 | HV7: 118.17 | HW7: 106.97 | HX7: 104.98 | HY7: 148.77 | HZ7: 117.72 | IA7: 88.03 | IB7: 130.36 | IC7: 0 | ID7: 100.96 | IE7: 0 | IF7: 114.58 | IG7: 111.44 | IH7: 126.24 | II7: 125.38 | IJ7: 129.29 | IK7: 128.64 | IL7: 123.67 | IM7: 129.18 | IN7: 124 | IO7: 114.38 | IP7: 84.46 | IQ7: 87.63 | IR7: 130.74 | IS7: 125.49 | IT7: 89.47 | IU7: 105.59 | IV7: 76.83 | IW7: 107.23 | IX7: 129.6 | IY7: 115.36 | IZ7: 122.76 | JA7: 117.35 | JC7: 126.56 | JD7: 131.56 | JE7: 118.81 | JF7: 118.75 | JG7: 165.02 | JH7: 133.6 | JI7: 111.3 | JJ7: 113.09 | JK7: 110.47 | JL7: 132.86 | JM7: 132.65 | JN7: 129.67 | JO7: 125.29 | JP7: 130.33 | JQ7: 123.09 | JR7: 118.38 | JS7: 131 | JT7: 140.54 | JU7: 129.77 | JV7: 105.15 | JW7: 107.07 | JX7: 101.73 | JY7: 124.47 | JZ7: 123.6 | KA7: 129.7 | KB7: 125.9 | KC7: 126.26 | KD7: 134.1 | KE7: 126.59 | KF7: 139.88
A8: 2005 | B8: Mart | C8: March | D8: 114.81 | E8: 113.03 | F8: 124.53 | G8: 99.69 | H8: 117.37 | I8: 112.15 | J8: 113.38 | K8: 119.42 | L8: 104.43 | M8: 111.89 | N8: 130.18 | O8: 129.26 | P8: 114.66 | Q8: 112.85 | R8: 115.51 | S8: 160.2 | T8: 122.06 | U8: 97.89 | V8: 104.85 | W8: 136.23 | X8: 114.83 | Y8: 111.06 | Z8: 111.21 | AA8: 126 | AB8: 109.84 | AC8: 95.84 | AD8: 117.94 | AE8: 117.69 | AF8: 107.2 | AG8: 96.21 | AH8: 125.98 | AI8: 138.55 | AJ8: 100.9 | AK8: 127.64 | AL8: 124.89 | AM8: 125.49 | AN8: 91.92 | AO8: 105.59 | AP8: 92.64 | AQ8: 113.24 | AR8: 123.16 | AS8: 132.85 | AT8: 113.97 | AU8: 108.63 | AV8: 132.93 | AW8: 132.64 | AX8: 129.67 | AY8: 124.32 | AZ8: 129.64 | BA8: 128.77 | BB8: 115.35 | BC8: 109.95 | BD8: 130.61 | BE8: 128.74 | BF8: 126.59 | BG8: 142.35 | BH8: 110.52 | BI8: 110.87 | BJ8: 131.83 | BK8: 120.31 | BL8: 106.58 | BM8: 95.92 | BN8: 120.17 | BO8: 117.61 | BP8: 118.38 | BQ8: 123.84 | BR8: 107.04 | BS8: 170.17 | BT8: 143.68 | BU8: 147.7 | BV8: 122.06 | BW8: 96.49 | BX8: 109.9 | BY8: 132.98 | BZ8: 104.71 | CA8: 124.56 | CB8: 136.23 | CC8: 114.83 | CD8: 110.35 | CE8: 99.93 | CF8: 116.9 | CG8: 116.95 | CH8: 127.02 | CI8: 121.67 | CJ8: 109.84 | CK8: 91.33 | CL8: 97.28 | CM8: 131.91 | CN8: 117.94 | CO8: 117.69 | CP8: 99.11 | CQ8: 128.5 | CR8: 93.33 | CS8: 119.33 | CT8: 111.9 | CU8: 152.07 | CV8: 115.76 | CW8: 87.2 | CX8: 138.55 | CY8: 100.64 | CZ8: 0 | DA8: 112.35 | DB8: 111.88 | DC8: 128.59 | DD8: 125.23 | DE8: 130.51 | DF8: 129.19 | DG8: 126.67 | DH8: 84.19 | DI8: 86.63 | DJ8: 131.16 | DK8: 125.49 | DL8: 91.92 | DM8: 105.59 | DN8: 81.94 | DO8: 94.44 | DP8: 128.93 | DQ8: 113.24 | DR8: 123.45 | DS8: 117.26 | DU8: 128.36 | DV8: 133.75 | DW8: 118.93 | DX8: 165.02 | DY8: 120.12 | DZ8: 106.75 | EA8: 113.12 | EB8: 108.63 | EC8: 132.93 | ED8: 132.64 | EE8: 129.67 | EF8: 124.32 | EG8: 129.64 | EH8: 128.77 | EI8: 139.16 | EJ8: 101.79 | EK8: 107.92 | EL8: 103.83 | EM8: 124.99 | EN8: 130.61 | EO8: 127.38 | EP8: 126.26 | EQ8: 129.79 | ER8: 126.59 | ES8: 142.35 | ET8: 121.41 | EU8: 108.81 | EV8: 107.04 | EW8: 124.13 | EX8: 100.36 | EY8: 112.54 | EZ8: 115.77 | FA8: 120.36 | FB8: 90.79 | FC8: 120.9 | FD8: 118.01 | FE8: 131.83 | FG8: 122.64 | FH8: 118.31 | FI8: 123.41 | FJ8: 112.8 | FK8: 127.86 | FL8: 102.89 | FM8: 105.35 | FN8: 90.03 | FO8: 127.94 | FP8: 121.55 | FQ8: 75.97 | FR8: 142.1 | FS8: 132.93 | FT8: 115.28 | FU8: 116.4 | FV8: 125.14 | FW8: 119.8 | FX8: 118.38 | FY8: 117.57 | FZ8: 124.4 | GA8: 125.51 | GB8: 104.14 | GC8: 107.11 | GD8: 111.99 | GE8: 170.17 | GF8: 143.68 | GG8: 147.7 | GH8: 122.16 | GI8: 96.75 | GJ8: 95.54 | GK8: 96.76 | GL8: 117.55 | GM8: 109.9 | GN8: 132.98 | GO8: 105.2 | GP8: 103.84 | GQ8: 104.84 | GR8: 124.56 | GS8: 136.23 | GT8: 114.83 | GU8: 110.35 | GV8: 99.93 | GW8: 115.35 | GX8: 117.72 | GY8: 116.95 | GZ8: 120.53 | HA8: 131.96 | HB8: 125.91 | HC8: 121.67 | HD8: 109.84 | HE8: 78.72 | HF8: 82.78 | HG8: 84.63 | HH8: 114.7 | HI8: 98.26 | HJ8: 97.28 | HK8: 131.91 | HL8: 114.77 | HM8: 124.29 | HN8: 119.36 | HO8: 112.94 | HP8: 122.21 | HQ8: 97.22 | HR8: 116.05 | HS8: 128.51 | HT8: 127.91 | HU8: 93.33 | HV8: 119.33 | HW8: 115.45 | HX8: 104.37 | HY8: 152.07 | HZ8: 115.76 | IA8: 82.79 | IB8: 138.55 | IC8: 0 | ID8: 100.64 | IE8: 0 | IF8: 112.35 | IG8: 111.88 | IH8: 128.59 | II8: 125.23 | IJ8: 130.51 | IK8: 129.61 | IL8: 127.66 | IM8: 130.18 | IN8: 124.43 | IO8: 114.12 | IP8: 84.19 | IQ8: 86.63 | IR8: 131.16 | IS8: 125.49 | IT8: 91.92 | IU8: 105.59 | IV8: 82.74 | IW8: 94.44 | IX8: 128.93 | IY8: 113.24 | IZ8: 123.45 | JA8: 117.26 | JC8: 128.36 | JD8: 133.75 | JE8: 119.09 | JF8: 118.81 | JG8: 165.02 | JH8: 120.12 | JI8: 106.75 | JJ8: 113.12 | JK8: 108.63 | JL8: 132.93 | JM8: 132.64 | JN8: 129.67 | JO8: 124.32 | JP8: 131.74 | JQ8: 124.67 | JR8: 123.25 | JS8: 135.92 | JT8: 144.52 | JU8: 133.9 | JV8: 101.79 | JW8: 107.92 | JX8: 103.83 | JY8: 125.79 | JZ8: 123.03 | KA8: 130.61 | KB8: 127.38 | KC8: 126.26 | KD8: 129.79 | KE8: 126.59 | KF8: 142.35
A9: 2005 | B9: Nisan | C9: April | D9: 115.63 | E9: 111.94 | F9: 124.6 | G9: 108.26 | H9: 117.82 | I9: 112.82 | J9: 114.17 | K9: 121.91 | L9: 104.19 | M9: 111 | N9: 130.06 | O9: 130.48 | P9: 115.84 | Q9: 111.65 | R9: 116.05 | S9: 161.32 | T9: 122.06 | U9: 105.61 | V9: 115.87 | W9: 137.22 | X9: 115.3 | Y9: 105.29 | Z9: 113.35 | AA9: 127.15 | AB9: 110.26 | AC9: 96.87 | AD9: 117.63 | AE9: 118.41 | AF9: 107.45 | AG9: 96.2 | AH9: 128.11 | AI9: 138.6 | AJ9: 102.86 | AK9: 132.69 | AL9: 125.28 | AM9: 125.49 | AN9: 89.61 | AO9: 105.6 | AP9: 91.35 | AQ9: 113.05 | AR9: 124.65 | AS9: 132.78 | AT9: 114.46 | AU9: 106.36 | AV9: 132.83 | AW9: 132.65 | AX9: 129.67 | AY9: 123.27 | AZ9: 130.21 | BA9: 130.81 | BB9: 116.16 | BC9: 111.71 | BD9: 131.08 | BE9: 123.83 | BF9: 128.68 | BG9: 144.01 | BH9: 110.34 | BI9: 115.47 | BJ9: 122.2 | BK9: 118.65 | BL9: 106.02 | BM9: 97.28 | BN9: 109.68 | BO9: 118.11 | BP9: 120.13 | BQ9: 124.57 | BR9: 107.42 | BS9: 170.49 | BT9: 149.48 | BU9: 148.85 | BV9: 122.06 | BW9: 104.78 | BX9: 112.03 | BY9: 133.19 | BZ9: 115.8 | CA9: 125.44 | CB9: 137.22 | CC9: 115.29 | CD9: 104.27 | CE9: 101.62 | CF9: 119.87 | CG9: 116.43 | CH9: 128.6 | CI9: 121.07 | CJ9: 110.26 | CK9: 92.43 | CL9: 97.76 | CM9: 132.66 | CN9: 117.63 | CO9: 118.41 | CP9: 98.6 | CQ9: 131.17 | CR9: 93.28 | CS9: 118.31 | CT9: 112.31 | CU9: 156.15 | CV9: 116.1 | CW9: 87.61 | CX9: 138.6 | CY9: 102.74 | CZ9: 0 | DA9: 107.31 | DB9: 111.41 | DC9: 134.44 | DD9: 126.47 | DE9: 130.4 | DF9: 129.48 | DG9: 126.7 | DH9: 91.75 | DI9: 86.85 | DJ9: 132.64 | DK9: 125.49 | DL9: 89.61 | DM9: 105.6 | DN9: 79.9 | DO9: 96.16 | DP9: 130.85 | DQ9: 113.05 | DR9: 125.29 | DS9: 117.43 | DU9: 130.21 | DV9: 133.64 | DW9: 118.86 | DX9: 165.02 | DY9: 121.65 | DZ9: 106.75 | EA9: 112.92 | EB9: 106.36 | EC9: 132.83 | ED9: 132.65 | EE9: 129.67 | EF9: 123.27 | EG9: 130.21 | EH9: 130.81 | EI9: 141.01 | EJ9: 101.8 | EK9: 108.46 | EL9: 106.22 | EM9: 125.11 | EN9: 131.08 | EO9: 128.11 | EP9: 119.78 | EQ9: 120.74 | ER9: 128.68 | ES9: 144.01 | ET9: 122.72 | EU9: 108.36 | EV9: 106.7 | EW9: 124.42 | EX9: 99.56 | EY9: 112.51 | EZ9: 115.24 | FA9: 119.77 | FB9: 107.88 | FC9: 120.77 | FD9: 117.45 | FE9: 122.2 | FG9: 122.31 | FH9: 118.25 | FI9: 122.92 | FJ9: 105.54 | FK9: 128.82 | FL9: 102.47 | FM9: 104.62 | FN9: 91.31 | FO9: 129.72 | FP9: 104.56 | FQ9: 76.55 | FR9: 142.09 | FS9: 133.64 | FT9: 115.35 | FU9: 117.18 | FV9: 126.34 | FW9: 121.65 | FX9: 120.13 | FY9: 118.48 | FZ9: 125.1 | GA9: 126.35 | GB9: 105.42 | GC9: 107.03 | GD9: 112.97 | GE9: 170.49 | GF9: 149.48 | GG9: 148.85 | GH9: 122.16 | GI9: 106.25 | GJ9: 102.89 | GK9: 104.58 | GL9: 121.43 | GM9: 112.03 | GN9: 133.19 | GO9: 117.39 | GP9: 116.61 | GQ9: 110.23 | GR9: 125.44 | GS9: 137.22 | GT9: 115.29 | GU9: 104.27 | GV9: 101.62 | GW9: 114.37 | GX9: 122.86 | GY9: 116.43 | GZ9: 122.8 | HA9: 134.27 | HB9: 127.06 | HC9: 121.07 | HD9: 110.26 | HE9: 79.81 | HF9: 83.38 | HG9: 87.22 | HH9: 115.39 | HI9: 99.74 | HJ9: 97.76 | HK9: 132.66 | HL9: 114.16 | HM9: 124.47 | HN9: 119.2 | HO9: 113.89 | HP9: 122.69 | HQ9: 96.68 | HR9: 115.8 | HS9: 131.21 | HT9: 129.32 | HU9: 93.28 | HV9: 118.31 | HW9: 116.65 | HX9: 103.1 | HY9: 156.15 | HZ9: 116.1 | IA9: 83.17 | IB9: 138.6 | IC9: 0 | ID9: 102.74 | IE9: 0 | IF9: 107.31 | IG9: 111.41 | IH9: 134.44 | II9: 126.47 | IJ9: 130.4 | IK9: 130.02 | IL9: 127.66 | IM9: 131.05 | IN9: 122.1 | IO9: 111.87 | IP9: 91.75 | IQ9: 86.85 | IR9: 132.64 | IS9: 125.49 | IT9: 89.61 | IU9: 105.6 | IV9: 80.11 | IW9: 96.16 | IX9: 130.85 | IY9: 113.05 | IZ9: 125.29 | JA9: 117.43 | JC9: 130.21 | JD9: 133.64 | JE9: 119.68 | JF9: 118.49 | JG9: 165.02 | JH9: 121.65 | JI9: 106.75 | JJ9: 112.92 | JK9: 106.36 | JL9: 132.83 | JM9: 132.65 | JN9: 129.67 | JO9: 123.27 | JP9: 132.69 | JQ9: 124.4 | JR9: 126.16 | JS9: 136.72 | JT9: 146.44 | JU9: 135.69 | JV9: 101.8 | JW9: 108.46 | JX9: 106.22 | JY9: 126.44 | JZ9: 121.91 | KA9: 131.08 | KB9: 128.11 | KC9: 119.78 | KD9: 120.74 | KE9: 128.68 | KF9: 144.01
A10: 2005 | B10: Mayıs | C10: May | D10: 116.69 | E10: 111.95 | F10: 124.6 | G10: 117.82 | H10: 117.47 | I10: 113.48 | J10: 114.27 | K10: 122.12 | L10: 105.05 | M10: 115.51 | N10: 130.53 | O10: 131.7 | P10: 115.9 | Q10: 111.63 | R10: 116.51 | S10: 161.36 | T10: 122.06 | U10: 117 | V10: 120.16 | W10: 138.92 | X10: 115.47 | Y10: 103.16 | Z10: 112.71 | AA10: 129.23 | AB10: 110.09 | AC10: 96.62 | AD10: 117.59 | AE10: 118.82 | AF10: 107.94 | AG10: 96.16 | AH10: 128.43 | AI10: 138.67 | AJ10: 104.1 | AK10: 130.96 | AL10: 126.51 | AM10: 125.49 | AN10: 92.61 | AO10: 106.2 | AP10: 97.32 | AQ10: 114.63 | AR10: 125.53 | AS10: 133.31 | AT10: 117.56 | AU10: 113.34 | AV10: 132.82 | AW10: 132.65 | AX10: 129.67 | AY10: 123.64 | AZ10: 132.02 | BA10: 131.28 | BB10: 116.16 | BC10: 111.92 | BD10: 131.37 | BE10: 122 | BF10: 128.66 | BG10: 144 | BH10: 110.61 | BI10: 116.07 | BJ10: 135.75 | BK10: 115.86 | BL10: 105.71 | BM10: 114.58 | BN10: 97.53 | BO10: 118.37 | BP10: 120.55 | BQ10: 125.8 | BR10: 107.21 | BS10: 170.55 | BT10: 149.76 | BU10: 148.8 | BV10: 122.06 | BW10: 117.15 | BX10: 112.69 | BY10: 134.45 | BZ10: 120.11 | CA10: 127.08 | CB10: 138.92 | CC10: 115.47 | CD10: 102.23 | CE10: 99.97 | CF10: 120.55 | CG10: 115.8 | CH10: 131 | CI10: 121.82 | CJ10: 110.09 | CK10: 92.14 | CL10: 97.66 | CM10: 132.72 | CN10: 117.59 | CO10: 118.82 | CP10: 98.39 | CQ10: 133.93 | CR10: 93.28 | CS10: 119.55 | CT10: 111.74 | CU10: 156.82 | CV10: 116.07 | CW10: 87.66 | CX10: 138.67 | CY10: 104.01 | CZ10: 0 | DA10: 107.31 | DB10: 110.18 | DC10: 132.31 | DD10: 127.61 | DE10: 132.57 | DF10: 129.19 | DG10: 128.03 | DH10: 91.54 | DI10: 86.85 | DJ10: 135.66 | DK10: 125.49 | DL10: 92.61 | DM10: 106.2 | DN10: 87.57 | DO10: 103.2 | DP10: 133.46 | DQ10: 114.63 | DR10: 126.15 | DS10: 118.23 | DU10: 131.22 | DV10: 135.59 | DW10: 118.55 | DX10: 165.02 | DY10: 129.79 | DZ10: 106.75 | EA10: 113.42 | EB10: 113.34 | EC10: 132.82 | ED10: 132.65 | EE10: 129.67 | EF10: 123.64 | EG10: 132.02 | EH10: 131.28 | EI10: 142.02 | EJ10: 102.34 | EK10: 108.16 | EL10: 106.22 | EM10: 125.84 | EN10: 131.37 | EO10: 129.23 | EP10: 110.37 | EQ10: 117.07 | ER10: 128.66 | ES10: 144 | ET10: 124.22 | EU10: 108.56 | EV10: 106.69 | EW10: 125.28 | EX10: 100.02 | EY10: 112.27 | EZ10: 115.3 | FA10: 120.35 | FB10: 109.1 | FC10: 120.68 | FD10: 118.31 | FE10: 135.75 | FG10: 120.17 | FH10: 116.56 | FI10: 122.97 | FJ10: 95.15 | FK10: 129.11 | FL10: 99.93 | FM10: 104.85 | FN10: 110.56 | FO10: 130.79 | FP10: 81.51 | FQ10: 91.8 | FR10: 141.85 | FS10: 133.82 | FT10: 115.28 | FU10: 117.63 | FV10: 127.28 | FW10: 122.61 | FX10: 120.55 | FY10: 118.53 | FZ10: 126.47 | GA10: 127.13 | GB10: 104.21 | GC10: 107.08 | GD10: 113.26 | GE10: 170.55 | GF10: 149.76 | GG10: 148.8 | GH10: 122.16 | GI10: 116.76 | GJ10: 116.79 | GK10: 118.73 | GL10: 122.04 | GM10: 112.69 | GN10: 134.45 | GO10: 121.51 | GP10: 122.24 | GQ10: 112.64 | GR10: 127.08 | GS10: 138.92 | GT10: 115.47 | GU10: 102.23 | GV10: 99.97 | GW10: 115.52 | GX10: 123.28 | GY10: 115.8 | GZ10: 123.24 | HA10: 134.12 | HB10: 130.88 | HC10: 121.82 | HD10: 110.09 | HE10: 79.81 | HF10: 83.72 | HG10: 87.19 | HH10: 115.4 | HI10: 96.03 | HJ10: 97.66 | HK10: 132.72 | HL10: 114.24 | HM10: 124.68 | HN10: 119.02 | HO10: 114.33 | HP10: 123.08 | HQ10: 96.4 | HR10: 116.39 | HS10: 133.98 | HT10: 131.37 | HU10: 93.28 | HV10: 119.55 | HW10: 116.64 | HX10: 101.32 | HY10: 156.82 | HZ10: 116.07 | IA10: 83.14 | IB10: 138.67 | IC10: 0 | ID10: 104.01 | IE10: 0 | IF10: 107.31 | IG10: 110.18 | IH10: 132.31 | II10: 127.61 | IJ10: 132.57 | IK10: 129.61 | IL10: 127.66 | IM10: 131.99 | IN10: 122.59 | IO10: 114.99 | IP10: 91.54 | IQ10: 86.85 | IR10: 135.66 | IS10: 125.49 | IT10: 92.61 | IU10: 106.2 | IV10: 88.19 | IW10: 103.2 | IX10: 133.46 | IY10: 114.63 | IZ10: 126.15 | JA10: 118.23 | JC10: 131.22 | JD10: 135.59 | JE10: 119.42 | JF10: 118.16 | JG10: 165.02 | JH10: 129.79 | JI10: 106.75 | JJ10: 113.42 | JK10: 113.34 | JL10: 132.82 | JM10: 132.65 | JN10: 129.67 | JO10: 123.64 | JP10: 134.31 | JQ10: 126.62 | JR10: 126.94 | JS10: 136.73 | JT10: 147.41 | JU10: 136.74 | JV10: 102.34 | JW10: 108.16 | JX10: 106.22 | JY10: 127.16 | JZ10: 122.66 | KA10: 131.37 | KB10: 129.23 | KC10: 110.37 | KD10: 117.07 | KE10: 128.66 | KF10: 144
A11: 2005 | B11: Haziran | C11: June | D11: 116.81 | E11: 110.12 | F11: 124.69 | G11: 118.78 | H11: 118.14 | I11: 114.61 | J11: 114.39 | K11: 122.99 | L11: 104.44 | M11: 120.14 | N11: 134.76 | O11: 132.69 | P11: 116.86 | Q11: 109.66 | R11: 116.66 | S11: 162.77 | T11: 122.06 | U11: 118.21 | V11: 120.38 | W11: 141.32 | X11: 115.94 | Y11: 103.53 | Z11: 112.83 | AA11: 131.54 | AB11: 109.53 | AC11: 98.03 | AD11: 117.47 | AE11: 118.84 | AF11: 108.63 | AG11: 96.03 | AH11: 128.91 | AI11: 138.79 | AJ11: 103.83 | AK11: 132.74 | AL11: 127.44 | AM11: 119.55 | AN11: 86.51 | AO11: 106.25 | AP11: 105.32 | AQ11: 114.51 | AR11: 125.99 | AS11: 134.68 | AT11: 119.72 | AU11: 119.3 | AV11: 140.03 | AW11: 143.23 | AX11: 129.67 | AY11: 123.44 | AZ11: 133.06 | BA11: 132.2 | BB11: 116.76 | BC11: 112.99 | BD11: 135.88 | BE11: 127.27 | BF11: 128.66 | BG11: 144.01 | BH11: 110.83 | BI11: 116.26 | BJ11: 132.11 | BK11: 114.06 | BL11: 105.09 | BM11: 106.19 | BN11: 92.86 | BO11: 118.42 | BP11: 121.15 | BQ11: 126.68 | BR11: 106.72 | BS11: 170.64 | BT11: 150.64 | BU11: 152.31 | BV11: 122.06 | BW11: 118.44 | BX11: 112.9 | BY11: 135.43 | BZ11: 120.34 | CA11: 126.99 | CB11: 141.32 | CC11: 115.94 | CD11: 102.61 | CE11: 99.97 | CF11: 120.84 | CG11: 115.33 | CH11: 133.7 | CI11: 122.53 | CJ11: 109.53 | CK11: 93.84 | CL11: 97.42 | CM11: 132.72 | CN11: 117.47 | CO11: 118.84 | CP11: 98.59 | CQ11: 136.15 | CR11: 93.28 | CS11: 120.03 | CT11: 110.5 | CU11: 157.8 | CV11: 116.12 | CW11: 87.67 | CX11: 138.79 | CY11: 103.73 | CZ11: 0 | DA11: 107.31 | DB11: 109.78 | DC11: 134.27 | DD11: 129.1 | DE11: 133.66 | DF11: 129.19 | DG11: 128.9 | DH11: 92.81 | DI11: 86.88 | DJ11: 141.21 | DK11: 119.55 | DL11: 86.51 | DM11: 106.25 | DN11: 97.25 | DO11: 108.49 | DP11: 142.64 | DQ11: 114.51 | DR11: 126.8 | DS11: 118.34 | DU11: 131.49 | DV11: 136.89 | DW11: 120.52 | DX11: 165.02 | DY11: 135.67 | DZ11: 106.75 | EA11: 113.54 | EB11: 119.3 | EC11: 140.03 | ED11: 143.23 | EE11: 129.67 | EF11: 123.44 | EG11: 133.06 | EH11: 132.2 | EI11: 142.73 | EJ11: 102.88 | EK11: 108.73 | EL11: 107.35 | EM11: 126.78 | EN11: 135.88 | EO11: 130.35 | EP11: 110.36 | EQ11: 125.7 | ER11: 128.66 | ES11: 144.01 | ET11: 124.76 | EU11: 108.43 | EV11: 106.9 | EW11: 125.44 | EX11: 101.35 | EY11: 111.75 | EZ11: 115.48 | FA11: 118.84 | FB11: 110.44 | FC11: 119.97 | FD11: 119.62 | FE11: 132.11 | FG11: 116.82 | FH11: 116.15 | FI11: 122.75 | FJ11: 90.84 | FK11: 127.8 | FL11: 99.23 | FM11: 104.31 | FN11: 101.06 | FO11: 131.46 | FP11: 65.66 | FQ11: 126.94 | FR11: 139.19 | FS11: 134.03 | FT11: 115.13 | FU11: 117.61 | FV11: 127.97 | FW11: 123 | FX11: 121.15 | FY11: 119.35 | FZ11: 127.36 | GA11: 127.51 | GB11: 103.17 | GC11: 106.76 | GD11: 112.97 | GE11: 170.64 | GF11: 150.64 | GG11: 152.31 | GH11: 122.16 | GI11: 117.66 | GJ11: 117.24 | GK11: 123.3 | GL11: 121.21 | GM11: 112.9 | GN11: 135.43 | GO11: 121.6 | GP11: 122.27 | GQ11: 113.54 | GR11: 126.99 | GS11: 141.32 | GT11: 115.94 | GU11: 102.61 | GV11: 99.97 | GW11: 115.95 | GX11: 123.49 | GY11: 115.33 | GZ11: 124.36 | HA11: 138.55 | HB11: 133.12 | HC11: 122.53 | HD11: 109.53 | HE11: 82.51 | HF11: 86.37 | HG11: 88.02 | HH11: 115.37 | HI11: 95.18 | HJ11: 97.42 | HK11: 132.72 | HL11: 114.09 | HM11: 124.85 | HN11: 118.87 | HO11: 114.12 | HP11: 123.33 | HQ11: 96.65 | HR11: 116.12 | HS11: 136.22 | HT11: 132.73 | HU11: 93.28 | HV11: 120.03 | HW11: 115.45 | HX11: 100 | HY11: 157.8 | HZ11: 116.12 | IA11: 83.09 | IB11: 138.79 | IC11: 0 | ID11: 103.73 | IE11: 0 | IF11: 107.31 | IG11: 109.78 | IH11: 134.27 | II11: 129.1 | IJ11: 133.66 | IK11: 129.61 | IL11: 127.66 | IM11: 132.42 | IN11: 123.38 | IO11: 117.55 | IP11: 92.81 | IQ11: 86.88 | IR11: 141.21 | IS11: 119.55 | IT11: 86.51 | IU11: 106.25 | IV11: 99.25 | IW11: 108.49 | IX11: 142.64 | IY11: 114.51 | IZ11: 126.8 | JA11: 118.34 | JC11: 131.49 | JD11: 136.89 | JE11: 119.93 | JF11: 120.69 | JG11: 165.02 | JH11: 135.67 | JI11: 106.75 | JJ11: 113.54 | JK11: 119.3 | JL11: 140.03 | JM11: 143.23 | JN11: 129.67 | JO11: 123.44 | JP11: 135.32 | JQ11: 127.72 | JR11: 128.68 | JS11: 136.53 | JT11: 147.97 | JU11: 137.57 | JV11: 102.88 | JW11: 108.73 | JX11: 107.35 | JY11: 128 | JZ11: 123.82 | KA11: 135.88 | KB11: 130.35 | KC11: 110.36 | KD11: 125.7 | KE11: 128.66 | KF11: 144.01
A12: 2005 | B12: Temmuz | C12: July | D12: 116.14 | E12: 108.85 | F12: 127.15 | G12: 109.93 | H12: 119.17 | I12: 114.26 | J12: 112.81 | K12: 124.14 | L12: 104.27 | M12: 121.39 | N12: 135.98 | O12: 133.97 | P12: 115.85 | Q12: 108.24 | R12: 117.59 | S12: 162.91 | T12: 124.67 | U12: 108.62 | V12: 113.66 | W12: 144.04 | X12: 116.29 | Y12: 102.27 | Z12: 113.99 | AA12: 132.15 | AB12: 109.07 | AC12: 95.94 | AD12: 117.34 | AE12: 118.59 | AF12: 108.68 | AG12: 92.25 | AH12: 130 | AI12: 139.51 | AJ12: 102.68 | AK12: 134.65 | AL12: 129.79 | AM12: 119.55 | AN12: 84.74 | AO12: 106.26 | AP12: 102.08 | AQ12: 114.31 | AR12: 125.42 | AS12: 134.96 | AT12: 120.95 | AU12: 124.9 | AV12: 141.87 | AW12: 146.04 | AX12: 129.67 | AY12: 124.12 | AZ12: 134.08 | BA12: 133.81 | BB12: 116.99 | BC12: 110.71 | BD12: 136.9 | BE12: 126.82 | BF12: 128.66 | BG12: 144.05 | BH12: 110.78 | BI12: 117.89 | BJ12: 135.05 | BK12: 113.1 | BL12: 104.97 | BM12: 95.01 | BN12: 90.96 | BO12: 118.46 | BP12: 121.31 | BQ12: 127.88 | BR12: 107.39 | BS12: 170.66 | BT12: 151.62 | BU12: 152.44 | BV12: 124.67 | BW12: 108.05 | BX12: 111.7 | BY12: 136.41 | BZ12: 113.55 | CA12: 128.29 | CB12: 144.04 | CC12: 116.29 | CD12: 101.31 | CE12: 99.97 | CF12: 123.32 | CG12: 115.95 | CH12: 134.28 | CI12: 123.24 | CJ12: 109.07 | CK12: 91.36 | CL12: 96.51 | CM12: 134.31 | CN12: 117.34 | CO12: 118.59 | CP12: 98.24 | CQ12: 137.51 | CR12: 89.06 | CS12: 119.93 | CT12: 109.69 | CU12: 159.49 | CV12: 116.84 | CW12: 88.11 | CX12: 139.51 | CY12: 102.6 | CZ12: 0 | DA12: 105.46 | DB12: 110.4 | DC12: 136.33 | DD12: 130.39 | DE12: 134.28 | DF12: 130.57 | DG12: 131.36 | DH12: 93.61 | DI12: 86.88 | DJ12: 144.64 | DK12: 119.55 | DL12: 84.74 | DM12: 106.26 | DN12: 92.3 | DO12: 110.38 | DP12: 137.45 | DQ12: 114.31 | DR12: 125.84 | DS12: 118.36 | DU12: 131.46 | DV12: 137.7 | DW12: 120.54 | DX12: 165.02 | DY12: 138.86 | DZ12: 106.89 | EA12: 113.65 | EB12: 124.9 | EC12: 141.87 | ED12: 146.04 | EE12: 129.67 | EF12: 124.12 | EG12: 134.08 | EH12: 133.81 | EI12: 144.36 | EJ12: 103.7 | EK12: 108.56 | EL12: 104.27 | EM12: 126.56 | EN12: 136.9 | EO12: 132.28 | EP12: 110.36 | EQ12: 123.45 | ER12: 128.66 | ES12: 144.05 | ET12: 124.53 | EU12: 108.61 | EV12: 106.68 | EW12: 125.72 | EX12: 102.07 | EY12: 111.79 | EZ12: 115.39 | FA12: 117.01 | FB12: 117.8 | FC12: 118.72 | FD12: 119.37 | FE12: 135.05 | FG12: 115.15 | FH12: 116.54 | FI12: 122.33 | FJ12: 88.41 | FK12: 129.16 | FL12: 99.29 | FM12: 104.02 | FN12: 88.47 | FO12: 131.89 | FP12: 62.13 | FQ12: 129.56 | FR12: 135.3 | FS12: 134.82 | FT12: 115.47 | FU12: 117.41 | FV12: 128.51 | FW12: 118.94 | FX12: 121.31 | FY12: 120.6 | FZ12: 128.59 | GA12: 127.41 | GB12: 103.7 | GC12: 107.53 | GD12: 113.39 | GE12: 170.66 | GF12: 151.62 | GG12: 152.44 | GH12: 124.81 | GI12: 108.22 | GJ12: 106.15 | GK12: 111.61 | GL12: 119.71 | GM12: 111.7 | GN12: 136.41 | GO12: 114.69 | GP12: 113.85 | GQ12: 109.98 | GR12: 128.29 | GS12: 144.04 | GT12: 116.29 | GU12: 101.31 | GV12: 99.97 | GW12: 121.78 | GX12: 124.12 | GY12: 115.95 | GZ12: 126.05 | HA12: 138.61 | HB12: 133.74 | HC12: 123.24 | HD12: 109.07 | HE12: 80.74 | HF12: 82.4 | HG12: 86.71 | HH12: 113.82 | HI12: 91.37 | HJ12: 96.51 | HK12: 134.31 | HL12: 113.71 | HM12: 124.89 | HN12: 118.93 | HO12: 113.52 | HP12: 123.45 | HQ12: 96.27 | HR12: 116.08 | HS12: 137.57 | HT12: 134.37 | HU12: 89.06 | HV12: 119.93 | HW12: 115.45 | HX12: 97.46 | HY12: 159.49 | HZ12: 116.84 | IA12: 83.5 | IB12: 139.51 | IC12: 0 | ID12: 102.6 | IE12: 0 | IF12: 105.46 | IG12: 110.4 | IH12: 136.33 | II12: 130.39 | IJ12: 134.28 | IK12: 131.55 | IL12: 127.66 | IM12: 133.93 | IN12: 123.97 | IO12: 124.26 | IP12: 93.61 | IQ12: 86.88 | IR12: 144.64 | IS12: 119.55 | IT12: 84.74 | IU12: 106.26 | IV12: 93.41 | IW12: 110.38 | IX12: 137.45 | IY12: 114.31 | IZ12: 125.84 | JA12: 118.36 | JC12: 131.46 | JD12: 137.7 | JE12: 120.02 | JF12: 120.69 | JG12: 165.02 | JH12: 138.86 | JI12: 106.89 | JJ12: 113.65 | JK12: 124.9 | JL12: 141.87 | JM12: 146.04 | JN12: 129.67 | JO12: 124.12 | JP12: 136.38 | JQ12: 128.67 | JR12: 131.56 | JS12: 136.32 | JT12: 149.05 | JU12: 139.7 | JV12: 103.7 | JW12: 108.56 | JX12: 104.27 | JY12: 127.49 | JZ12: 124.28 | KA12: 136.9 | KB12: 132.28 | KC12: 110.36 | KD12: 123.45 | KE12: 128.66 | KF12: 144.05
A13: 2005 | B13: Ağustos | C13: August | D13: 117.13 | E13: 108.77 | F13: 148.6 | G13: 104.36 | H13: 120.25 | I13: 113.93 | J13: 111.16 | K13: 125.9 | L13: 104.57 | M13: 123.04 | N13: 136.93 | O13: 134.86 | P13: 117.38 | Q13: 108.11 | R13: 118.28 | S13: 162.88 | T13: 147.54 | U13: 102.94 | V13: 108.45 | W13: 147.83 | X13: 116.19 | Y13: 103.21 | Z13: 114.22 | AA13: 131.56 | AB13: 109.02 | AC13: 98.19 | AD13: 117.38 | AE13: 118.82 | AF13: 106.52 | AG13: 88.41 | AH13: 130.9 | AI13: 140.6 | AJ13: 102.62 | AK13: 136.64 | AL13: 132.83 | AM13: 119.55 | AN13: 86.41 | AO13: 106.4 | AP13: 101.76 | AQ13: 115.26 | AR13: 124.62 | AS13: 136.98 | AT13: 120.29 | AU13: 129.68 | AV13: 142.69 | AW13: 147.33 | AX13: 129.67 | AY13: 126.44 | AZ13: 134.87 | BA13: 134.83 | BB13: 117.28 | BC13: 113.36 | BD13: 139.69 | BE13: 130.87 | BF13: 128.66 | BG13: 144.08 | BH13: 111.09 | BI13: 122.66 | BJ13: 133.86 | BK13: 111.72 | BL13: 104.79 | BM13: 84.64 | BN13: 92.96 | BO13: 118.91 | BP13: 121.91 | BQ13: 129.73 | BR13: 107.06 | BS13: 170.68 | BT13: 151.9 | BU13: 152.25 | BV13: 147.54 | BW13: 101.92 | BX13: 110.17 | BY13: 137.93 | BZ13: 108.29 | CA13: 129.38 | CB13: 147.83 | CC13: 116.19 | CD13: 102.27 | CE13: 99.97 | CF13: 123.78 | CG13: 115.86 | CH13: 133.68 | CI13: 122.72 | CJ13: 109.02 | CK13: 93.33 | CL13: 102.22 | CM13: 134.31 | CN13: 117.38 | CO13: 118.82 | CP13: 95.06 | CQ13: 138.79 | CR13: 84.86 | CS13: 120.51 | CT13: 107.95 | CU13: 160.95 | CV13: 117.55 | CW13: 88.31 | CX13: 140.6 | CY13: 102.7 | CZ13: 0 | DA13: 97.93 | DB13: 110.9 | DC13: 138.47 | DD13: 132.1 | DE13: 134.9 | DF13: 132.53 | DG13: 134.57 | DH13: 94.45 | DI13: 87.13 | DJ13: 147.95 | DK13: 119.55 | DL13: 86.41 | DM13: 106.4 | DN13: 92.82 | DO13: 106.82 | DP13: 133.34 | DQ13: 115.26 | DR13: 124.92 | DS13: 116.78 | DU13: 131.87 | DV13: 143.74 | DW13: 120.41 | DX13: 165.02 | DY13: 137.7 | DZ13: 105.75 | EA13: 114.01 | EB13: 129.68 | EC13: 142.69 | ED13: 147.33 | EE13: 129.67 | EF13: 126.44 | EG13: 134.87 | EH13: 134.83 | EI13: 146.22 | EJ13: 99.91 | EK13: 108.53 | EL13: 107.68 | EM13: 127.22 | EN13: 139.69 | EO13: 133.71 | EP13: 110.31 | EQ13: 129.64 | ER13: 128.66 | ES13: 144.08 | ET13: 124.84 | EU13: 108.65 | EV13: 106.99 | EW13: 126.48 | EX13: 102.32 | EY13: 111 | EZ13: 115.7 | FA13: 115.21 | FB13: 135.28 | FC13: 118.17 | FD13: 119.23 | FE13: 133.86 | FG13: 109.28 | FH13: 116.8 | FI13: 121.69 | FJ13: 89.79 | FK13: 127.87 | FL13: 99.69 | FM13: 103.78 | FN13: 76.89 | FO13: 131.55 | FP13: 66.65 | FQ13: 123.88 | FR13: 134.43 | FS13: 135.36 | FT13: 115.79 | FU13: 117.54 | FV13: 129.29 | FW13: 120.44 | FX13: 121.91 | FY13: 121.19 | FZ13: 130.59 | GA13: 128.25 | GB13: 102.77 | GC13: 107.58 | GD13: 112.22 | GE13: 170.68 | GF13: 151.9 | GG13: 152.25 | GH13: 147.26 | GI13: 102.79 | GJ13: 99.18 | GK13: 105.49 | GL13: 118.18 | GM13: 110.17 | GN13: 137.93 | GO13: 109.35 | GP13: 106.46 | GQ13: 108.73 | GR13: 129.38 | GS13: 147.83 | GT13: 116.19 | GU13: 102.27 | GV13: 99.97 | GW13: 121.84 | GX13: 124.81 | GY13: 115.86 | GZ13: 126.35 | HA13: 134.56 | HB13: 134.45 | HC13: 122.72 | HD13: 109.02 | HE13: 82.96 | HF13: 84.63 | HG13: 87.32 | HH13: 114.04 | HI13: 95.84 | HJ13: 102.22 | HK13: 134.31 | HL13: 113.85 | HM13: 125.28 | HN13: 118.81 | HO13: 113.41 | HP13: 124.01 | HQ13: 92.82 | HR13: 115.67 | HS13: 138.85 | HT13: 135.77 | HU13: 84.86 | HV13: 120.51 | HW13: 113.75 | HX13: 95.65 | HY13: 160.95 | HZ13: 117.55 | IA13: 83.68 | IB13: 140.6 | IC13: 0 | ID13: 102.7 | IE13: 0 | IF13: 97.93 | IG13: 110.9 | IH13: 138.47 | II13: 132.1 | IJ13: 134.9 | IK13: 134.42 | IL13: 127.42 | IM13: 137.74 | IN13: 124.16 | IO13: 126.28 | IP13: 94.45 | IQ13: 87.13 | IR13: 147.95 | IS13: 119.55 | IT13: 86.41 | IU13: 106.4 | IV13: 93.58 | IW13: 106.82 | IX13: 133.34 | IY13: 115.26 | IZ13: 124.92 | JA13: 116.78 | JC13: 131.87 | JD13: 143.74 | JE13: 119.24 | JF13: 120.81 | JG13: 165.02 | JH13: 137.7 | JI13: 105.75 | JJ13: 114.01 | JK13: 129.68 | JL13: 142.69 | JM13: 147.33 | JN13: 129.67 | JO13: 126.44 | JP13: 137.39 | JQ13: 128.96 | JR13: 132.9 | JS13: 136.91 | JT13: 150.65 | JU13: 141.8 | JV13: 99.91 | JW13: 108.53 | JX13: 107.68 | JY13: 128.37 | JZ13: 124.44 | KA13: 139.69 | KB13: 133.71 | KC13: 110.31 | KD13: 129.64 | KE13: 128.66 | KF13: 144.08
A14: 2005 | B14: Eylül | C14: September | D14: 118.33 | E14: 110.23 | F14: 148.6 | G14: 105.56 | H14: 122.41 | I14: 112.33 | J14: 111.36 | K14: 128.12 | L14: 105.13 | M14: 119.68 | N14: 140.37 | O14: 137.06 | P14: 119.31 | Q14: 109.6 | R14: 119.34 | S14: 162.83 | T14: 147.54 | U14: 103.08 | V14: 112.66 | W14: 151.3 | X14: 116.18 | Y14: 103.71 | Z14: 116.68 | AA14: 128.61 | AB14: 108.77 | AC14: 96.58 | AD14: 117.26 | AE14: 119 | AF14: 105.32 | AG14: 88.38 | AH14: 131.34 | AI14: 141.11 | AJ14: 102.4 | AK14: 140.9 | AL14: 135.09 | AM14: 119.55 | AN14: 91.02 | AO14: 106.48 | AP14: 99.43 | AQ14: 116.89 | AR14: 125.42 | AS14: 140.19 | AT14: 123.35 | AU14: 117.15 | AV14: 143.74 | AW14: 147.35 | AX14: 137.8 | AY14: 127.71 | AZ14: 135.85 | BA14: 138.56 | BB14: 117.31 | BC14: 117.08 | BD14: 146 | BE14: 132.18 | BF14: 128.66 | BG14: 144.15 | BH14: 111.41 | BI14: 120.13 | BJ14: 119.12 | BK14: 117.6 | BL14: 105.03 | BM14: 85.98 | BN14: 99.82 | BO14: 118.99 | BP14: 122.1 | BQ14: 130.47 | BR14: 108.39 | BS14: 170.77 | BT14: 151.71 | BU14: 152.01 | BV14: 147.54 | BW14: 102.06 | BX14: 110.27 | BY14: 140.17 | BZ14: 112.53 | CA14: 130.36 | CB14: 151.3 | CC14: 116.18 | CD14: 102.78 | CE14: 99.97 | CF14: 129.46 | CG14: 116.38 | CH14: 130.08 | CI14: 122.44 | CJ14: 108.77 | CK14: 91.56 | CL14: 101.06 | CM14: 134.31 | CN14: 117.26 | CO14: 119 | CP14: 93.12 | CQ14: 140.03 | CR14: 84.9 | CS14: 120.31 | CT14: 107.44 | CU14: 161.85 | CV14: 117.37 | CW14: 88.45 | CX14: 141.11 | CY14: 102.36 | CZ14: 0 | DA14: 103.25 | DB14: 110.8 | DC14: 143.28 | DD14: 133.76 | DE14: 136.47 | DF14: 132.93 | DG14: 137.09 | DH14: 92.08 | DI14: 87.38 | DJ14: 151.56 | DK14: 119.55 | DL14: 91.02 | DM14: 106.48 | DN14: 91.25 | DO14: 99.89 | DP14: 129.63 | DQ14: 116.89 | DR14: 125.85 | DS14: 116.79 | DU14: 133.09 | DV14: 152.7 | DW14: 120.69 | DX14: 165.02 | DY14: 146.27 | DZ14: 105.75 | EA14: 113.9 | EB14: 117.15 | EC14: 143.74 | ED14: 147.35 | EE14: 137.8 | EF14: 127.71 | EG14: 135.85 | EH14: 138.56 | EI14: 147.43 | EJ14: 100.94 | EK14: 108.21 | EL14: 111.32 | EM14: 131.15 | EN14: 146 | EO14: 136.82 | EP14: 110.36 | EQ14: 129.68 | ER14: 128.66 | ES14: 144.15 | ET14: 126.13 | EU14: 108.58 | EV14: 107.24 | EW14: 126.64 | EX14: 103.59 | EY14: 111.07 | EZ14: 116.21 | FA14: 114.57 | FB14: 126.29 | FC14: 118.35 | FD14: 120.09 | FE14: 119.12 | FG14: 107.74 | FH14: 117.6 | FI14: 122.23 | FJ14: 120.88 | FK14: 127.96 | FL14: 100.65 | FM14: 103.85 | FN14: 78.22 | FO14: 132.82 | FP14: 78.6 | FQ14: 118.18 | FR14: 133.58 | FS14: 136.76 | FT14: 115.98 | FU14: 116.45 | FV14: 129.84 | FW14: 121.27 | FX14: 122.1 | FY14: 122.34 | FZ14: 131.3 | GA14: 128.07 | GB14: 105.15 | GC14: 108.82 | GD14: 112.09 | GE14: 170.77 | GF14: 151.71 | GG14: 152.01 | GH14: 147.26 | GI14: 101.07 | GJ14: 100.33 | GK14: 107.93 | GL14: 118.4 | GM14: 110.27 | GN14: 140.17 | GO14: 113.01 | GP14: 110.68 | GQ14: 114.38 | GR14: 130.36 | GS14: 151.3 | GT14: 116.18 | GU14: 102.78 | GV14: 99.97 | GW14: 127.23 | GX14: 130.65 | GY14: 116.38 | GZ14: 127.04 | HA14: 132.14 | HB14: 129.61 | HC14: 122.44 | HD14: 108.77 | HE14: 81.19 | HF14: 82.52 | HG14: 85.7 | HH14: 114.18 | HI14: 91.59 | HJ14: 101.06 | HK14: 134.31 | HL14: 113.74 | HM14: 125.05 | HN14: 118.71 | HO14: 113.22 | HP14: 124.56 | HQ14: 90.72 | HR14: 115.4 | HS14: 140.1 | HT14: 136.71 | HU14: 84.9 | HV14: 120.31 | HW14: 113.42 | HX14: 94.74 | HY14: 161.85 | HZ14: 117.37 | IA14: 83.71 | IB14: 141.11 | IC14: 0 | ID14: 102.36 | IE14: 0 | IF14: 103.25 | IG14: 110.8 | IH14: 143.28 | II14: 133.76 | IJ14: 136.47 | IK14: 134.99 | IL14: 127.42 | IM14: 140.86 | IN14: 127.19 | IO14: 126.35 | IP14: 92.08 | IQ14: 87.38 | IR14: 151.56 | IS14: 119.55 | IT14: 91.02 | IU14: 106.48 | IV14: 91.6 | IW14: 99.89 | IX14: 129.63 | IY14: 116.89 | IZ14: 125.85 | JA14: 116.79 | JC14: 133.09 | JD14: 152.7 | JE14: 119.76 | JF14: 121 | JG14: 165.02 | JH14: 146.27 | JI14: 105.75 | JJ14: 113.9 | JK14: 117.15 | JL14: 143.74 | JM14: 147.35 | JN14: 137.8 | JO14: 127.71 | JP14: 138.81 | JQ14: 128.98 | JR14: 133.14 | JS14: 145.51 | JT14: 152.15 | JU14: 142.75 | JV14: 100.94 | JW14: 108.21 | JX14: 111.32 | JY14: 133.34 | JZ14: 125.86 | KA14: 146 | KB14: 136.82 | KC14: 110.36 | KD14: 129.68 | KE14: 128.66 | KF14: 144.15
